Workbook
Name UPDATE: 'Data Sheet'!$E$1

Sheet Profit & Loss
A1: ='Data Sheet'!B1 -> ITC LTD | H1: =UPDATE
A3: Narration | B3: ='Data Sheet'!B16 -> 42460 | C3: ='Data Sheet'!C16 -> 42825 | D3: ='Data Sheet'!D16 -> 43190 | E3: ='Data Sheet'!E16 -> 43555 | F3: ='Data Sheet'!F16 -> 43921 | G3: ='Data Sheet'!G16 -> 44286 | H3: ='Data Sheet'!H16 -> 44651 | I3: ='Data Sheet'!I16 -> 45016 | ... K3: ='Data Sheet'!K16 -> 45747 | L3: Trailing | M3: Best Case | N3: Worst Case
A4: Sales | B4: ='Data Sheet'!B17 -> 39192.1 | C4: ='Data Sheet'!C17 -> 42767.6 | D4: ='Data Sheet'!D17 -> 43448.94 | E4: ='Data Sheet'!E17 -> 48339.58 | F4: ='Data Sheet'!F17 -> 49387.7 | G4: ='Data Sheet'!G17 -> 49257.45 | H4: ='Data Sheet'!H17 -> 60644.54 | I4: ='Data Sheet'!I17 -> 70919.03 | ... K4: ='Data Sheet'!K17 -> 75323.34 | L4: =SUM(Quarters!H4:K4) -> 79040.32 | M4: =$K4+M23*K4 -> 83518.968 | N4: =$K4+N23*L4 -> 81245.656
A5: Expenses | B5: =SUM('Data Sheet'!B18,'Data Sheet'!B20:B24, -1*'Data Sheet'!B19) -> 24660.61 | C5: =SUM('Data Sheet'!C18,'Data Sheet'!C20:C24, -1*'Data Sheet'!C19) -> 27298.09 | D5: =SUM('Data Sheet'!D18,'Data Sheet'!D20:D24, -1*'Data Sheet'!D19) -> 26928.35 | E5: =SUM('Data Sheet'!E18,'Data Sheet'!E20:E24, -1*'Data Sheet'!E19) -> 29802.19 | F5: =SUM('Data Sheet'!F18,'Data Sheet'!F20:F24, -1*'Data Sheet'!F19) -> 30044.16 | G5: =SUM('Data Sheet'!G18,'Data Sheet'!G20:G24, -1*'Data Sheet'!G19) -> 32192.67 | H5: =SUM('Data Sheet'!H18,'Data Sheet'!H20:H24, -1*'Data Sheet'!H19) -> 40021.39 | I5: =SUM('Data Sheet'!I18,'Data Sheet'!I20:I24, -1*'Data Sheet'!I19) -> 45214.77 | ... K5: =SUM('Data Sheet'!K18,'Data Sheet'!K20:K24, -1*'Data Sheet'!K19) -> 49483.89 | L5: =SUM(Quarters!H5:K5) -> 52790.48 | M5: =M4-M6 -> 53597.014 | N5: =N4-N6 -> 54263.409
A6: Operating Profit | B6: =B4-B5 -> 14531.49 | C6: =C4-C5 -> 15469.51 | D6: =D4-D5 -> 16520.59 | E6: =E4-E5 -> 18537.39 | F6: =F4-F5 -> 19343.54 | G6: =G4-G5 -> 17064.78 | H6: =H4-H5 -> 20623.15 | I6: =I4-I5 -> 25704.26 | ... K6: =K4-K5 -> 25839.45 | L6: =SUM(Quarters!H6:K6) -> 26249.84 | M6: =M4*M24 -> 29921.955 | N6: =N4*N24 -> 26982.247
A7: Other Income | B7: ='Data Sheet'!B25 -> 1483.11 | C7: ='Data Sheet'!C25 -> 1758.63 | D7: ='Data Sheet'!D25 -> 2239.81 | E7: ='Data Sheet'!E25 -> 2080.44 | F7: ='Data Sheet'!F25 -> 2417.32 | G7: ='Data Sheet'!G25 -> 2576.95 | H7: ='Data Sheet'!H25 -> 1909.72 | I7: ='Data Sheet'!I25 -> 2097.64 | ... K7: ='Data Sheet'!K25 -> 17794.88 | L7: =SUM(Quarters!H7:K7) -> 17635.96 | M7: 0 | N7: 0
A8: Depreciation | B8: ='Data Sheet'!B26 -> 1077.4 | C8: ='Data Sheet'!C26 -> 1152.79 | D8: ='Data Sheet'!D26 -> 1236.28 | E8: ='Data Sheet'!E26 -> 1396.61 | F8: ='Data Sheet'!F26 -> 1644.91 | G8: ='Data Sheet'!G26 -> 1645.59 | H8: ='Data Sheet'!H26 -> 1732.41 | I8: ='Data Sheet'!I26 -> 1809.01 | ... K8: ='Data Sheet'!K26 -> 1646.32 | L8: =SUM(Quarters!H8:K8) -> 1666.15 | M8: =+$L8 -> 1666.15 | N8: =+$L8 -> 1666.15
A9: Interest | B9: ='Data Sheet'!B27 -> 78.13 | C9: ='Data Sheet'!C27 -> 49.03 | D9: ='Data Sheet'!D27 -> 115.01 | E9: ='Data Sheet'!E27 -> 71.4 | F9: ='Data Sheet'!F27 -> 81.38 | G9: ='Data Sheet'!G27 -> 57.97 | H9: ='Data Sheet'!H27 -> 59.99 | I9: ='Data Sheet'!I27 -> 77.77 | ... K9: ='Data Sheet'!K27 -> 45.06 | L9: =SUM(Quarters!H9:K9) -> 51.93 | M9: =+$L9 -> 51.93 | N9: =+$L9 -> 51.93
A10: Profit before tax | B10: ='Data Sheet'!B28 -> 14859.07 | C10: ='Data Sheet'!C28 -> 16026.32 | D10: ='Data Sheet'!D28 -> 17409.11 | E10: ='Data Sheet'!E28 -> 19149.82 | F10: ='Data Sheet'!F28 -> 20034.57 | G10: ='Data Sheet'!G28 -> 17938.17 | H10: ='Data Sheet'!H28 -> 20740.47 | I10: ='Data Sheet'!I28 -> 25915.12 | ... K10: ='Data Sheet'!K28 -> 41942.95 | L10: =SUM(Quarters!H10:K10) -> 42167.72 | M10: =M6+M7-SUM(M8:M9) -> 28203.875 | N10: =N6+N7-SUM(N8:N9) -> 25264.167
A11: Tax | B11: ='Data Sheet'!B29 -> 5358.21 | C11: ='Data Sheet'!C29 -> 5549.09 | D11: ='Data Sheet'!D29 -> 5916.43 | E11: ='Data Sheet'!E29 -> 6313.92 | F11: ='Data Sheet'!F29 -> 4441.79 | G11: ='Data Sheet'!G29 -> 4555.29 | H11: ='Data Sheet'!H29 -> 5237.34 | I11: ='Data Sheet'!I29 -> 6438.4 | ... K11: ='Data Sheet'!K29 -> 6890.47 | L11: =SUM(Quarters!H11:K11) -> 6948.82 | M11: =IF($L10>0,$L11/$L10,0) -> 0.16479003 | N11: =IF($L10>0,$L11/$L10,0) -> 0.16479003
A12: Net profit | B12: ='Data Sheet'!B30 -> 9344.45 | C12: ='Data Sheet'!C30 -> 10289.44 | D12: ='Data Sheet'!D30 -> 11271.2 | E12: ='Data Sheet'!E30 -> 12592.33 | F12: ='Data Sheet'!F30 -> 15306.23 | G12: ='Data Sheet'!G30 -> 13161.19 | H12: ='Data Sheet'!H30 -> 15242.66 | I12: ='Data Sheet'!I30 -> 19191.66 | ... K12: ='Data Sheet'!K30 -> 34746.63 | L12: =SUM(Quarters!H12:K12) -> 34899.24 | M12: =M10-M11*M10 -> 23556.157 | N12: =N10-N11*N10 -> 21100.884
A13: EPS | B13: =IF('Data Sheet'!B93>0,B12/'Data Sheet'!B93,0) -> 7.7413676 | C13: =IF('Data Sheet'!C93>0,C12/'Data Sheet'!C93,0) -> 8.4704875 | D13: =IF('Data Sheet'!D93>0,D12/'Data Sheet'!D93,0) -> 9.2354334 | E13: =IF('Data Sheet'!E93>0,E12/'Data Sheet'!E93,0) -> 10.272242 | F13: =IF('Data Sheet'!F93>0,F12/'Data Sheet'!F93,0) -> 12.451986 | G13: =IF('Data Sheet'!G93>0,G12/'Data Sheet'!G93,0) -> 10.692505 | H13: =IF('Data Sheet'!H93>0,H12/'Data Sheet'!H93,0) -> 12.368976 | I13: =IF('Data Sheet'!I93>0,I12/'Data Sheet'!I93,0) -> 15.442276 | ... K13: =IF('Data Sheet'!K93>0,K12/'Data Sheet'!K93,0) -> 27.765984 | L13: =IF('Data Sheet'!$B6>0,'Profit & Loss'!L12/'Data Sheet'!$B6,0) -> 27.85661 | M13: =IF('Data Sheet'!$B6>0,'Profit & Loss'!M12/'Data Sheet'!$B6,0) -> 18.802549 | N13: =IF('Data Sheet'!$B6>0,'Profit & Loss'!N12/'Data Sheet'!$B6,0) -> 16.842748
A14: Price to earning | B14: =IF(B15>0,B15/B13,"") -> 26.497902 | C14: =IF(C15>0,C15/C13,"") -> 31.019466 | D14: =IF(D15>0,D15/D13,"") -> 25.93273 | E14: =IF(E15>0,E15/E13,"") -> 27.12553 | F14: =IF(F15>0,F15/F13,"") -> 12.925649 | G14: =IF(G15>0,G15/G13,"") -> 19.155475 | H14: =IF(H15>0,H15/H13,"") -> 18.995914 | I14: =IF(I15>0,I15/I13,"") -> 23.2796 | ... K14: =IF(K15>0,K15/K13,"") -> 14.757266 | L14: =IF(L13>0,L15/L13,0) -> 14.852848 | M14: =M25 -> 19.348138 | N14: =N25 -> 14.852848
A15: Price | B15: ='Data Sheet'!B90 -> 205.13 | C15: ='Data Sheet'!C90 -> 262.75 | D15: ='Data Sheet'!D90 -> 239.5 | E15: ='Data Sheet'!E90 -> 278.64 | F15: ='Data Sheet'!F90 -> 160.95 | G15: ='Data Sheet'!G90 -> 204.82 | H15: ='Data Sheet'!H90 -> 234.96 | I15: ='Data Sheet'!I90 -> 359.49 | ... K15: ='Data Sheet'!K90 -> 409.75 | L15: ='Data Sheet'!B8 -> 413.75 | M15: =M13*M14 -> 363.79432 | N15: =N13*N14 -> 250.16278
A17: RATIOS:
A18: Dividend Payout | B18: =IF('Data Sheet'!B30>0, 'Data Sheet'!B31/'Data Sheet'!B30, 0) -> 0.73199814 | C18: =IF('Data Sheet'!C30>0, 'Data Sheet'!C31/'Data Sheet'!C30, 0) -> 0.56077104 | D18: =IF('Data Sheet'!D30>0, 'Data Sheet'!D31/'Data Sheet'!D30, 0) -> 0.5576345 | E18: =IF('Data Sheet'!E30>0, 'Data Sheet'!E31/'Data Sheet'!E30, 0) -> 0.55976138 | F18: =IF('Data Sheet'!F30>0, 'Data Sheet'!F31/'Data Sheet'!F30, 0) -> 0.81513083 | G18: =IF('Data Sheet'!G30>0, 'Data Sheet'!G31/'Data Sheet'!G30, 0) -> 1.0053772 | H18: =IF('Data Sheet'!H30>0, 'Data Sheet'!H31/'Data Sheet'!H30, 0) -> 0.92974586 | I18: =IF('Data Sheet'!I30>0, 'Data Sheet'!I31/'Data Sheet'!I30, 0) -> 1.0037381 | ... K18: =IF('Data Sheet'!K30>0, 'Data Sheet'!K31/'Data Sheet'!K30, 0) -> 0.51681933
A19: OPM | B19: =IF(B6>0,B6/B4,0) -> 0.370776 | C19: =IF(C6>0,C6/C4,0) -> 0.36171097 | D19: =IF(D6>0,D6/D4,0) -> 0.38022999 | E19: =IF(E6>0,E6/E4,0) -> 0.38348265 | F19: =IF(F6>0,F6/F4,0) -> 0.39166716 | G19: =IF(G6>0,G6/G4,0) -> 0.34644059 | H19: =IF(H6>0,H6/H4,0) -> 0.34006606 | I19: =IF(I6>0,I6/I4,0) -> 0.36244517 | ... L19: =IF(L6>0,L6/L4,0) -> 0.33210696
G22: TRENDS: | H22: 10 YEARS | I22: 7 YEARS | J22: 5 YEARS | K22: 3 YEARS | L22: RECENT | M22: BEST | N22: WORST
G23: Sales Growth | H23: =IF(B4=0,"",POWER($K4/B4,1/9)-1) -> 0.075290157 | I23: =IF(D4=0,"",POWER($K4/D4,1/7)-1) -> 0.081772082 | J23: =IF(F4=0,"",POWER($K4/F4,1/5)-1) -> 0.088083322 | K23: =IF(H4=0,"",POWER($K4/H4, 1/3)-1) -> 0.074927782 | L23: =IF(ISERROR(MAX(IF(J4=0,"",(K4-J4)/J4),IF(K4=0,"",(L4-K4)/K4))),"",MAX(IF(J4=0,"",(K4-J4)/J4),IF(K4=0,"",(L4-K4)/K4))) -> 0.10880596 | M23: =MAX(K23:L23) -> 0.10880596 | N23: =MIN(H23:L23) -> 0.074927782
G24: OPM | H24: =IF(SUM(B4:$K$4)=0,"",SUMPRODUCT(B19:$K$19,B4:$K$4)/SUM(B4:$K$4)) -> 0.36333562 | I24: =IF(SUM(E4:$K$4)=0,"",SUMPRODUCT(E19:$K$19,E4:$K$4)/SUM(E4:$K$4)) -> 0.36106877 | J24: =IF(SUM(G4:$K$4)=0,"",SUMPRODUCT(G19:$K$19,G4:$K$4)/SUM(G4:$K$4)) -> 0.35306244 | K24: =IF(SUM(I4:$K$4)=0, "", SUMPRODUCT(I19:$K$19,I4:$K$4)/SUM(I4:$K$4)) -> 0.35826538 | L24: =L19 -> 0.33210696 | M24: =MAX(K24:L24) -> 0.35826538 | N24: =MIN(H24:L24) -> 0.33210696
G25: Price to Earning | H25: =IF(ISERROR(AVERAGEIF(B14:$L14,">0")),"",AVERAGEIF(B14:$L14,">0")) -> 21.731383 | I25: =IF(ISERROR(AVERAGEIF(E14:$L14,">0")),"",AVERAGEIF(E14:$L14,">0")) -> 19.44939 | J25: =IF(ISERROR(AVERAGEIF(G14:$L14,">0")),"",AVERAGEIF(G14:$L14,">0")) -> 19.257323 | K25: =IF(ISERROR(AVERAGEIF(I14:$L14,">0")),"",AVERAGEIF(I14:$L14,">0")) -> 19.348138 | L25: =L14 -> 14.852848 | M25: =MAX(K25:L25) -> 19.348138 | N25: =MIN(H25:L25) -> 14.852848

Sheet Historical Financial Statemen
B3: ="Historical Financial Statement - "&'Balance Sheet'!A1 -> Historical Financial Statement - ITC LTD
B4: Years | C4: ='Balance Sheet'!B3 -> 42460 | D4: ='Balance Sheet'!C3 -> 42825 | E4: ='Balance Sheet'!D3 -> 43190 | F4: ='Balance Sheet'!E3 -> 43555 | G4: ='Balance Sheet'!F3 -> 43921 | H4: ='Balance Sheet'!G3 -> 44286 | I4: ='Balance Sheet'!H3 -> 44651 | J4: ='Balance Sheet'!I3 -> 45016 | ... L4: ='Balance Sheet'!K3 -> 45747 | M4: LTM
B6: Income Statement
B7: Sales | C7: =IFERROR('Data Sheet'!B17,0) -> 39192.1 | D7: =IFERROR('Data Sheet'!C17,0) -> 42767.6 | E7: =IFERROR('Data Sheet'!D17,0) -> 43448.94 | F7: =IFERROR('Data Sheet'!E17,0) -> 48339.58 | G7: =IFERROR('Data Sheet'!F17,0) -> 49387.7 | H7: =IFERROR('Data Sheet'!G17,0) -> 49257.45 | I7: =IFERROR('Data Sheet'!H17,0) -> 60644.54 | J7: =IFERROR('Data Sheet'!I17,0) -> 70919.03 | ... L7: =IFERROR('Data Sheet'!K17,0) -> 75323.34 | M7: =IFERROR(SUM(Quarters!J4:K4),0) -> 40259.79
B8: Sales Growth | F8: - | G8: =(G7-F7)/F7 -> 0.021682439 | H8: =(H7-G7)/G7 -> -0.0026372963 | I8: =(I7-H7)/H7 -> 0.23117498 | J8: =(J7-I7)/I7 -> 0.16942152 | K8: =(K7-J7)/J7 -> -0.042119724 | L8: =(L7-K7)/K7 -> 0.10880596 | M8: =(M7-L7)/L7 -> -0.46550711
B10: COGS | C10: =IFERROR(SUM('Data Sheet'!B18:B23),0) -> 23815.48 | D10: =IFERROR(SUM('Data Sheet'!C18:C23),0) -> 24943.72 | E10: =IFERROR(SUM('Data Sheet'!D18:D23),0) -> 23866.85 | F10: =IFERROR(SUM('Data Sheet'!E18:E23),0) -> 29168.72 | G10: =IFERROR(SUM('Data Sheet'!F18:F23),0) -> 30225.29 | H10: =IFERROR(SUM('Data Sheet'!G18:G23),0) -> 32408.82 | I10: =IFERROR(SUM('Data Sheet'!H18:H23),0) -> 40283.44 | J10: =IFERROR(SUM('Data Sheet'!I18:I23),0) -> 44623.39 | ... L10: =IFERROR(SUM('Data Sheet'!K18:K23),0) -> 48713.8 | M10: =IFERROR(Quarters!D5,0) -> 11320.23
B11: COGS % Sales | C11: =C10/C7 -> 0.60766022 | D11: =D10/D7 -> 0.58323871 | E11: =E10/E7 -> 0.54930799 | F11: =F10/F7 -> 0.60341277 | G11: =G10/G7 -> 0.61200036 | H11: =H10/H7 -> 0.65794758 | I11: =I10/I7 -> 0.66425502 | J11: =J10/J7 -> 0.62921602 | ... M11: =M10/M7 -> 0.28117956
B13: Gross Profit | C13: =C7-C10 -> 15376.62 | D13: =D7-D10 -> 17823.88 | E13: =E7-E10 -> 19582.09 | F13: =F7-F10 -> 19170.86 | G13: =G7-G10 -> 19162.41 | H13: =H7-H10 -> 16848.63 | I13: =I7-I10 -> 20361.1 | J13: =J7-J10 -> 26295.64 | ... M13: =M7-M10 -> 28939.56
B14: Gross Profit % Sales | C14: =C13/C7 -> 0.39233978 | D14: =D13/D7 -> 0.41676129 | E14: =E13/E7 -> 0.45069201 | F14: =F13/F7 -> 0.39658723 | G14: =G13/G7 -> 0.38799964 | H14: =H13/H7 -> 0.34205242 | I14: =I13/I7 -> 0.33574498 | J14: =J13/J7 -> 0.37078398 | ... M14: =M13/M7 -> 0.71882044
B16: Sales &General Expenses | C16: =IFERROR(SUM('Data Sheet'!B24:B25),0) -> 2719 | D16: =IFERROR(SUM('Data Sheet'!C24:C25),0) -> 2927.86 | E16: =IFERROR(SUM('Data Sheet'!D24:D25),0) -> 3245.79 | F16: =IFERROR(SUM('Data Sheet'!E24:E25),0) -> 3120.29 | G16: =IFERROR(SUM('Data Sheet'!F24:F25),0) -> 3642.45 | H16: =IFERROR(SUM('Data Sheet'!G24:G25),0) -> 3651.34 | I16: =IFERROR(SUM('Data Sheet'!H24:H25),0) -> 3019.67 | J16: =IFERROR(SUM('Data Sheet'!I24:I25),0) -> 3406.2 | ... M16: =IFERROR(SUM('Data Sheet'!L24:L25),0) -> 0
B17: S&G Exp % Sales | C17: =C16/C7 -> 0.069376226 | D17: =D16/D7 -> 0.068459769 | E17: =E16/E7 -> 0.074703549 | F17: =F16/F7 -> 0.064549382 | G17: =G16/G7 -> 0.073752169 | H17: =H16/H7 -> 0.07412767 | I17: =I16/I7 -> 0.049792941 | J17: =J16/J7 -> 0.048029422 | ... M17: =M16/M7 -> 0
B19: EBITDA | C19: =C13-C16 -> 12657.62 | D19: =D13-D16 -> 14896.02 | E19: =E13-E16 -> 16336.3 | F19: =F13-F16 -> 16050.57 | G19: =G13-G16 -> 15519.96 | H19: =H13-H16 -> 13197.29 | I19: =I13-I16 -> 17341.43 | J19: =J13-J16 -> 22889.44 | ... M19: =M13-M16 -> 28939.56
B20: EBITDA Margins | C20: =C19/C7 -> 0.32296356 | D20: =D19/D7 -> 0.34830152 | E20: =E19/E7 -> 0.37598846 | F20: =F19/F7 -> 0.33203785 | G20: =G19/G7 -> 0.31424747 | H20: =H19/H7 -> 0.26792475 | I20: =I19/I7 -> 0.28595204 | J20: =J19/J7 -> 0.32275456 | ... M20: =M19/M7 -> 0.71882044
B22: Interest | C22: =IFERROR('Data Sheet'!B27,0) -> 78.13 | D22: =IFERROR('Data Sheet'!C27,0) -> 49.03 | E22: =IFERROR('Data Sheet'!D27,0) -> 115.01 | F22: =IFERROR('Data Sheet'!E27,0) -> 71.4 | G22: =IFERROR('Data Sheet'!F27,0) -> 81.38 | H22: =IFERROR('Data Sheet'!G27,0) -> 57.97 | I22: =IFERROR('Data Sheet'!H27,0) -> 59.99 | J22: =IFERROR('Data Sheet'!I27,0) -> 77.77 | ... L22: =IFERROR('Data Sheet'!K27,0) -> 45.06 | M22: =IFERROR(Quarters!J9+N11,0) -> 10.91
B23: Int. % Sales | C23: =C22/C7 -> 0.001993514 | D23: =D22/D7 -> 0.0011464286 | E23: =E22/E7 -> 0.0026470151 | F23: =F22/F7 -> 0.0014770505 | G23: =G22/G7 -> 0.0016477787 | H23: =H22/H7 -> 0.0011768778 | I23: =I22/I7 -> 0.00098920694 | J23: =J22/J7 -> 0.0010966027 | ... M23: =M22/M7 -> 0.00027098999
B25: Depreciation | C25: =IFERROR('Data Sheet'!B26,0) -> 1077.4 | D25: =IFERROR('Data Sheet'!C26,0) -> 1152.79 | E25: =IFERROR('Data Sheet'!D26,0) -> 1236.28 | F25: =IFERROR('Data Sheet'!E26,0) -> 1396.61 | G25: =IFERROR('Data Sheet'!F26,0) -> 1644.91 | H25: =IFERROR('Data Sheet'!G26,0) -> 1645.59 | I25: =IFERROR('Data Sheet'!H26,0) -> 1732.41 | J25: =IFERROR('Data Sheet'!I26,0) -> 1809.01 | ... L25: =IFERROR('Data Sheet'!K26,0) -> 1646.32 | M25: =IFERROR(Quarters!J8+N10,0) -> 411.03
B26: Dep. % Sales | C26: =C25/C7 -> 0.027490234 | D26: =D25/D7 -> 0.026954751 | E26: =E25/E7 -> 0.028453629 | F26: =F25/F7 -> 0.028891645 | G26: =G25/G7 -> 0.033306066 | H26: =H25/H7 -> 0.033407941 | I26: =I25/I7 -> 0.028566628 | J26: =J25/J7 -> 0.025508104 | ... M26: =M25/M7 -> 0.010209442
B28: Other Income | C28: =IFERROR('Data Sheet'!B25,0) -> 1483.11 | D28: =IFERROR('Data Sheet'!C25,0) -> 1758.63 | E28: =IFERROR('Data Sheet'!D25,0) -> 2239.81 | F28: =IFERROR('Data Sheet'!E25,0) -> 2080.44 | G28: =IFERROR('Data Sheet'!F25,0) -> 2417.32 | H28: =IFERROR('Data Sheet'!G25,0) -> 2576.95 | I28: =IFERROR('Data Sheet'!H25,0) -> 1909.72 | J28: =IFERROR('Data Sheet'!I25,0) -> 2097.64 | ... L28: =IFERROR('Data Sheet'!K25,0) -> 17794.88 | M28: =IFERROR(Quarters!J7+N9,0) -> 15391.28
B30: Earning Before Tax | C30: =C19+C28-C25-C22 -> 12985.2 | D30: =D19+D28-D25-D22 -> 15452.83 | E30: =E19+E28-E25-E22 -> 17224.82 | F30: =F19+F28-F25-F22 -> 16663 | G30: =G19+G28-G25-G22 -> 16210.99 | H30: =H19+H28-H25-H22 -> 14070.68 | I30: =I19+I28-I25-I22 -> 17458.75 | J30: =J19+J28-J25-J22 -> 23100.3 | ... M30: =M19+M28-M25-M22 -> 43908.9
B31: EBT % Sales | C31: =C30/C7 -> 0.33132187 | D31: =D30/D7 -> 0.36132095 | E31: =E30/E7 -> 0.39643821 | F31: =F30/F7 -> 0.34470717 | G31: =G30/G7 -> 0.32823942 | H31: =H30/H7 -> 0.28565588 | I31: =I30/I7 -> 0.28788659 | J31: =J30/J7 -> 0.32572781 | ... M31: =M30/M7 -> 1.0906391
B34: Tax | C34: =IFERROR('Data Sheet'!B29,0) -> 5358.21 | D34: =IFERROR('Data Sheet'!C29,0) -> 5549.09 | E34: =IFERROR('Data Sheet'!D29,0) -> 5916.43 | F34: =IFERROR('Data Sheet'!E29,0) -> 6313.92 | G34: =IFERROR('Data Sheet'!F29,0) -> 4441.79 | H34: =IFERROR('Data Sheet'!G29,0) -> 4555.29 | I34: =IFERROR('Data Sheet'!H29,0) -> 5237.34 | J34: =IFERROR('Data Sheet'!I29,0) -> 6438.4 | ... L34: =IFERROR('Data Sheet'!K29,0) -> 6890.47 | M34: =IFERROR(Quarters!J11+N13,0) -> 1680.85
B35: Effective Tax Rate | C35: =C34/C30 -> 0.41263977 | D35: =D34/D30 -> 0.35909862 | E35: =E34/E30 -> 0.34348283 | F35: =F34/F30 -> 0.37891856 | G35: =G34/G30 -> 0.27399869 | H35: =H34/H30 -> 0.32374342 | I35: =I34/I30 -> 0.29998368 | J35: =J34/J30 -> 0.278715 | ... M35: =M34/M30 -> 0.038280394
B37: Net Profit | C37: =C30-C34 -> 7626.99 | D37: =D30-D34 -> 9903.74 | E37: =E30-E34 -> 11308.39 | F37: =F30-F34 -> 10349.08 | G37: =G30-G34 -> 11769.2 | H37: =H30-H34 -> 9515.39 | I37: =I30-I34 -> 12221.41 | J37: =J30-J34 -> 16661.9 | ... M37: =M30-M34 -> 42228.05
B38: Proift Margin | C38: =C37/C7 -> 0.19460529 | D38: =D37/D7 -> 0.2315711 | E38: =E37/E7 -> 0.26026849 | F38: =F37/F7 -> 0.21409123 | G38: =G37/G7 -> 0.23830225 | H38: =H37/H7 -> 0.19317667 | I38: =I37/I7 -> 0.20152531 | J38: =J37/J7 -> 0.23494258 | ... M38: =M37/M7 -> 1.048889
B40: No. of Equity Shares | C40: =IFERROR( 'Data Sheet'!B93,0) -> 1207.08 | D40: =IFERROR( 'Data Sheet'!C93,0) -> 1214.74 | E40: =IFERROR( 'Data Sheet'!D93,0) -> 1220.43 | F40: =IFERROR( 'Data Sheet'!E93,0) -> 1225.86 | G40: =IFERROR( 'Data Sheet'!F93,0) -> 1229.22 | H40: =IFERROR( 'Data Sheet'!G93,0) -> 1230.88 | I40: =IFERROR( 'Data Sheet'!H93,0) -> 1232.33 | J40: =IFERROR( 'Data Sheet'!I93,0) -> 1242.8 | ... L40: =IFERROR( 'Data Sheet'!K93,0) -> 1251.41 | M40: =IFERROR( L40,0) -> 1251.41
B42: Earning Per Share | C42: =C37/C40 -> 6.3185456 | D42: =D37/D40 -> 8.152971 | E42: =E37/E40 -> 9.2659063 | F42: =F37/F40 -> 8.4423017 | G42: =G37/G40 -> 9.5745269 | H42: =H37/H40 -> 7.7305586 | I42: =I37/I40 -> 9.9173192 | J42: =J37/J40 -> 13.406743 | ... M42: =M37/M40 -> 33.744376
B44: Dividend Per Sharing | C44: =IFERROR('Data Sheet'!B31/'Data Sheet'!B93,0) -> 5.6666667 | D44: =IFERROR('Data Sheet'!C31/'Data Sheet'!C93,0) -> 4.7500041 | E44: =IFERROR('Data Sheet'!D31/'Data Sheet'!D93,0) -> 5.1499963 | F44: =IFERROR('Data Sheet'!E31/'Data Sheet'!E93,0) -> 5.7500041 | G44: =IFERROR('Data Sheet'!F31/'Data Sheet'!F93,0) -> 10.149998 | H44: =IFERROR('Data Sheet'!G31/'Data Sheet'!G93,0) -> 10.75 | I44: =IFERROR('Data Sheet'!H31/'Data Sheet'!H93,0) -> 11.500004 | J44: =IFERROR('Data Sheet'!I31/'Data Sheet'!I93,0) -> 15.5 | ... L44: =IFERROR('Data Sheet'!K31/'Data Sheet'!K93,0) -> 14.349997 | M44: -
B45: Dividend Payout Ratio | C45: =C44/C42 -> 0.89683086 | D45: =D44/D42 -> 0.58261021 | E45: =E44/E42 -> 0.5558006 | F45: =F44/F42 -> 0.68109436 | G45: =G44/G42 -> 1.0601043 | H45: =H44/H42 -> 1.3905851 | I45: =I44/I42 -> 1.159588 | J45: =J44/J42 -> 1.1561347 | ... L45: =L44/L42 -> 1.1361122 | M45: -
B47: Retained Earning | C47: =IFERROR(IF(C44<C42,1-C45,0),0) -> 0.10316914 | D47: =IFERROR(IF(D44<D42,1-D45,0),0) -> 0.41738979 | E47: =IFERROR(IF(E44<E42,1-E45,0),0) -> 0.4441994 | F47: =IFERROR(IF(F44<F42,1-F45,0),0) -> 0.31890564 | G47: =IFERROR(IF(G44<G42,1-G45,0),0) -> 0 | H47: =IFERROR(IF(H44<H42,1-H45,0),0) -> 0 | I47: =IFERROR(IF(I44<I42,1-I45,0),0) -> 0 | J47: =IFERROR(IF(J44<J42,1-J45,0),0) -> 0 | ... M47: =IFERROR(IF(M44<M42,1-M45,0),0) -> 0
B52: Balance Sheet
B53: Equity Share Capital | C53: ='Balance Sheet'!B4 -> 804.72 | D53: ='Balance Sheet'!C4 -> 1214.74 | E53: ='Balance Sheet'!D4 -> 1220.43 | F53: 1225.86 | G53: 1229.22 | H53: 1230.88 | I53: 1232.33 | J53: 1242.8 | K53: 1248.47 | L53: 1251.41 | M53: -
B54: Reserves | C54: ='Balance Sheet'!B5 -> 41874.8 | D54: ='Balance Sheet'!C5 -> 45198.19 | E54: ='Balance Sheet'!D5 -> 51289.68 | F54: 57915.01 | G54: 64044.04 | H54: 59116.46 | I54: 61223.24 | J54: 67912.46 | K54: 73258.53 | L54: 68778.64 | M54: -
B55: Borrowings | C55: ='Balance Sheet'!B6 -> 83.78 | D55: ='Balance Sheet'!C6 -> 45.72 | E55: ='Balance Sheet'!D6 -> 35.92 | F55: 13.44 | G55: 277.45 | H55: 270.83 | I55: 249.44 | J55: 306.04 | K55: 303.43 | L55: 284.54 | M55: -
B56: Other Liabilities | C56: ='Balance Sheet'!B7 -> 8888.04 | D56: ='Balance Sheet'!C7 -> 9439.67 | E56: ='Balance Sheet'!D7 -> 11694.85 | F56: 12584.73 | G56: 11760.04 | H56: 13142.59 | I56: 14491.01 | J56: 16369.66 | K56: 16943.54 | L56: 17688.11 | M56: -
B57: Total | C57: =SUM(C53:C56) -> 51651.34 | D57: =SUM(D53:D56) -> 55898.32 | E57: =SUM(E53:E56) -> 64240.88 | F57: 71739.04 | G57: 77310.75 | H57: 73760.76 | I57: 77196.02 | J57: 85830.96 | K57: 91753.97 | L57: 88002.7 | M57: -
B59: Net Block | C59: ='Balance Sheet'!B10 -> 15106.63 | D59: ='Balance Sheet'!C10 -> 15893.48 | E59: ='Balance Sheet'!D10 -> 16523.96 | F59: 19374.19 | G59: 21713.34 | H59: 23298.48 | I59: 24231.59 | J59: 25851.27 | K59: 27820.22 | L59: 21954.85 | M59: -
B60: Capital Work in Progress | C60: ='Balance Sheet'!B11 -> 2559.72 | D60: ='Balance Sheet'!C11 -> 3729.89 | E60: ='Balance Sheet'!D11 -> 5508.33 | F60: 4136.42 | G60: 3256.46 | H60: 4011.29 | I60: 3225.54 | J60: 3003.3 | K60: 2860.78 | L60: 1090.91 | M60: -
B61: Investments | C61: ='Balance Sheet'!B12 -> 11747.59 | D61: ='Balance Sheet'!C12 -> 17581.38 | E61: ='Balance Sheet'!D12 -> 22052.86 | F61: 25043.49 | G61: 28663.35 | H61: 24870.87 | I61: 24841.01 | J61: 29415.02 | K61: 31114.02 | L61: 34719.82 | M61: -
B62: Other Assets | C62: =IFERROR('Data Sheet'!B65-'Historical Financial Statemen'!C68,0) -> 14104.84 | D62: =IFERROR('Data Sheet'!C65-'Historical Financial Statemen'!D68,0) -> 10561.01 | E62: =IFERROR('Data Sheet'!D65-'Historical Financial Statemen'!E68,0) -> 12023.17 | F62: =IFERROR('Data Sheet'!E65-'Historical Financial Statemen'!F68,0) -> 15052.38 | G62: =IFERROR('Data Sheet'!F65-'Historical Financial Statemen'!G68,0) -> 7458.93 | H62: =IFERROR('Data Sheet'!G65-'Historical Financial Statemen'!H68,0) -> 6461.94 | I62: =IFERROR('Data Sheet'!H65-'Historical Financial Statemen'!I68,0) -> 9317.31 | J62: =IFERROR('Data Sheet'!I65-'Historical Financial Statemen'!J68,0) -> 10848.02 | ... L62: =IFERROR('Data Sheet'!K65-'Historical Financial Statemen'!L68,0) -> 10525.2 | M62: -
B63: Total Non-Current Assets | C63: =C62+C61+C60+C59 -> 43518.78 | D63: =D62+D61+D60+D59 -> 47765.76 | E63: =E62+E61+E60+E59 -> 56108.32 | F63: =F62+F61+F60+F59 -> 63606.48 | G63: =G62+G61+G60+G59 -> 61092.08 | H63: =H62+H61+H60+H59 -> 58642.58 | I63: =I62+I61+I60+I59 -> 61615.45 | J63: =J62+J61+J60+J59 -> 69117.61 | ... L63: =L62+L61+L60+L59 -> 68290.78 | M63: -
B65: Receivables | C65: 4035.28 | D65: 4035.28 | E65: 4035.28 | F65: 4035.28 | G65: 2562.48 | H65: 2501.7 | I65: 2461.9 | J65: 2956.17 | K65: 4025.82 | L65: 4719.67 | M65: -
B66: Inventory | C66: 4035.28 | D66: 4035.28 | E66: 4035.28 | F66: 4035.28 | G66: 8879.33 | H66: 10397.16 | I66: 10864.15 | J66: 11771.16 | K66: 14152.88 | L66: 15637.56 | M66: -
B67: Cash & Bank | C67: 4035.28 | D67: 4035.28 | E67: 4035.28 | F67: 4035.28 | G67: 7277.34 | H67: 4659.02 | I67: 4654.42 | J67: 4880.19 | K67: 7217.68 | L67: 4012.36 | M67: -
B68: Total Current Assets | C68: =C67+C66+62 -> 8132.56 | D68: =D67+D66+62 -> 8132.56 | E68: =E67+E66+62 -> 8132.56 | F68: =F67+F66+62 -> 8132.56 | G68: =G67+G66+62 -> 16218.67 | H68: =H67+H66+62 -> 15118.18 | I68: =I67+I66+62 -> 15580.57 | J68: =J67+J66+62 -> 16713.35 | ... L68: =L67+L66+62 -> 19711.92 | M68: -
B70: Total Assets | C70: =C68+C63 -> 51651.34 | D70: =D68+D63 -> 55898.32 | E70: =E68+E63 -> 64240.88 | F70: =F68+F63 -> 71739.04 | G70: =G68+G63 -> 77310.75 | H70: =H68+H63 -> 73760.76 | I70: =I68+I63 -> 77196.02 | J70: =J68+J63 -> 85830.96 | ... L70: =L68+L63 -> 88002.7 | M70: -
B72: Check | C72: =C70=C57 -> TRUE | D72: =D70=D57 -> TRUE | E72: =E70=E57 -> TRUE | F72: =F70=F57 -> TRUE | G72: =G70=G57 -> TRUE | H72: =H70=H57 -> TRUE | I72: =I70=I57 -> TRUE | J72: =J70=J57 -> TRUE | ... L72: =L70=L57 -> TRUE | M72: -
B77: Cash Flow
B78: Operating Activity
B79: Profit from operations | C79: =Sheet1!C3 -> 14261 | D79: =Sheet1!D3 -> 15154 | E79: =Sheet1!E3 -> 16075 | F79: 18862 | G79: 19416 | H79: 17326 | I79: 20857 | J79: 26052 | K79: 26635 | L79: 26719
B80: Receivables | C80: =Sheet1!C4 -> 558 | D80: =Sheet1!D4 -> -207 | E80: =Sheet1!E4 -> -870 | F80: -755 | G80: 1411 | H80: -66 | I80: -732 | J80: -884 | K80: -934 | L80: -1023
B81: Inventory | C81: =Sheet1!C5 -> -505 | D81: =Sheet1!D5 -> -693 | E81: =Sheet1!E5 -> 593 | F81: -359 | G81: -508 | H81: -1460 | I81: -466 | J81: -1098 | K81: -2545 | L81: -2975
B82: Payables | C82: =Sheet1!C6 -> -23 | D82: =Sheet1!D6 -> 622 | E82: =Sheet1!E6 -> 321 | F82: 639 | G82: -607 | H82: 1112 | I82: 1099 | J82: 1058 | K82: 141 | L82: 1256
B83: Working capital changes | C83: =Sheet1!C7 -> 31 | D83: =Sheet1!D7 -> -277 | E83: =Sheet1!E7 -> 44 | F83: -476 | G83: 296 | H83: -413 | I83: -100 | J83: -924 | K83: -3337 | L83: -2742
B84: Direct taxes | C84: =Sheet1!C8 -> -4449 | D84: =Sheet1!D8 -> -5078 | E84: =Sheet1!E8 -> -5492 | F84: -5803 | G84: -5023 | H84: -4387 | I84: -4982 | J84: -6250 | K84: -6120 | L84: -6350
B85: Cash from Operating Activity | C85: =IFERROR(SUM(C79:C84),0) -> 9873 | D85: =IFERROR(SUM(D79:D84),0) -> 9521 | E85: =IFERROR(SUM(E79:E84),0) -> 10671 | F85: =IFERROR(SUM(F79:F84),0) -> 12108 | G85: =IFERROR(SUM(G79:G84),0) -> 14985 | H85: =IFERROR(SUM(H79:H84),0) -> 12112 | I85: =IFERROR(SUM(I79:I84),0) -> 15676 | J85: =IFERROR(SUM(J79:J84),0) -> 17954 | ... L85: =IFERROR(SUM(L79:L84),0) -> 14885
B87: Investing Activity
B88: Fixed assets purchased | C88: =Sheet1!C10 -> -3300 | D88: =Sheet1!D10 -> -2348 | E88: =Sheet1!E10 -> -3122 | F88: -3169 | G88: -2441 | H88: -1837 | I88: -2142 | J88: -2743 | K88: -3563 | L88: -2279
B89: Fixed assets sold | C89: =Sheet1!C11 -> 9 | D89: =Sheet1!D11 -> 8 | E89: =Sheet1!E11 -> 50 | F89: 28 | G89: 27 | H89: 3 | I89: 133 | J89: 49 | K89: 107 | L89: 175
B90: Investments purchased | C90: =Sheet1!C12 -> -98742 | D90: =Sheet1!D12 -> -154081 | E90: =Sheet1!E12 -> -85683 | F90: -94187 | G90: -79835 | H90: -57553 | I90: -69776 | J90: -80932 | K90: -75107 | L90: -66373
B91: Investments sold | C91: =Sheet1!C13 -> 99658 | D91: =Sheet1!D13 -> 150651 | E91: =Sheet1!E13 -> 81034 | F91: 92454 | G91: 75835 | H91: 62797 | I91: 70992 | J91: 77230 | K91: 77830 | L91: 67311
B92: Interest received | C92: =Sheet1!C14 -> 559 | D92: =Sheet1!D14 -> 741 | E92: =Sheet1!E14 -> 756 | F92: 1184 | G92: 1513 | H92: 1275 | I92: 1035 | J92: 1324 | K92: 1138 | L92: 1072
B93: Dividends received | C93: =Sheet1!C15 -> 268 | D93: =Sheet1!D15 -> 64 | E93: =Sheet1!E15 -> 4 | F93: 13 | G93: 17 | H93: 7 | I93: 16 | J93: 19 | K93: 36 | L93: 38
B94: Invest in subsidiaries | C94: =Sheet1!C16 -> 0 | D94: =Sheet1!D16 -> -8 | E94: =Sheet1!E16 -> 0 | F94: 0 | G94: 0 | H94: 0 | I94: 0 | J94: 0 | K94: 0 | L94: 0
B95: Investment in group cos | C95: =Sheet1!C17 -> 0 | D95: =Sheet1!D17 -> 0 | E95: =Sheet1!E17 -> 0 | F95: 0 | G95: 0 | H95: -2 | I95: -2 | J95: -2 | K95: -65 | L95: -30
B96: Redemp n Canc of Shares | C96: =Sheet1!C18 -> 0 | D96: =Sheet1!D18 -> 0 | E96: =Sheet1!E18 -> 129 | F96: 18 | G96: 0 | H96: 0 | I96: 0 | J96: 56 | K96: 0 | L96: 0
B97: Other investing items | C97: =Sheet1!C19 -> -3728 | D97: =Sheet1!D19 -> 1052 | E97: =Sheet1!E19 -> 3579 | F97: -1887 | G97: -1290 | H97: 1051 | I97: -2494 | J97: -733 | K97: 1187 | L97: -478
B98: Cash from Investing Activity - | C98: =IFERROR(SUM(C88:C97),0) -> -5276 | D98: =IFERROR(SUM(D88:D97),0) -> -3921 | E98: =IFERROR(SUM(E88:E97),0) -> -3253 | F98: =IFERROR(SUM(F88:F97),0) -> -5546 | G98: =IFERROR(SUM(G88:G97),0) -> -6174 | H98: =IFERROR(SUM(H88:H97),0) -> 5741 | I98: =IFERROR(SUM(I88:I97),0) -> -2238 | J98: =IFERROR(SUM(J88:J97),0) -> -5732 | ... L98: =IFERROR(SUM(L88:L97),0) -> -564
B100: Financing Activity
B101: Proceeds from shares | C101: =Sheet1!C21 -> 979 | D101: =Sheet1!D21 -> 532 | E101: =Sheet1!E21 -> 1067 | F101: 969 | G101: 625 | H101: 291 | I101: 292 | J101: 2477 | K101: 1443 | L101: 797
B102: Proceeds from borrowings | C102: =Sheet1!C22 -> 7 | D102: =Sheet1!D22 -> 0 | E102: =Sheet1!E22 -> 0 | F102: 0 | G102: 0 | H102: 0 | I102: 0 | J102: 0 | K102: 8 | L102: 90
B103: Repayment of borrowings | C103: =Sheet1!C23 -> -20 | D103: =Sheet1!D23 -> -13 | E103: =Sheet1!E23 -> -13 | F103: -18 | G103: -3 | H103: -2 | I103: -1 | J103: -1 | K103: -2 | L103: -54
B104: Interest paid fin | C104: =Sheet1!C24 -> -16 | D104: =Sheet1!D24 -> -28 | E104: =Sheet1!E24 -> -25 | F104: -98 | G104: -44 | H104: -41 | I104: -40 | J104: -41 | K104: -46 | L104: -50
B105: Dividends paid | C105: =Sheet1!C25 -> -4876 | D105: =Sheet1!D25 -> -5133 | E105: =Sheet1!E25 -> -6994 | F105: -6519 | G105: -7302 | H105: -18881 | I105: -13788 | J105: -15418 | K105: -19899 | L105: -17782
B106: Financial liabilities | C106: =Sheet1!C26 -> 0 | D106: =Sheet1!D26 -> 0 | E106: =Sheet1!E26 -> 0 | F106: 0 | G106: -49 | H106: -55 | I106: -59 | J106: -59 | K106: -67 | L106: -66
B107: Other financing items | C107: =Sheet1!C27 -> -734 | D107: =Sheet1!D27 -> -971 | E107: =Sheet1!E27 -> -1335 | F107: -1203 | G107: -1409 | H107: 55 | I107: 15 | J107: 35 | K107: 12 | L107: 28
B108: Cash from Financing Activity - | C108: =IFERROR(SUM(C101:C107),0) -> -4660 | D108: =IFERROR(SUM(D101:D107),0) -> -5613 | E108: =IFERROR(SUM(E101:E107),0) -> -7300 | F108: =IFERROR(SUM(F101:F107),0) -> -6869 | G108: =IFERROR(SUM(G101:G107),0) -> -8182 | H108: =IFERROR(SUM(H101:H107),0) -> -18633 | I108: =IFERROR(SUM(I101:I107),0) -> -13581 | J108: =IFERROR(SUM(J101:J107),0) -> -13007 | ... L108: =IFERROR(SUM(L101:L107),0) -> -17037
B110: Net Cash Flow | C110: =C108+C98+C85 -> -63 | D110: =D108+D98+D85 -> -13 | E110: =E108+E98+E85 -> 118 | F110: =F108+F98+F85 -> -307 | G110: =G108+G98+G85 -> 629 | H110: =H108+H98+H85 -> -780 | I110: =I108+I98+I85 -> -143 | J110: =J108+J98+J85 -> -785 | ... L110: =L108+L98+L85 -> -2716

Sheet Ratio Analysis
B3: ="Ratio Analysis - "&'Balance Sheet'!A1 -> Ratio Analysis - ITC LTD
B4: Years | C4: ='Historical Financial Statemen'!C4 -> 42460 | D4: ='Historical Financial Statemen'!D4 -> 42825 | E4: ='Historical Financial Statemen'!E4 -> 43190 | F4: ='Historical Financial Statemen'!F4 -> 43555 | G4: ='Balance Sheet'!F3 -> 43921 | H4: ='Balance Sheet'!G3 -> 44286 | I4: ='Balance Sheet'!H3 -> 44651 | J4: ='Balance Sheet'!I3 -> 45016 | K4: ='Balance Sheet'!J3 -> 45382 | L4: ='Balance Sheet'!K3 -> 45747
B6: Sales Growth | C6: =IFERROR('Data Sheet'!B17/'Data Sheet'!A17-1,0) -> 0 | D6: =IFERROR('Data Sheet'!C17/'Data Sheet'!B17-1,0) -> 0.09123012 | E6: =IFERROR('Data Sheet'!D17/'Data Sheet'!C17-1,0) -> 0.015931219 | F6: =IFERROR('Data Sheet'!E17/'Data Sheet'!D17-1,0) -> 0.11256063 | G6: =IFERROR('Data Sheet'!F17/'Data Sheet'!E17-1,0) -> 0.021682439 | H6: =IFERROR('Data Sheet'!G17/'Data Sheet'!F17-1,0) -> -0.0026372963 | I6: =IFERROR('Data Sheet'!H17/'Data Sheet'!G17-1,0) -> 0.23117498 | J6: =IFERROR('Data Sheet'!I17/'Data Sheet'!H17-1,0) -> 0.16942152 | ... L6: =IFERROR('Data Sheet'!K17/'Data Sheet'!J17-1,0) -> 0.10880596
B7: EBITDA Growth | C7: =IFERROR('Historical Financial Statemen'!C19/'Historical Financial Statemen'!B19-1,0) -> 0 | D7: =IFERROR('Historical Financial Statemen'!D19/'Historical Financial Statemen'!C19-1,0) -> 0.17684209 | E7: =IFERROR('Historical Financial Statemen'!E19/'Historical Financial Statemen'!D19-1,0) -> 0.096688914 | F7: =IFERROR('Historical Financial Statemen'!F19/'Historical Financial Statemen'!E19-1,0) -> -0.017490497 | G7: =IFERROR('Historical Financial Statemen'!G19/'Historical Financial Statemen'!F19-1,0) -> -0.033058639 | H7: =IFERROR('Historical Financial Statemen'!H19/'Historical Financial Statemen'!G19-1,0) -> -0.14965696 | I7: =IFERROR('Historical Financial Statemen'!I19/'Historical Financial Statemen'!H19-1,0) -> 0.31401447 | J7: =IFERROR('Historical Financial Statemen'!J19/'Historical Financial Statemen'!I19-1,0) -> 0.31992806 | ... L7: =IFERROR('Historical Financial Statemen'!L19/'Historical Financial Statemen'!K19-1,0) -> -0.68784142
B8: EBIT Growth | C8: =IFERROR(('Historical Financial Statemen'!C19-'Historical Financial Statemen'!C25)/('Historical Financial Statemen'!B19-'Historical Financial Statemen'!B25)-1,0) -> 0 | D8: =IFERROR(('Historical Financial Statemen'!D19-'Historical Financial Statemen'!D25)/('Historical Financial Statemen'!C19-'Historical Financial Statemen'!C25)-1,0) -> 0.18678488 | E8: =IFERROR(('Historical Financial Statemen'!E19-'Historical Financial Statemen'!E25)/('Historical Financial Statemen'!D19-'Historical Financial Statemen'!D25)-1,0) -> 0.098724245 | F8: =IFERROR(('Historical Financial Statemen'!F19-'Historical Financial Statemen'!F25)/('Historical Financial Statemen'!E19-'Historical Financial Statemen'!E25)-1,0) -> -0.029540358 | G8: =IFERROR(('Historical Financial Statemen'!G19-'Historical Financial Statemen'!G25)/('Historical Financial Statemen'!F19-'Historical Financial Statemen'!F25)-1,0) -> -0.05315355 | H8: =IFERROR(('Historical Financial Statemen'!H19-'Historical Financial Statemen'!H25)/('Historical Financial Statemen'!G19-'Historical Financial Statemen'!G25)-1,0) -> -0.16744805 | I8: =IFERROR(('Historical Financial Statemen'!I19-'Historical Financial Statemen'!I25)/('Historical Financial Statemen'!H19-'Historical Financial Statemen'!H25)-1,0) -> 0.35123142 | J8: =IFERROR(('Historical Financial Statemen'!J19-'Historical Financial Statemen'!J25)/('Historical Financial Statemen'!I19-'Historical Financial Statemen'!I25)-1,0) -> 0.35052873 | ... L8: =IFERROR(('Historical Financial Statemen'!L19-'Historical Financial Statemen'!L25)/('Historical Financial Statemen'!K19-'Historical Financial Statemen'!K25)-1,0) -> -0.74764953
B9: Net Profit Growth | C9: =IFERROR('Historical Financial Statemen'!C37/'Historical Financial Statemen'!B37-1,0) -> 0 | D9: =IFERROR('Historical Financial Statemen'!D37/'Historical Financial Statemen'!C37-1,0) -> 0.29851226 | E9: =IFERROR('Historical Financial Statemen'!E37/'Historical Financial Statemen'!D37-1,0) -> 0.14183026 | F9: =IFERROR('Historical Financial Statemen'!F37/'Historical Financial Statemen'!E37-1,0) -> -0.084831705 | G9: =IFERROR('Historical Financial Statemen'!G37/'Historical Financial Statemen'!F37-1,0) -> 0.13722186 | H9: =IFERROR('Historical Financial Statemen'!H37/'Historical Financial Statemen'!G37-1,0) -> -0.1915007 | I9: =IFERROR('Historical Financial Statemen'!I37/'Historical Financial Statemen'!H37-1,0) -> 0.28438351 | J9: =IFERROR('Historical Financial Statemen'!J37/'Historical Financial Statemen'!I37-1,0) -> 0.36333696 | ... L9: =IFERROR('Historical Financial Statemen'!L37/'Historical Financial Statemen'!K37-1,0) -> -0.052685077
B10: Dividend Growth | C10: =IFERROR('Historical Financial Statemen'!C44/'Historical Financial Statemen'!B44-1,0) -> 0 | D10: =IFERROR('Historical Financial Statemen'!D44/'Historical Financial Statemen'!C44-1,0) -> -0.16176398 | E10: =IFERROR('Historical Financial Statemen'!E44/'Historical Financial Statemen'!D44-1,0) -> 0.084208811 | F10: =IFERROR('Historical Financial Statemen'!F44/'Historical Financial Statemen'!E44-1,0) -> 0.11650645 | G10: =IFERROR('Historical Financial Statemen'!G44/'Historical Financial Statemen'!F44-1,0) -> 0.76521571 | H10: =IFERROR('Historical Financial Statemen'!H44/'Historical Financial Statemen'!G44-1,0) -> 0.059113555 | I10: =IFERROR('Historical Financial Statemen'!I44/'Historical Financial Statemen'!H44-1,0) -> 0.069767819 | J10: =IFERROR('Historical Financial Statemen'!J44/'Historical Financial Statemen'!I44-1,0) -> 0.34782561 | ... L10: =IFERROR('Historical Financial Statemen'!L44/'Historical Financial Statemen'!K44-1,0) -> 0.043636312
B12: Gross Margin | C12: ='Historical Financial Statemen'!C14 -> 0.39233978 | D12: ='Historical Financial Statemen'!D14 -> 0.41676129 | E12: ='Historical Financial Statemen'!E14 -> 0.45069201 | F12: ='Historical Financial Statemen'!F14 -> 0.39658723 | G12: ='Historical Financial Statemen'!G14 -> 0.38799964 | H12: ='Historical Financial Statemen'!H14 -> 0.34205242 | I12: ='Historical Financial Statemen'!I14 -> 0.33574498 | J12: ='Historical Financial Statemen'!J14 -> 0.37078398 | ... L12: ='Historical Financial Statemen'!L14 -> 0.35327085
B13: EBITDA Margin | C13: ='Historical Financial Statemen'!C20 -> 0.32296356 | D13: ='Historical Financial Statemen'!D20 -> 0.34830152 | E13: ='Historical Financial Statemen'!E20 -> 0.37598846 | F13: ='Historical Financial Statemen'!F20 -> 0.33203785 | G13: ='Historical Financial Statemen'!G20 -> 0.31424747 | H13: ='Historical Financial Statemen'!H20 -> 0.26792475 | I13: ='Historical Financial Statemen'!I20 -> 0.28595204 | J13: ='Historical Financial Statemen'!J20 -> 0.32275456 | ... L13: ='Historical Financial Statemen'!L20 -> 0.087532895
B14: EBIT Margin | C14: =IFERROR(('Historical Financial Statemen'!C19-'Historical Financial Statemen'!C25)/'Historical Financial Statemen'!C7,0) -> 0.29547332 | D14: =IFERROR(('Historical Financial Statemen'!D19-'Historical Financial Statemen'!D25)/'Historical Financial Statemen'!D7,0) -> 0.32134677 | E14: =IFERROR(('Historical Financial Statemen'!E19-'Historical Financial Statemen'!E25)/'Historical Financial Statemen'!E7,0) -> 0.34753483 | F14: =IFERROR(('Historical Financial Statemen'!F19-'Historical Financial Statemen'!F25)/'Historical Financial Statemen'!F7,0) -> 0.3031462 | G14: =IFERROR(('Historical Financial Statemen'!G19-'Historical Financial Statemen'!G25)/'Historical Financial Statemen'!G7,0) -> 0.28094141 | H14: =IFERROR(('Historical Financial Statemen'!H19-'Historical Financial Statemen'!H25)/'Historical Financial Statemen'!H7,0) -> 0.23451681 | I14: =IFERROR(('Historical Financial Statemen'!I19-'Historical Financial Statemen'!I25)/'Historical Financial Statemen'!I7,0) -> 0.25738541 | J14: =IFERROR(('Historical Financial Statemen'!J19-'Historical Financial Statemen'!J25)/'Historical Financial Statemen'!J7,0) -> 0.29724645 | ... L14: =IFERROR(('Historical Financial Statemen'!L19-'Historical Financial Statemen'!L25)/'Historical Financial Statemen'!L7,0) -> 0.06567619
B15: Net Profit Margin | C15: ='Historical Financial Statemen'!C38 -> 0.19460529 | D15: ='Historical Financial Statemen'!D38 -> 0.2315711 | E15: ='Historical Financial Statemen'!E38 -> 0.26026849 | F15: ='Historical Financial Statemen'!F38 -> 0.21409123 | G15: ='Historical Financial Statemen'!G38 -> 0.23830225 | H15: ='Historical Financial Statemen'!H38 -> 0.19317667 | I15: ='Historical Financial Statemen'!I38 -> 0.20152531 | J15: ='Historical Financial Statemen'!J38 -> 0.23494258 | ... L15: ='Historical Financial Statemen'!L38 -> 0.20984598
B17: Sales Expenses % Sales | C17: ='Historical Financial Statemen'!C17 -> 0.069376226 | D17: ='Historical Financial Statemen'!D17 -> 0.068459769 | E17: ='Historical Financial Statemen'!E17 -> 0.074703549 | F17: ='Historical Financial Statemen'!F17 -> 0.064549382 | G17: ='Historical Financial Statemen'!G17 -> 0.073752169 | H17: ='Historical Financial Statemen'!H17 -> 0.07412767 | I17: ='Historical Financial Statemen'!I17 -> 0.049792941 | J17: ='Historical Financial Statemen'!J17 -> 0.048029422 | ... L17: ='Historical Financial Statemen'!L17 -> 0.26573795
B18: Depreciation % Sales | C18: ='Historical Financial Statemen'!C26 -> 0.027490234 | D18: ='Historical Financial Statemen'!D26 -> 0.026954751 | E18: ='Historical Financial Statemen'!E26 -> 0.028453629 | F18: ='Historical Financial Statemen'!F26 -> 0.028891645 | G18: ='Historical Financial Statemen'!G26 -> 0.033306066 | H18: ='Historical Financial Statemen'!H26 -> 0.033407941 | I18: ='Historical Financial Statemen'!I26 -> 0.028566628 | J18: ='Historical Financial Statemen'!J26 -> 0.025508104 | ... L18: ='Historical Financial Statemen'!L26 -> 0.021856705
B19: Operating Income % Sales | C19: =C14 -> 0.29547332 | D19: =D14 -> 0.32134677 | E19: =E14 -> 0.34753483 | F19: =F14 -> 0.3031462 | G19: =G14 -> 0.28094141 | H19: =H14 -> 0.23451681 | I19: =I14 -> 0.25738541 | J19: =J14 -> 0.29724645 | ... L19: =L14 -> 0.06567619
B21: Return on Capital Employed | C21: ='Historical Financial Statemen'!C19/('Data Sheet'!B57+B60+B59) -> 15.729223 | D21: ='Historical Financial Statemen'!D19/('Data Sheet'!C57+C60+C59) -> 12.262723 | E21: ='Historical Financial Statemen'!E19/('Data Sheet'!D57+D60+D59) -> 13.385692 | F21: ='Historical Financial Statemen'!F19/('Data Sheet'!E57+E60+E59) -> 13.093314 | G21: ='Historical Financial Statemen'!G19/('Data Sheet'!F57+F60+F59) -> 12.62586 | H21: ='Historical Financial Statemen'!H19/('Data Sheet'!G57+G60+G59) -> 10.721833 | I21: ='Historical Financial Statemen'!I19/('Data Sheet'!H57+H60+H59) -> 14.072067 | J21: ='Historical Financial Statemen'!J19/('Data Sheet'!I57+I60+I59) -> 18.417638 | ... L21: ='Historical Financial Statemen'!L19/('Data Sheet'!K57+K60+K59) -> 5.2686729
B22: Retained Earning % | C22: ='Historical Financial Statemen'!C47 -> 0.10316914 | D22: ='Historical Financial Statemen'!D47 -> 0.41738979 | E22: ='Historical Financial Statemen'!E47 -> 0.4441994 | F22: ='Historical Financial Statemen'!F47 -> 0.31890564 | G22: ='Historical Financial Statemen'!G47 -> 0 | H22: ='Historical Financial Statemen'!H47 -> 0 | I22: ='Historical Financial Statemen'!I47 -> 0 | J22: ='Historical Financial Statemen'!J47 -> 0 | ... L22: ='Historical Financial Statemen'!L47 -> 0
B23: Return on Equity % | C23: ='Historical Financial Statemen'!C37/('Data Sheet'!B57+'Data Sheet'!B58) -> 0.17870374 | D23: ='Historical Financial Statemen'!D37/('Data Sheet'!C57+'Data Sheet'!C58) -> 0.21338321 | E23: ='Historical Financial Statemen'!E37/('Data Sheet'!D57+'Data Sheet'!D58) -> 0.21535643 | F23: ='Historical Financial Statemen'!F37/('Data Sheet'!E57+'Data Sheet'!E58) -> 0.17499032 | G23: ='Historical Financial Statemen'!G37/('Data Sheet'!F57+'Data Sheet'!F58) -> 0.18030661 | H23: ='Historical Financial Statemen'!H37/('Data Sheet'!G57+'Data Sheet'!G58) -> 0.15767704 | I23: ='Historical Financial Statemen'!I37/('Data Sheet'!H57+'Data Sheet'!H58) -> 0.19568167 | J23: ='Historical Financial Statemen'!J37/('Data Sheet'!I57+'Data Sheet'!I58) -> 0.24093467 | ... L23: ='Historical Financial Statemen'!L37/('Data Sheet'!K57+'Data Sheet'!K58) -> 0.22570739
B24: Self Substained Growth Rate | C24: =C23*C22 -> 0.018436712 | D24: =D23*D22 -> 0.089063974 | E24: =E23*E22 -> 0.095661197 | F24: =F23*F22 -> 0.055805402 | G24: =G23*G22 -> 0 | H24: =H23*H22 -> 0 | I24: =I23*I22 -> 0 | J24: =J23*J22 -> 0 | ... L24: =L23*L22 -> 0
B25: Interest Coverage Ratio | C25: =('Historical Financial Statemen'!C19-'Historical Financial Statemen'!C25)/'Historical Financial Statemen'!C22 -> 148.21733 | D25: =('Historical Financial Statemen'!D19-'Historical Financial Statemen'!D25)/'Historical Financial Statemen'!D22 -> 280.30247 | E25: =('Historical Financial Statemen'!E19-'Historical Financial Statemen'!E25)/'Historical Financial Statemen'!E22 -> 131.2931 | F25: =('Historical Financial Statemen'!F19-'Historical Financial Statemen'!F25)/'Historical Financial Statemen'!F22 -> 205.23754 | G25: =('Historical Financial Statemen'!G19-'Historical Financial Statemen'!G25)/'Historical Financial Statemen'!G22 -> 170.49705 | H25: =('Historical Financial Statemen'!H19-'Historical Financial Statemen'!H25)/'Historical Financial Statemen'!H22 -> 199.27031 | I25: =('Historical Financial Statemen'!I19-'Historical Financial Statemen'!I25)/'Historical Financial Statemen'!I22 -> 260.1937 | J25: =('Historical Financial Statemen'!J19-'Historical Financial Statemen'!J25)/'Historical Financial Statemen'!J22 -> 271.06121 | ... L25: =('Historical Financial Statemen'!L19-'Historical Financial Statemen'!L25)/'Historical Financial Statemen'!L22 -> 109.78584
B27: Debtor Turnover Ratio | C27: ='Data Sheet'!B17/'Data Sheet'!B67 -> 20.442577 | D27: ='Data Sheet'!C17/'Data Sheet'!C67 -> 17.284797 | E27: ='Data Sheet'!D17/'Data Sheet'!D67 -> 16.19845 | F27: ='Data Sheet'!E17/'Data Sheet'!E67 -> 11.979238 | G27: ='Data Sheet'!F17/'Data Sheet'!F67 -> 19.273399 | H27: ='Data Sheet'!G17/'Data Sheet'!G67 -> 19.689591 | I27: ='Data Sheet'!H17/'Data Sheet'!H67 -> 24.633226 | J27: ='Data Sheet'!I17/'Data Sheet'!I67 -> 23.990173 | ... L27: ='Data Sheet'!K17/'Data Sheet'!K67 -> 15.959451
B28: Creditor Turnover Ratio | C28: ='Historical Financial Statemen'!C7/'Historical Financial Statemen'!C56 -> 4.4095324 | D28: ='Historical Financial Statemen'!D7/'Historical Financial Statemen'!D56 -> 4.5306245 | E28: ='Historical Financial Statemen'!E7/'Historical Financial Statemen'!E56 -> 3.7152199 | F28: ='Historical Financial Statemen'!F7/'Historical Financial Statemen'!F56 -> 3.8411297 | G28: ='Historical Financial Statemen'!G7/'Historical Financial Statemen'!G56 -> 4.1996201 | H28: ='Historical Financial Statemen'!H7/'Historical Financial Statemen'!H56 -> 3.7479256 | I28: ='Historical Financial Statemen'!I7/'Historical Financial Statemen'!I56 -> 4.1849768 | J28: ='Historical Financial Statemen'!J7/'Historical Financial Statemen'!J56 -> 4.3323459 | ... L28: ='Historical Financial Statemen'!L7/'Historical Financial Statemen'!L56 -> 4.2584165
B29: Inventory Turnover | C29: ='Historical Financial Statemen'!C7/'Historical Financial Statemen'!C66 -> 9.712362 | D29: ='Historical Financial Statemen'!D7/'Historical Financial Statemen'!D66 -> 10.598422 | E29: ='Historical Financial Statemen'!E7/'Historical Financial Statemen'!E66 -> 10.767268 | F29: ='Historical Financial Statemen'!F7/'Historical Financial Statemen'!F66 -> 11.979238 | G29: ='Historical Financial Statemen'!G7/'Historical Financial Statemen'!G66 -> 5.5620976 | H29: ='Historical Financial Statemen'!H7/'Historical Financial Statemen'!H66 -> 4.737587 | I29: ='Historical Financial Statemen'!I7/'Historical Financial Statemen'!I66 -> 5.5820787 | J29: ='Historical Financial Statemen'!J7/'Historical Financial Statemen'!J66 -> 6.0248123 | ... L29: ='Historical Financial Statemen'!L7/'Historical Financial Statemen'!L66 -> 4.8168218
B30: Fixed Asset Turnover | C30: ='Historical Financial Statemen'!C7/'Historical Financial Statemen'!C59 -> 2.5943642 | D30: ='Historical Financial Statemen'!D7/'Historical Financial Statemen'!D59 -> 2.6908896 | E30: ='Historical Financial Statemen'!E7/'Historical Financial Statemen'!E59 -> 2.6294508 | F30: ='Historical Financial Statemen'!F7/'Historical Financial Statemen'!F59 -> 2.4950504 | G30: ='Historical Financial Statemen'!G7/'Historical Financial Statemen'!G59 -> 2.2745326 | H30: ='Historical Financial Statemen'!H7/'Historical Financial Statemen'!H59 -> 2.1141916 | I30: ='Historical Financial Statemen'!I7/'Historical Financial Statemen'!I59 -> 2.5027058 | J30: ='Historical Financial Statemen'!J7/'Historical Financial Statemen'!J59 -> 2.743348 | ... L30: ='Historical Financial Statemen'!L7/'Historical Financial Statemen'!L59 -> 3.4308292
B31: Capital Turnover Ratio | C31: ='Historical Financial Statemen'!C7/('Historical Financial Statemen'!C53+'Historical Financial Statemen'!C54) -> 0.91828821 | D31: ='Historical Financial Statemen'!D7/('Historical Financial Statemen'!D53+'Historical Financial Statemen'!D54) -> 0.92145874 | E31: ='Historical Financial Statemen'!E7/('Historical Financial Statemen'!E53+'Historical Financial Statemen'!E54) -> 0.82743952 | F31: ='Historical Financial Statemen'!F7/('Historical Financial Statemen'!F53+'Historical Financial Statemen'!F54) -> 0.81736336 | G31: ='Historical Financial Statemen'!G7/('Historical Financial Statemen'!G53+'Historical Financial Statemen'!G54) -> 0.7566299 | H31: ='Historical Financial Statemen'!H7/('Historical Financial Statemen'!H53+'Historical Financial Statemen'!H54) -> 0.81623233 | I31: ='Historical Financial Statemen'!I7/('Historical Financial Statemen'!I53+'Historical Financial Statemen'!I54) -> 0.97100291 | J31: ='Historical Financial Statemen'!J7/('Historical Financial Statemen'!J53+'Historical Financial Statemen'!J54) -> 1.0255045 | ... L31: ='Historical Financial Statemen'!L7/('Historical Financial Statemen'!L53+'Historical Financial Statemen'!L54) -> 1.075586
B33: Debtor Days | C33: =365/C27 -> 17.854892 | D33: =365/D27 -> 21.116823 | E33: =365/E27 -> 22.53302 | F33: =365/F27 -> 30.469383 | G33: =365/G27 -> 18.938019 | H33: =365/H27 -> 18.537714 | I33: =365/I27 -> 14.817385 | J33: =365/J27 -> 15.214563 | ... L33: =365/L27 -> 22.870462
B34: Payable Days | C34: =365/C28 -> 82.775217 | D34: =365/D28 -> 80.562845 | E34: =365/E28 -> 98.24452 | F34: =365/F28 -> 95.024128 | G34: =365/G28 -> 86.912624 | H34: =365/H28 -> 97.387204 | I34: =365/I28 -> 87.216733 | J34: =365/J28 -> 84.249966 | ... L34: =365/L28 -> 85.712611
B35: Inventory Days | C35: =365/C29 -> 37.580972 | D35: =365/D29 -> 34.439089 | E35: =365/E29 -> 33.899036 | F35: =365/F29 -> 30.469383 | G35: =365/G29 -> 65.622725 | H35: =365/H29 -> 77.04344 | I35: =365/I29 -> 65.387828 | J35: =365/J29 -> 60.5828 | ... L35: =365/L29 -> 75.776106
B36: Cash Conversion Cycle | C36: =365/C30 -> 140.68958 | D36: =365/D30 -> 135.64287 | E36: =365/E30 -> 138.81226 | F36: =365/F30 -> 146.28963 | G36: =365/G30 -> 160.47253 | H36: =365/H30 -> 172.64282 | I36: =365/I30 -> 145.84215 | J36: =365/J30 -> 133.04911 | ... L36: =365/L30 -> 106.38828
B38: CFO/Sales | C38: ='Historical Financial Statemen'!C85/'Historical Financial Statemen'!C7 -> 0.25191301 | D38: ='Historical Financial Statemen'!D85/'Historical Financial Statemen'!D7 -> 0.2226218 | E38: ='Historical Financial Statemen'!E85/'Historical Financial Statemen'!E7 -> 0.24559863 | F38: ='Historical Financial Statemen'!F85/'Historical Financial Statemen'!F7 -> 0.25047797 | G38: ='Historical Financial Statemen'!G85/'Historical Financial Statemen'!G7 -> 0.30341563 | H38: ='Historical Financial Statemen'!H85/'Historical Financial Statemen'!H7 -> 0.24589174 | I38: ='Historical Financial Statemen'!I85/'Historical Financial Statemen'!I7 -> 0.25848988 | J38: ='Historical Financial Statemen'!J85/'Historical Financial Statemen'!J7 -> 0.25316195 | ... L38: ='Historical Financial Statemen'!L85/'Historical Financial Statemen'!L7 -> 0.19761471
B39: CFO/Total Assets | C39: ='Historical Financial Statemen'!C85/'Historical Financial Statemen'!C70 -> 0.19114703 | D39: ='Historical Financial Statemen'!D85/'Historical Financial Statemen'!D70 -> 0.17032712 | E39: ='Historical Financial Statemen'!E85/'Historical Financial Statemen'!E70 -> 0.16610918 | F39: ='Historical Financial Statemen'!F85/'Historical Financial Statemen'!F70 -> 0.16877839 | G39: ='Historical Financial Statemen'!G85/'Historical Financial Statemen'!G70 -> 0.19382815 | H39: ='Historical Financial Statemen'!H85/'Historical Financial Statemen'!H70 -> 0.16420655 | I39: ='Historical Financial Statemen'!I85/'Historical Financial Statemen'!I70 -> 0.20306746 | J39: ='Historical Financial Statemen'!J85/'Historical Financial Statemen'!J70 -> 0.2091786 | ... L39: ='Historical Financial Statemen'!L85/'Historical Financial Statemen'!L70 -> 0.16914254
B40: CFO/Total Debt | C40: ='Historical Financial Statemen'!C85/'Historical Financial Statemen'!C55 -> 117.84435 | D40: ='Historical Financial Statemen'!D85/'Historical Financial Statemen'!D55 -> 208.24584 | E40: ='Historical Financial Statemen'!E85/'Historical Financial Statemen'!E55 -> 297.07684 | F40: ='Historical Financial Statemen'!F85/'Historical Financial Statemen'!F55 -> 900.89286 | G40: ='Historical Financial Statemen'!G85/'Historical Financial Statemen'!G55 -> 54.009731 | H40: ='Historical Financial Statemen'!H85/'Historical Financial Statemen'!H55 -> 44.721781 | I40: ='Historical Financial Statemen'!I85/'Historical Financial Statemen'!I55 -> 62.844772 | J40: ='Historical Financial Statemen'!J85/'Historical Financial Statemen'!J55 -> 58.665534 | ... L40: ='Historical Financial Statemen'!L85/'Historical Financial Statemen'!L55 -> 52.312504

Sheet Sheet1
A1: 41699 | B1: 42064 | C1: 42430 | D1: 42795 | E1: 43160 | F1: 43525 | G1: 43891 | H1: 44256 | I1: 44621 | J1: 44986 | K1: 45352 | L1: 45717
A2: Cash from Operating Activity - | B2: 7344 | C2: 9843 | D2: 9799 | E2: 10627 | F2: 13169 | G2: 12583 | H2: 14690 | I2: 12527 | J2: 15776 | K2: 18878 | L2: 17179 | M2: 17627
A3: Profit from operations | B3: 13172 | C3: 14261 | D3: 15154 | E3: 16075 | F3: 17433 | G3: 18862 | H3: 19416 | I3: 17326 | J3: 20857 | K3: 26052 | L3: 26635 | M3: 26719
A4: Receivables | B4: -1546 | C4: 558 | D4: -207 | E4: -870 | F4: -964 | G4: -755 | H4: 1411 | I4: -66 | J4: -732 | K4: -884 | L4: -934 | M4: -1023
A5: Inventory | B5: -755 | C5: -505 | D5: -693 | E5: 593 | F5: 602 | G5: -359 | H5: -508 | I5: -1460 | J5: -466 | K5: -1098 | L5: -2545 | M5: -2975
A6: Payables | B6: 456 | C6: -23 | D6: 622 | E6: 321 | F6: 2098 | G6: 639 | H6: -607 | I6: 1112 | J6: 1099 | K6: 1058 | L6: 141 | M6: 1256
A7: Working capital changes | B7: -1844 | C7: 31 | D7: -277 | E7: 44 | F7: 1736 | G7: -476 | H7: 296 | I7: -413 | J7: -100 | K7: -924 | L7: -3337 | M7: -2742
A8: Direct taxes | B8: -3984 | C8: -4449 | D8: -5078 | E8: -5492 | F8: -6000 | G8: -5803 | H8: -5023 | I8: -4387 | J8: -4982 | K8: -6250 | L8: -6120 | M8: -6350
A9: Cash from Investing Activity - | B9: -3254 | C9: -5275 | D9: -3921 | E9: -3251 | F9: -7114 | G9: -5546 | H9: -6174 | I9: 5740 | J9: -2238 | K9: -5732 | L9: 1563 | M9: -564
A10: Fixed assets purchased | B10: -2887 | C10: -3300 | D10: -2348 | E10: -3122 | F10: -2878 | G10: -3169 | H10: -2441 | I10: -1837 | J10: -2142 | K10: -2743 | L10: -3563 | M10: -2279
A11: Fixed assets sold | B11: 38 | C11: 9 | D11: 8 | E11: 50 | F11: 80 | G11: 28 | H11: 27 | I11: 3 | J11: 133 | K11: 49 | L11: 107 | M11: 175
A12: Investments purchased | B12: -94242 | C12: -98742 | D12: -154081 | E12: -85683 | F12: -98330 | G12: -94187 | H12: -79835 | I12: -57553 | J12: -69776 | K12: -80932 | L12: -75107 | M12: -66373
A13: Investments sold | B13: 93293 | C13: 99658 | D13: 150651 | E13: 81034 | F13: 95017 | G13: 92454 | H13: 75835 | I13: 62797 | J13: 70992 | K13: 77230 | L13: 77830 | M13: 67311
... A28: Net Cash Flow | B28: -32 | C28: -93 | D28: 266 | E28: 75 | F28: -166 | G28: 169 | H28: 334 | I28: -367 | J28: -43 | K28: 139 | L28: 191 | M28: 26

Sheet Forecasting
B3: ="Forecasting - "&'Data Sheet'!B1 -> Forecasting - ITC LTD | G3: Forecasting - ITC LTD
B4: Year Weightage | C4: Year | D4: Sales | E4: YoY Growth | G4: Year Weightage | H4: Year | I4: EBITDA | J4: YoY Growth
B5: 1 | C5: 42460 | D5: 39192.1 | G5: 1 | H5: 42460 | I5: 12657.62
B6: 2 | C6: 42825 | D6: 42767.6 | E6: =(D6/D5)-1 -> 0.09123012 | G6: 2 | H6: 42825 | I6: 14896.02 | J6: =I6/I5-1 -> 0.17684209
B7: 3 | C7: 43190 | D7: 43448.94 | E7: =(D7/D6)-1 -> 0.015931219 | G7: 3 | H7: 43190 | I7: 16336.3 | J7: =I7/I6-1 -> 0.096688914
B8: 4 | C8: 43555 | D8: 48339.58 | E8: =(D8/D7)-1 -> 0.11256063 | G8: 4 | H8: 43555 | I8: 16050.57 | J8: =I8/I7-1 -> -0.017490497
B9: 5 | C9: 43921 | D9: 49387.7 | E9: =(D9/D8)-1 -> 0.021682439 | G9: 5 | H9: 43921 | I9: 15519.96 | J9: =I9/I8-1 -> -0.033058639
B10: 6 | C10: 44286 | D10: 49257.45 | E10: =(D10/D9)-1 -> -0.0026372963 | G10: 6 | H10: 44286 | I10: 13197.29 | J10: =I10/I9-1 -> -0.14965696
B11: 7 | C11: 44651 | D11: 60644.54 | E11: =(D11/D10)-1 -> 0.23117498 | G11: 7 | H11: 44651 | I11: 17341.43 | J11: =I11/I10-1 -> 0.31401447
B12: 8 | C12: 45016 | D12: 70919.03 | E12: =(D12/D11)-1 -> 0.16942152 | G12: 8 | H12: 45016 | I12: 22889.44 | J12: =I12/I11-1 -> 0.31992806
B13: 9 | C13: 45382 | D13: 67931.94 | E13: =(D13/D12)-1 -> -0.042119724 | G13: 9 | H13: 45382 | I13: 21121.54 | J13: =I13/I12-1 -> -0.07723649
B14: 10 | C14: 45747 | D14: 75323.34 | E14: =(D14/D13)-1 -> 0.10880596 | G14: 10 | H14: 45747 | I14: 6593.27 | J14: =I14/I13-1 -> -0.68784142
B15: 11 | C15: 46112 | D15: =FORECAST(B15,D5:D14,B5:B14) -> 77236.776 | E15: =(D15/D14)-1 -> 0.025402963 | G15: 11 | H15: 46112 | I15: =FORECAST(G15,I5:I14,G5:G14) -> 16437.514 | J15: =I15/I14-1 -> 1.4930746
B16: 12 | C16: 46477 | D16: =FORECAST(B16,D6:D15,B6:B15) -> 82101.898 | E16: =(D16/D15)-1 -> 0.062989714 | G16: 12 | H16: 46477 | I16: =FORECAST(G16,I6:I15,G6:G15) -> 15947.656 | J16: =I16/I15-1 -> -0.029801246
B17: 13 | C17: 46843 | D17: =FORECAST(B17,D7:D16,B7:B16) -> 87330.225 | E17: =(D17/D16)-1 -> 0.063680943 | G17: 13 | H17: 46843 | I17: =FORECAST(G17,I7:I16,G7:G16) -> 15606.768 | J17: =I17/I16-1 -> -0.021375432
B18: 14 | C18: 47208 | D18: =FORECAST(B18,D8:D17,B8:B17) -> 92209.286 | E18: =(D18/D17)-1 -> 0.055869098 | G18: 14 | H18: 47208 | I18: =FORECAST(G18,I8:I17,G8:G17) -> 15443.49 | J18: =I18/I17-1 -> -0.010461975
B19: 15 | C19: 47573 | D19: =FORECAST(B19,D9:D18,B9:B18) -> 97418.723 | E19: =(D19/D18)-1 -> 0.056495796 | G19: 15 | H19: 47573 | I19: =FORECAST(G19,I9:I18,G9:G18) -> 15187.342 | J19: =I19/I18-1 -> -0.016586136

Sheet Data Sheet
A1: COMPANY NAME | B1: ITC LTD | E1: =IF(B2<>B3, "A NEW VERSION OF THE WORKSHEET IS AVAILABLE", "")
A2: LATEST VERSION | B2: 2.1 | E2: PLEASE DO NOT MAKE ANY CHANGES TO THIS SHEET
A3: CURRENT VERSION | B3: 2.1
A5: META
A6: Number of shares | B6: =IF(B9>0, B9/B8, 0) -> 1252.8172
A7: Face Value | B7: 1
A8: Current Price | B8: 413.75
A9: Market Capitalization | B9: 518353.12
A15: PROFIT & LOSS
A16: Report Date | B16: 42460 | C16: 42825 | D16: 43190 | E16: 43555 | F16: 43921 | G16: 44286 | H16: 44651 | I16: 45016 | J16: 45382 | K16: 45747
A17: Sales | B17: 39192.1 | C17: 42767.6 | D17: 43448.94 | E17: 48339.58 | F17: 49387.7 | G17: 49257.45 | H17: 60644.54 | I17: 70919.03 | J17: 67931.94 | K17: 75323.34
A18: Raw Material Cost | B18: 13763.88 | C18: 15456.59 | D18: 14827.72 | E18: 17623.52 | F18: 18048.6 | G18: 20776.71 | H18: 27071.07 | I18: 29364.36 | J18: 27348.57 | K18: 32704.37
A19: Change in Inventory | B19: 195.38 | C19: -592.57 | D19: -1027.76 | E19: 203.19 | F19: 703.13 | G19: 645.27 | H19: 686 | I19: 358.59 | J19: 367.77 | K19: 725.65
A20: Power and Fuel | B20: 571.88 | C20: 584.33 | D20: 653.5 | E20: 746.73 | F20: 780.85 | G20: 699.56 | H20: 889.77 | I20: 1232.34 | J20: 952.9 | K20: 975.35
A21: Other Mfr. Exp | B21: 1581.59 | C21: 1683.9 | D21: 1697.62 | E21: 1871.01 | F21: 1908.29 | G21: 1587.18 | H21: 1887.67 | I21: 2327.8 | J21: 2183.76 | K21: 2345.36
A22: Employee Cost | B22: 3440.97 | C22: 3631.73 | D22: 3760.9 | E22: 4177.88 | F22: 4295.79 | G22: 4463.33 | H22: 4890.55 | I22: 5736.22 | J22: 5548.53 | K22: 6169.78
A23: Selling and admin | B23: 4261.78 | C23: 4179.74 | D23: 3954.87 | E23: 4546.39 | F23: 4488.63 | G23: 4236.77 | H23: 4858.38 | I23: 5604.08 | J23: 5312.45 | K23: 5793.29
A24: Other Expenses | B24: 1235.89 | C24: 1169.23 | D24: 1005.98 | E24: 1039.85 | F24: 1225.13 | G24: 1074.39 | H24: 1109.95 | I24: 1308.56 | J24: 1765.97 | K24: 2221.39
A25: Other Income | B25: 1483.11 | C25: 1758.63 | D25: 2239.81 | E25: 2080.44 | F25: 2417.32 | G25: 2576.95 | H25: 1909.72 | I25: 2097.64 | J25: 3330.45 | K25: 17794.88
A26: Depreciation | B26: 1077.4 | C26: 1152.79 | D26: 1236.28 | E26: 1396.61 | F26: 1644.91 | G26: 1645.59 | H26: 1732.41 | I26: 1809.01 | J26: 1518.05 | K26: 1646.32
A27: Interest | B27: 78.13 | C27: 49.03 | D27: 115.01 | E27: 71.4 | F27: 81.38 | G27: 57.97 | H27: 59.99 | I27: 77.77 | J27: 39.11 | K27: 45.06
... A31: Dividend Amount | B31: 6840.12 | C31: 5770.02 | D31: 6285.21 | E31: 7048.7 | F31: 12476.58 | G31: 13231.96 | H31: 14171.8 | I31: 19263.4 | J31: 17166.46 | K31: 17957.73
A33: EBiTDA | B33: =B30+B29+B27+B26 -> 15858.19 | C33: =C30+C29+C27+C26 -> 17040.35 | D33: =D30+D29+D27+D26 -> 18538.92 | E33: =E30+E29+E27+E26 -> 20374.26 | F33: =F30+F29+F27+F26 -> 21474.31 | G33: =G30+G29+G27+G26 -> 19420.04 | H33: =H30+H29+H27+H26 -> 22272.4 | I33: =I30+I29+I27+I26 -> 27516.84 | ... K33: =K30+K29+K27+K26 -> 43328.48
A40: Quarters
A41: Report Date | B41: 45016 | C41: 45107 | D41: 45199 | E41: 45291 | F41: 45382 | G41: 45473 | H41: 45565 | I41: 45657 | J41: 45747 | K41: 45838
A42: Sales | B42: 17634.89 | C42: 17164.46 | D42: 17774.47 | E42: 17195.24 | F42: 17037.8 | G42: 17777.81 | H42: 19990.36 | I42: 18790.17 | J42: 18765 | K42: 21494.79
A43: Expenses | B43: 11010.89 | C43: 10494.39 | D43: 11320.23 | E43: 10985.01 | F43: 10735.73 | G43: 11232.97 | H43: 13438.28 | I43: 12428.27 | J43: 12245.61 | K43: 14678.32
A44: Other Income | B44: 682.52 | C44: 722.3 | D44: 673.5 | E44: 820.26 | F44: 868 | G44: 771.13 | H44: 690.31 | I44: 803.4 | J44: 15391.28 | K44: 750.97
A45: Depreciation | B45: 461.4 | C45: 442.46 | D45: 453.04 | E45: 384.04 | F45: 385.09 | G45: 403.13 | H45: 416.18 | I45: 415.98 | J45: 411.03 | K45: 422.96
A46: Interest | B46: 12.15 | C46: 9.9 | D46: 9.87 | E46: 11.94 | F46: 10.72 | G46: 9.6 | H46: 14.73 | I46: 9.82 | J46: 10.91 | K46: 16.47
A47: Profit before tax | B47: 6832.97 | C47: 6940.01 | D47: 6664.83 | E47: 6634.51 | F47: 6774.26 | G47: 6903.24 | H47: 6811.48 | I47: 6739.5 | J47: 21488.73 | K47: 7128.01
A48: Tax | B48: 1607.95 | C48: 1759.89 | D48: 1700.31 | E48: 1227.99 | F48: 1583.55 | G48: 1726.25 | H48: 1757.05 | I48: 1726.32 | J48: 1680.85 | K48: 1784.6
A49: Net profit | B49: 5175.48 | C49: 5104.93 | D49: 4898.07 | E49: 5335.23 | F49: 5120.55 | G49: 5091.59 | H49: 4992.87 | I49: 4934.8 | J49: 19727.37 | K49: 5244.2
A50: Operating Profit | B50: 6624 | C50: 6670.07 | D50: 6454.24 | E50: 6210.23 | F50: 6302.07 | G50: 6544.84 | H50: 6552.08 | I50: 6361.9 | J50: 6519.39 | K50: 6816.47
A55: BALANCE SHEET
A56: Report Date | B56: 42460 | C56: 42825 | D56: 43190 | E56: 43555 | F56: 43921 | G56: 44286 | H56: 44651 | I56: 45016 | J56: 45382 | K56: 45747
A57: Equity Share Capital | B57: 804.72 | C57: 1214.74 | D57: 1220.43 | E57: 1225.86 | F57: 1229.22 | G57: 1230.88 | H57: 1232.33 | I57: 1242.8 | J57: 1248.47 | K57: 1251.41
A58: Reserves | B58: 41874.8 | C58: 45198.19 | D58: 51289.68 | E58: 57915.01 | F58: 64044.04 | G58: 59116.46 | H58: 61223.24 | I58: 67912.46 | J58: 73258.53 | K58: 68778.64
A59: Borrowings | B59: 83.78 | C59: 45.72 | D59: 35.92 | E59: 13.44 | F59: 277.45 | G59: 270.83 | H59: 249.44 | I59: 306.04 | J59: 303.43 | K59: 284.54
A60: Other Liabilities | B60: 8888.04 | C60: 9439.67 | D60: 11694.85 | E60: 12584.73 | F60: 11760.04 | G60: 13142.59 | H60: 14491.01 | I60: 16369.66 | J60: 16943.54 | K60: 17688.11
A61: Total | B61: 51651.34 | C61: 55898.32 | D61: 64240.88 | E61: 71739.04 | F61: 77310.75 | G61: 73760.76 | H61: 77196.02 | I61: 85830.96 | J61: 91753.97 | K61: 88002.7
A62: Net Block | B62: 15106.63 | C62: 15893.48 | D62: 16523.96 | E62: 19374.19 | F62: 21713.34 | G62: 23298.48 | H62: 24231.59 | I62: 25851.27 | J62: 27820.22 | K62: 21954.85
A63: Capital Work in Progress | B63: 2559.72 | C63: 3729.89 | D63: 5508.33 | E63: 4136.42 | F63: 3256.46 | G63: 4011.29 | H63: 3225.54 | I63: 3003.3 | J63: 2860.78 | K63: 1090.91
A64: Investments | B64: 11747.59 | C64: 17581.38 | D64: 22052.86 | E64: 25043.49 | F64: 28663.35 | G64: 24870.87 | H64: 24841.01 | I64: 29415.02 | J64: 31114.02 | K64: 34719.82
A65: Other Assets | B65: 22237.4 | C65: 18693.57 | D65: 20155.73 | E65: 23184.94 | F65: 23677.6 | G65: 21580.12 | H65: 24897.88 | I65: 27561.37 | J65: 29958.95 | K65: 30237.12
A66: Total | B66: 51651.34 | C66: 55898.32 | D66: 64240.88 | E66: 71739.04 | F66: 77310.75 | G66: 73760.76 | H66: 77196.02 | I66: 85830.96 | J66: 91753.97 | K66: 88002.7
A67: Receivables | B67: 1917.18 | C67: 2474.29 | D67: 2682.29 | E67: 4035.28 | F67: 2562.48 | G67: 2501.7 | H67: 2461.9 | I67: 2956.17 | J67: 4025.82 | K67: 4719.67
... A70: No. of Equity Shares | B70: 8047206991 | C70: 12147383071 | D70: 12204294911 | E70: 12258631601 | F70: 12292231241 | G70: 12308844231 | H70: 12323255931 | I70: 12428017741 | J70: 12484700000 | K70: 12514119781
A71: New Bonus Shares | C71: 4026657100
A72: Face value | B72: 1 | C72: 1 | D72: 1 | E72: 1 | F72: 1 | G72: 1 | H72: 1 | I72: 1 | J72: 1 | K72: 1
A74: Other Asset | B74: =B65-SUM(B67:B69) -> 5194.82 | C74: =C65-SUM(C67:C69) -> 5135.78 | D74: =D65-SUM(D67:D69) -> 7078.75 | E74: =E65-SUM(E67:E69) -> 7138.07 | F74: =F65-SUM(F67:F69) -> 4958.45 | G74: =G65-SUM(G67:G69) -> 4022.24 | H74: =H65-SUM(H67:H69) -> 6917.41 | I74: =I65-SUM(I67:I69) -> 7953.85 | ... K74: =K65-SUM(K67:K69) -> 5867.53
A80: CASH FLOW:
A81: Report Date | B81: 42460 | C81: 42825 | D81: 43190 | E81: 43555 | F81: 43921 | G81: 44286 | H81: 44651 | I81: 45016 | J81: 45382 | K81: 45747
A82: Cash from Operating Activity | B82: 9799.04 | C82: 10627.31 | D82: 13169.4 | E82: 12583.41 | F82: 14689.66 | G82: 12526.97 | H82: 15775.51 | I82: 18877.55 | J82: 17178.86 | K82: 17627.04
A83: Cash from Investing Activity | B83: -3920.73 | C83: -3250.93 | D83: -7113.89 | E83: -5545.68 | F83: -6174.02 | G83: 5739.98 | H83: -2238.49 | I83: -5732.29 | J83: 1562.77 | K83: -563.84
A84: Cash from Financing Activity | B84: -5612.52 | C84: -7301.03 | D84: -6221.13 | E84: -6868.64 | F84: -8181.48 | G84: -18633.83 | H84: -13580.5 | I84: -13006.03 | J84: -18550.96 | K84: -17037.4
A85: Net Cash Flow | B85: 265.79 | C85: 75.35 | D85: -165.62 | E85: 169.09 | F85: 334.16 | G85: -366.88 | H85: -43.48 | I85: 139.23 | J85: 190.67 | K85: 25.8
A90: PRICE: | B90: 205.13 | C90: 262.75 | D90: 239.5 | E90: 278.64 | F90: 160.95 | G90: 204.82 | H90: 234.96 | I90: 359.49 | J90: 401.53 | K90: 409.75
A92: DERIVED:
A93: Adjusted Equity Shares in Cr | B93: 1207.08 | C93: 1214.74 | D93: 1220.43 | E93: 1225.86 | F93: 1229.22 | G93: 1230.88 | H93: 1232.33 | I93: 1242.8 | J93: 1248.47 | K93: 1251.41

Sheet Quarters
A1: ='Profit & Loss'!A1 -> ITC LTD | E1: =UPDATE | J1: SCREENER.IN
A3: Narration | B3: ='Data Sheet'!B41 -> 45016 | C3: ='Data Sheet'!C41 -> 45107 | D3: ='Data Sheet'!D41 -> 45199 | E3: ='Data Sheet'!E41 -> 45291 | F3: ='Data Sheet'!F41 -> 45382 | G3: ='Data Sheet'!G41 -> 45473 | H3: ='Data Sheet'!H41 -> 45565 | I3: ='Data Sheet'!I41 -> 45657 | ... K3: ='Data Sheet'!K41 -> 45838
A4: Sales | B4: ='Data Sheet'!B42 -> 17634.89 | C4: ='Data Sheet'!C42 -> 17164.46 | D4: ='Data Sheet'!D42 -> 17774.47 | E4: ='Data Sheet'!E42 -> 17195.24 | F4: ='Data Sheet'!F42 -> 17037.8 | G4: ='Data Sheet'!G42 -> 17777.81 | H4: ='Data Sheet'!H42 -> 19990.36 | I4: ='Data Sheet'!I42 -> 18790.17 | ... K4: ='Data Sheet'!K42 -> 21494.79
A5: Expenses | B5: ='Data Sheet'!B43 -> 11010.89 | C5: ='Data Sheet'!C43 -> 10494.39 | D5: ='Data Sheet'!D43 -> 11320.23 | E5: ='Data Sheet'!E43 -> 10985.01 | F5: ='Data Sheet'!F43 -> 10735.73 | G5: ='Data Sheet'!G43 -> 11232.97 | H5: ='Data Sheet'!H43 -> 13438.28 | I5: ='Data Sheet'!I43 -> 12428.27 | ... K5: ='Data Sheet'!K43 -> 14678.32
A6: Operating Profit | B6: ='Data Sheet'!B50 -> 6624 | C6: ='Data Sheet'!C50 -> 6670.07 | D6: ='Data Sheet'!D50 -> 6454.24 | E6: ='Data Sheet'!E50 -> 6210.23 | F6: ='Data Sheet'!F50 -> 6302.07 | G6: ='Data Sheet'!G50 -> 6544.84 | H6: ='Data Sheet'!H50 -> 6552.08 | I6: ='Data Sheet'!I50 -> 6361.9 | ... K6: ='Data Sheet'!K50 -> 6816.47
A7: Other Income | B7: ='Data Sheet'!B44 -> 682.52 | C7: ='Data Sheet'!C44 -> 722.3 | D7: ='Data Sheet'!D44 -> 673.5 | E7: ='Data Sheet'!E44 -> 820.26 | F7: ='Data Sheet'!F44 -> 868 | G7: ='Data Sheet'!G44 -> 771.13 | H7: ='Data Sheet'!H44 -> 690.31 | I7: ='Data Sheet'!I44 -> 803.4 | ... K7: ='Data Sheet'!K44 -> 750.97
A8: Depreciation | B8: ='Data Sheet'!B45 -> 461.4 | C8: ='Data Sheet'!C45 -> 442.46 | D8: ='Data Sheet'!D45 -> 453.04 | E8: ='Data Sheet'!E45 -> 384.04 | F8: ='Data Sheet'!F45 -> 385.09 | G8: ='Data Sheet'!G45 -> 403.13 | H8: ='Data Sheet'!H45 -> 416.18 | I8: ='Data Sheet'!I45 -> 415.98 | ... K8: ='Data Sheet'!K45 -> 422.96
A9: Interest | B9: ='Data Sheet'!B46 -> 12.15 | C9: ='Data Sheet'!C46 -> 9.9 | D9: ='Data Sheet'!D46 -> 9.87 | E9: ='Data Sheet'!E46 -> 11.94 | F9: ='Data Sheet'!F46 -> 10.72 | G9: ='Data Sheet'!G46 -> 9.6 | H9: ='Data Sheet'!H46 -> 14.73 | I9: ='Data Sheet'!I46 -> 9.82 | ... K9: ='Data Sheet'!K46 -> 16.47
A10: Profit before tax | B10: ='Data Sheet'!B47 -> 6832.97 | C10: ='Data Sheet'!C47 -> 6940.01 | D10: ='Data Sheet'!D47 -> 6664.83 | E10: ='Data Sheet'!E47 -> 6634.51 | F10: ='Data Sheet'!F47 -> 6774.26 | G10: ='Data Sheet'!G47 -> 6903.24 | H10: ='Data Sheet'!H47 -> 6811.48 | I10: ='Data Sheet'!I47 -> 6739.5 | ... K10: ='Data Sheet'!K47 -> 7128.01
A11: Tax | B11: ='Data Sheet'!B48 -> 1607.95 | C11: ='Data Sheet'!C48 -> 1759.89 | D11: ='Data Sheet'!D48 -> 1700.31 | E11: ='Data Sheet'!E48 -> 1227.99 | F11: ='Data Sheet'!F48 -> 1583.55 | G11: ='Data Sheet'!G48 -> 1726.25 | H11: ='Data Sheet'!H48 -> 1757.05 | I11: ='Data Sheet'!I48 -> 1726.32 | ... K11: ='Data Sheet'!K48 -> 1784.6
A12: Net profit | B12: ='Data Sheet'!B49 -> 5175.48 | C12: ='Data Sheet'!C49 -> 5104.93 | D12: ='Data Sheet'!D49 -> 4898.07 | E12: ='Data Sheet'!E49 -> 5335.23 | F12: ='Data Sheet'!F49 -> 5120.55 | G12: ='Data Sheet'!G49 -> 5091.59 | H12: ='Data Sheet'!H49 -> 4992.87 | I12: ='Data Sheet'!I49 -> 4934.8 | ... K12: ='Data Sheet'!K49 -> 5244.2
A14: OPM | B14: =IF(B4>0,B6/B4,"") -> 0.37561901 | C14: =IF(C4>0,C6/C4,"") -> 0.38859772 | D14: =IF(D4>0,D6/D4,"") -> 0.36311856 | E14: =IF(E4>0,E6/E4,"") -> 0.36115983 | F14: =IF(F4>0,F6/F4,"") -> 0.36988754 | G14: =IF(G4>0,G6/G4,"") -> 0.36814658 | H14: =IF(H4>0,H6/H4,"") -> 0.32776198 | I14: =IF(I4>0,I6/I4,"") -> 0.33857597 | ... K14: =IF(K4>0,K6/K4,"") -> 0.31712196

Sheet WACC
B3: Weighted Average Cost of Capital
G6: Debt / | H6: Debt / | I6: Levered | J6: Unlevered
B7: Name of the Company | C7: Country | D7: Total Debt | E7: Total Equity | F7: Tax Rate 1 | G7: Equity | H7: Capital | I7: Beta 2 | J7: Beta 3
B9: ITC | C9: India | D9: 91.26 | E9: 70030.05 | F9: 0.25 | G9: =D9/E9 -> 0.0013031549 | H9: =D9/(D9+E9) -> 0.0013014589 | I9: ='Reg. Beta'!J13 -> 0.63865833 | J9: =I9/(1+(1-F9)*G9) -> 0.63803474
B10: Hind. Unilever | C10: India | D10: 1139 | E10: 611503.9 | F10: 0.25 | G10: =D10/E10 -> 0.001862621 | H10: =D10/(D10+E10) -> 0.0018591581 | I10: 1 | J10: =I10/(1+(1-F10)*G10) -> 0.99860498
B11: Nestle India | C11: India | D11: 279.9 | E11: 182975 | F11: 0.25 | G11: =D11/E11 -> 0.0015297172 | H11: =D11/(D11+E11) -> 0.0015273807 | I11: 1 | J11: =I11/(1+(1-F11)*G11) -> 0.99885403
B12: Britannia Inds. | C12: India | D12: 3037.7 | E12: 110690 | F12: 0.25 | G12: =D12/E12 -> 0.02744331 | H12: =D12/(D12+E12) -> 0.026710291 | I12: 1 | J12: =I12/(1+(1-F12)*G12) -> 0.97983261
B13: Godrej Consumer | C13: India | D13: 1164.5 | E13: 96256.4 | F13: 0.25 | G13: =D13/E13 -> 0.012097897 | H13: =D13/(D13+E13) -> 0.011953287 | I13: 1 | J13: =I13/(1+(1-F13)*G13) -> 0.99100816
B14: Dabur India | C14: India | D14: 1068.1 | E14: 94940.4 | F14: 0.25 | G14: =D14/E14 -> 0.011250216 | H14: =D14/(D14+E14) -> 0.011125057 | I14: 1 | J14: =I14/(1+(1-F14)*G14) -> 0.99163294
E16: Average | F16: =AVERAGE(F10:F14) -> 0.25 | G16: =AVERAGE(G10:G14) -> 0.010836752 | H16: =AVERAGE(H10:H14) -> 0.010635035 | I16: =AVERAGE(I10:I14) -> 1 | J16: =AVERAGE(J10:J14) -> 0.99198654
E17: Median | F17: =MEDIAN(F10:F14) -> 0.25 | G17: =MEDIAN(G10:G14) -> 0.011250216 | H17: =MEDIAN(H10:H14) -> 0.011125057 | I17: =MEDIAN(I10:I14) -> 1 | J17: =MEDIAN(J10:J14) -> 0.99163294
B20: Cost Of Debt | H20: Cost of Equity
B22: Pre Tax Cost of Debt | D22: 0.084 | H22: Risk Free Rate | J22: 0.065
B23: Cost of Debt | D23: 0.3 | H23: Equity Risk Premium | J23: 0.08
B24: Post Tax Cost of Debt | D24: =D22*(1-D23) -> 0.0588 | H24: Levered Beta 4 | J24: =J35 -> 0.99915519
H25: Cost of Equity | J25: =J22+(J23*J24) -> 0.14493242
B30: Capital Structure | H30: Levered Beta
D32: Current | E32: Target | H32: Comps Median Unlevered Beta | J32: =J17 -> 0.99163294
B33: Total Debt | C33: 174441 | D33: =C33/C35 -> 0.34958747 | E33: =H16 -> 0.010635035 | H33: Target Debt/Equity | J33: =E37 -> 0.010836752
B34: Market Capitalization | C34: 324550 | D34: =C34/C35 -> 0.65041253 | E34: =E35-E33 -> 0.98936497 | H34: Tax Rate | J34: =D23 -> 0.3
B35: Total Capital | C35: =C33+C34 -> 498991 | D35: 1 | E35: =D35 -> 1 | H35: Levered Beta | J35: =J32*(1+(1-J34)*J33) -> 0.99915519
B37: Debt/Equity | D37: =C33/C34 -> 0.53748575 | E37: =G16 -> 0.010836752 | H37: Weightage Cost of Capital
B39: Noted | I39: Total Cost | J39: Total Weight
B40: 1. Tax Rate considered as Marginal Tax Rate for the country | H40: Debt | I40: =D24 -> 0.0588 | J40: =E33 -> 0.010635035
B41: 2. Levered Beta is based on 5 year monthly data | H41: Equity | I41: =J25 -> 0.14493242 | J41: =E34 -> 0.98936497
B42: 3. Unlevered Beta = Levered Beta/(1+(1-Tax Rate) x Debt/Equity) | H42: WeightedAverage Cost of Capital | J42: =SUMPRODUCT(I40:I41,J40:J41) -> 0.14401639
B43: 4. Levered Beta = Unlevered Beta*(1+(1-Tax Rate) x Debt/Equity)

Sheet Balance Sheet
A1: ='Profit & Loss'!A1 -> ITC LTD | E1: =UPDATE | J1: SCREENER.IN
A3: Narration | B3: ='Data Sheet'!B56 -> 42460 | C3: ='Data Sheet'!C56 -> 42825 | D3: ='Data Sheet'!D56 -> 43190 | E3: ='Data Sheet'!E56 -> 43555 | F3: ='Data Sheet'!F56 -> 43921 | G3: ='Data Sheet'!G56 -> 44286 | H3: ='Data Sheet'!H56 -> 44651 | I3: ='Data Sheet'!I56 -> 45016 | ... K3: ='Data Sheet'!K56 -> 45747
A4: Equity Share Capital | B4: ='Data Sheet'!B57 -> 804.72 | C4: ='Data Sheet'!C57 -> 1214.74 | D4: ='Data Sheet'!D57 -> 1220.43 | E4: ='Data Sheet'!E57 -> 1225.86 | F4: ='Data Sheet'!F57 -> 1229.22 | G4: ='Data Sheet'!G57 -> 1230.88 | H4: ='Data Sheet'!H57 -> 1232.33 | I4: ='Data Sheet'!I57 -> 1242.8 | ... K4: ='Data Sheet'!K57 -> 1251.41
A5: Reserves | B5: ='Data Sheet'!B58 -> 41874.8 | C5: ='Data Sheet'!C58 -> 45198.19 | D5: ='Data Sheet'!D58 -> 51289.68 | E5: ='Data Sheet'!E58 -> 57915.01 | F5: ='Data Sheet'!F58 -> 64044.04 | G5: ='Data Sheet'!G58 -> 59116.46 | H5: ='Data Sheet'!H58 -> 61223.24 | I5: ='Data Sheet'!I58 -> 67912.46 | ... K5: ='Data Sheet'!K58 -> 68778.64
A6: Borrowings | B6: ='Data Sheet'!B59 -> 83.78 | C6: ='Data Sheet'!C59 -> 45.72 | D6: ='Data Sheet'!D59 -> 35.92 | E6: ='Data Sheet'!E59 -> 13.44 | F6: ='Data Sheet'!F59 -> 277.45 | G6: ='Data Sheet'!G59 -> 270.83 | H6: ='Data Sheet'!H59 -> 249.44 | I6: ='Data Sheet'!I59 -> 306.04 | ... K6: ='Data Sheet'!K59 -> 284.54
A7: Other Liabilities | B7: ='Data Sheet'!B60 -> 8888.04 | C7: ='Data Sheet'!C60 -> 9439.67 | D7: ='Data Sheet'!D60 -> 11694.85 | E7: ='Data Sheet'!E60 -> 12584.73 | F7: ='Data Sheet'!F60 -> 11760.04 | G7: ='Data Sheet'!G60 -> 13142.59 | H7: ='Data Sheet'!H60 -> 14491.01 | I7: ='Data Sheet'!I60 -> 16369.66 | ... K7: ='Data Sheet'!K60 -> 17688.11
A8: Total | B8: ='Data Sheet'!B61 -> 51651.34 | C8: ='Data Sheet'!C61 -> 55898.32 | D8: ='Data Sheet'!D61 -> 64240.88 | E8: ='Data Sheet'!E61 -> 71739.04 | F8: ='Data Sheet'!F61 -> 77310.75 | G8: ='Data Sheet'!G61 -> 73760.76 | H8: ='Data Sheet'!H61 -> 77196.02 | I8: ='Data Sheet'!I61 -> 85830.96 | ... K8: ='Data Sheet'!K61 -> 88002.7
A10: Net Block | B10: ='Data Sheet'!B62 -> 15106.63 | C10: ='Data Sheet'!C62 -> 15893.48 | D10: ='Data Sheet'!D62 -> 16523.96 | E10: ='Data Sheet'!E62 -> 19374.19 | F10: ='Data Sheet'!F62 -> 21713.34 | G10: ='Data Sheet'!G62 -> 23298.48 | H10: ='Data Sheet'!H62 -> 24231.59 | I10: ='Data Sheet'!I62 -> 25851.27 | ... K10: ='Data Sheet'!K62 -> 21954.85
A11: Capital Work in Progress | B11: ='Data Sheet'!B63 -> 2559.72 | C11: ='Data Sheet'!C63 -> 3729.89 | D11: ='Data Sheet'!D63 -> 5508.33 | E11: ='Data Sheet'!E63 -> 4136.42 | F11: ='Data Sheet'!F63 -> 3256.46 | G11: ='Data Sheet'!G63 -> 4011.29 | H11: ='Data Sheet'!H63 -> 3225.54 | I11: ='Data Sheet'!I63 -> 3003.3 | ... K11: ='Data Sheet'!K63 -> 1090.91
A12: Investments | B12: ='Data Sheet'!B64 -> 11747.59 | C12: ='Data Sheet'!C64 -> 17581.38 | D12: ='Data Sheet'!D64 -> 22052.86 | E12: ='Data Sheet'!E64 -> 25043.49 | F12: ='Data Sheet'!F64 -> 28663.35 | G12: ='Data Sheet'!G64 -> 24870.87 | H12: ='Data Sheet'!H64 -> 24841.01 | I12: ='Data Sheet'!I64 -> 29415.02 | ... K12: ='Data Sheet'!K64 -> 34719.82
A13: Other Assets | B13: ='Data Sheet'!B65 -> 22237.4 | C13: ='Data Sheet'!C65 -> 18693.57 | D13: ='Data Sheet'!D65 -> 20155.73 | E13: ='Data Sheet'!E65 -> 23184.94 | F13: ='Data Sheet'!F65 -> 23677.6 | G13: ='Data Sheet'!G65 -> 21580.12 | H13: ='Data Sheet'!H65 -> 24897.88 | I13: ='Data Sheet'!I65 -> 27561.37 | ... K13: ='Data Sheet'!K65 -> 30237.12
A14: Total | B14: ='Data Sheet'!B66 -> 51651.34 | C14: ='Data Sheet'!C66 -> 55898.32 | D14: ='Data Sheet'!D66 -> 64240.88 | E14: ='Data Sheet'!E66 -> 71739.04 | F14: ='Data Sheet'!F66 -> 77310.75 | G14: ='Data Sheet'!G66 -> 73760.76 | H14: ='Data Sheet'!H66 -> 77196.02 | I14: ='Data Sheet'!I66 -> 85830.96 | ... K14: ='Data Sheet'!K66 -> 88002.7
A16: Working Capital | B16: =B13-B7 -> 13349.36 | C16: =C13-C7 -> 9253.9 | D16: =D13-D7 -> 8460.88 | E16: =E13-E7 -> 10600.21 | F16: =F13-F7 -> 11917.56 | G16: =G13-G7 -> 8437.53 | H16: =H13-H7 -> 10406.87 | I16: =I13-I7 -> 11191.71 | ... K16: =K13-K7 -> 12549.01
A17: Debtors | B17: ='Data Sheet'!B67 -> 1917.18 | C17: ='Data Sheet'!C67 -> 2474.29 | D17: ='Data Sheet'!D67 -> 2682.29 | E17: ='Data Sheet'!E67 -> 4035.28 | F17: ='Data Sheet'!F67 -> 2562.48 | G17: ='Data Sheet'!G67 -> 2501.7 | H17: ='Data Sheet'!H67 -> 2461.9 | I17: ='Data Sheet'!I67 -> 2956.17 | ... K17: ='Data Sheet'!K67 -> 4719.67
A18: Inventory | B18: ='Data Sheet'!B68 -> 9062.1 | C18: ='Data Sheet'!C68 -> 8116.1 | D18: ='Data Sheet'!D68 -> 7495.09 | E18: ='Data Sheet'!E68 -> 7859.56 | F18: ='Data Sheet'!F68 -> 8879.33 | G18: ='Data Sheet'!G68 -> 10397.16 | H18: ='Data Sheet'!H68 -> 10864.15 | I18: ='Data Sheet'!I68 -> 11771.16 | ... K18: ='Data Sheet'!K68 -> 15637.56
A20: Debtor Days | B20: =IF('Profit & Loss'!B4>0,'Balance Sheet'!B17/('Profit & Loss'!B4/365),0) -> 17.854892 | C20: =IF('Profit & Loss'!C4>0,'Balance Sheet'!C17/('Profit & Loss'!C4/365),0) -> 21.116823 | D20: =IF('Profit & Loss'!D4>0,'Balance Sheet'!D17/('Profit & Loss'!D4/365),0) -> 22.53302 | E20: =IF('Profit & Loss'!E4>0,'Balance Sheet'!E17/('Profit & Loss'!E4/365),0) -> 30.469383 | F20: =IF('Profit & Loss'!F4>0,'Balance Sheet'!F17/('Profit & Loss'!F4/365),0) -> 18.938019 | G20: =IF('Profit & Loss'!G4>0,'Balance Sheet'!G17/('Profit & Loss'!G4/365),0) -> 18.537714 | H20: =IF('Profit & Loss'!H4>0,'Balance Sheet'!H17/('Profit & Loss'!H4/365),0) -> 14.817385 | I20: =IF('Profit & Loss'!I4>0,'Balance Sheet'!I17/('Profit & Loss'!I4/365),0) -> 15.214563 | ... K20: =IF('Profit & Loss'!K4>0,'Balance Sheet'!K17/('Profit & Loss'!K4/365),0) -> 22.870462
A21: Inventory Turnover | B21: =IF('Balance Sheet'!B18>0,'Profit & Loss'!B4/'Balance Sheet'!B18,0) -> 4.3248364 | C21: =IF('Balance Sheet'!C18>0,'Profit & Loss'!C4/'Balance Sheet'!C18,0) -> 5.2694767 | D21: =IF('Balance Sheet'!D18>0,'Profit & Loss'!D4/'Balance Sheet'!D18,0) -> 5.7969871 | E21: =IF('Balance Sheet'!E18>0,'Profit & Loss'!E4/'Balance Sheet'!E18,0) -> 6.1504181 | F21: =IF('Balance Sheet'!F18>0,'Profit & Loss'!F4/'Balance Sheet'!F18,0) -> 5.5620976 | G21: =IF('Balance Sheet'!G18>0,'Profit & Loss'!G4/'Balance Sheet'!G18,0) -> 4.737587 | H21: =IF('Balance Sheet'!H18>0,'Profit & Loss'!H4/'Balance Sheet'!H18,0) -> 5.5820787 | I21: =IF('Balance Sheet'!I18>0,'Profit & Loss'!I4/'Balance Sheet'!I18,0) -> 6.0248123 | ... K21: =IF('Balance Sheet'!K18>0,'Profit & Loss'!K4/'Balance Sheet'!K18,0) -> 4.8168218
A23: Return on Equity | B23: =IF(SUM('Balance Sheet'!B4:B5)>0,'Profit & Loss'!B12/SUM('Balance Sheet'!B4:B5),"") -> 0.21894459 | C23: =IF(SUM('Balance Sheet'!C4:C5)>0,'Profit & Loss'!C12/SUM('Balance Sheet'!C4:C5),"") -> 0.22169339 | D23: =IF(SUM('Balance Sheet'!D4:D5)>0,'Profit & Loss'!D12/SUM('Balance Sheet'!D4:D5),"") -> 0.21464819 | E23: =IF(SUM('Balance Sheet'!E4:E5)>0,'Profit & Loss'!E12/SUM('Balance Sheet'!E4:E5),"") -> 0.21292095 | F23: =IF(SUM('Balance Sheet'!F4:F5)>0,'Profit & Loss'!F12/SUM('Balance Sheet'!F4:F5),"") -> 0.23449465 | G23: =IF(SUM('Balance Sheet'!G4:G5)>0,'Profit & Loss'!G12/SUM('Balance Sheet'!G4:G5),"") -> 0.21809064 | H23: =IF(SUM('Balance Sheet'!H4:H5)>0,'Profit & Loss'!H12/SUM('Balance Sheet'!H4:H5),"") -> 0.24405605 | I23: =IF(SUM('Balance Sheet'!I4:I5)>0,'Profit & Loss'!I12/SUM('Balance Sheet'!I4:I5),"") -> 0.27751555 | ... K23: =IF(SUM('Balance Sheet'!K4:K5)>0,'Profit & Loss'!K12/SUM('Balance Sheet'!K4:K5),"") -> 0.49616743
A24: Return on Capital Emp | C24: =IF((B4+B5+B6+C4+C5+C6)>0,('Profit & Loss'!C10+'Profit & Loss'!C9)*2/(B4+B5+B6+C4+C5+C6),"") -> 0.36034518 | D24: =IF((C4+C5+C6+D4+D5+D6)>0,('Profit & Loss'!D10+'Profit & Loss'!D9)*2/(C4+C5+C6+D4+D5+D6),"") -> 0.35400589 | E24: =IF((D4+D5+D6+E4+E5+E6)>0,('Profit & Loss'!E10+'Profit & Loss'!E9)*2/(D4+D5+D6+E4+E5+E6),"") -> 0.34415688 | F24: =IF((E4+E5+E6+F4+F5+F6)>0,('Profit & Loss'!F10+'Profit & Loss'!F9)*2/(E4+E5+E6+F4+F5+F6),"") -> 0.32261652 | G24: =IF((F4+F5+F6+G4+G5+G6)>0,('Profit & Loss'!G10+'Profit & Loss'!G9)*2/(F4+F5+F6+G4+G5+G6),"") -> 0.28527066 | H24: =IF((G4+G5+G6+H4+H5+H6)>0,('Profit & Loss'!H10+'Profit & Loss'!H9)*2/(G4+G5+G6+H4+H5+H6),"") -> 0.33733253 | I24: =IF((H4+H5+H6+I4+I5+I6)>0,('Profit & Loss'!I10+'Profit & Loss'!I9)*2/(H4+H5+H6+I4+I5+I6),"") -> 0.39333609 | J24: =IF((I4+I5+I6+J4+J5+J6)>0,('Profit & Loss'!J10+'Profit & Loss'!J9)*2/(I4+I5+I6+J4+J5+J6),"") -> 0.37429273 | K24: =IF((J4+J5+J6+K4+K5+K6)>0,('Profit & Loss'!K10+'Profit & Loss'!K9)*2/(J4+J5+J6+K4+K5+K6),"") -> 0.57864605

Sheet Cash Flow
A1: ='Balance Sheet'!A1 -> ITC LTD | E1: =UPDATE | J1: SCREENER.IN
A3: Narration | B3: ='Data Sheet'!B81 -> 42460 | C3: ='Data Sheet'!C81 -> 42825 | D3: ='Data Sheet'!D81 -> 43190 | E3: ='Data Sheet'!E81 -> 43555 | F3: ='Data Sheet'!F81 -> 43921 | G3: ='Data Sheet'!G81 -> 44286 | H3: ='Data Sheet'!H81 -> 44651 | I3: ='Data Sheet'!I81 -> 45016 | ... K3: ='Data Sheet'!K81 -> 45747
A4: Cash from Operating Activity | B4: ='Data Sheet'!B82 -> 9799.04 | C4: ='Data Sheet'!C82 -> 10627.31 | D4: ='Data Sheet'!D82 -> 13169.4 | E4: ='Data Sheet'!E82 -> 12583.41 | F4: ='Data Sheet'!F82 -> 14689.66 | G4: ='Data Sheet'!G82 -> 12526.97 | H4: ='Data Sheet'!H82 -> 15775.51 | I4: ='Data Sheet'!I82 -> 18877.55 | ... K4: ='Data Sheet'!K82 -> 17627.04
A5: Cash from Investing Activity | B5: ='Data Sheet'!B83 -> -3920.73 | C5: ='Data Sheet'!C83 -> -3250.93 | D5: ='Data Sheet'!D83 -> -7113.89 | E5: ='Data Sheet'!E83 -> -5545.68 | F5: ='Data Sheet'!F83 -> -6174.02 | G5: ='Data Sheet'!G83 -> 5739.98 | H5: ='Data Sheet'!H83 -> -2238.49 | I5: ='Data Sheet'!I83 -> -5732.29 | ... K5: ='Data Sheet'!K83 -> -563.84
A6: Cash from Financing Activity | B6: ='Data Sheet'!B84 -> -5612.52 | C6: ='Data Sheet'!C84 -> -7301.03 | D6: ='Data Sheet'!D84 -> -6221.13 | E6: ='Data Sheet'!E84 -> -6868.64 | F6: ='Data Sheet'!F84 -> -8181.48 | G6: ='Data Sheet'!G84 -> -18633.83 | H6: ='Data Sheet'!H84 -> -13580.5 | I6: ='Data Sheet'!I84 -> -13006.03 | ... K6: ='Data Sheet'!K84 -> -17037.4
A7: Net Cash Flow | B7: ='Data Sheet'!B85 -> 265.79 | C7: ='Data Sheet'!C85 -> 75.35 | D7: ='Data Sheet'!D85 -> -165.62 | E7: ='Data Sheet'!E85 -> 169.09 | F7: ='Data Sheet'!F85 -> 334.16 | G7: ='Data Sheet'!G85 -> -366.88 | H7: ='Data Sheet'!H85 -> -43.48 | I7: ='Data Sheet'!I85 -> 139.23 | ... K7: ='Data Sheet'!K85 -> 25.8

Sheet Customization
A1: How to use it?
A3: You can customize this workbook as you want.
B4: You can add custom formating, add conditional formating, add your own formulas… do ANYTHING.
B5: Please don't edit the "Data Sheet" only.
A7: After customization, you can upload this back on Screener.
B8: Upload on: | C8: https://www.screener.in/excel/
A10: Download your customized workbooks now onwards.
B11: Now whenever you will "Export to excel" from Screener, it will export your customized file.
A14: TESTING:
B15: This is a testing feature currently.
B16: You can report any formula errors on the worksheet at: support@screener.in

Sheet Raw Data
B2: 41699 | C2: 42064 | D2: 42430 | E2: 42795 | F2: 43160 | G2: 43525 | H2: 43891 | I2: 44256 | J2: 44621 | K2: 44986 | L2: 45352 | M2: 45717 | N2: 45901
B4: Particular
B5: Equity Capital | C5: 795 | D5: 802 | E5: 805 | F5: 1215 | G5: 1220 | H5: 1226 | I5: 1229 | J5: 1231 | K5: 1232 | L5: 1243 | M5: 1248 | N5: 1251 | O5: 1253
B6: Reserves | C6: 26442 | D6: 30934 | E6: 41875 | F6: 45198 | G6: 51290 | H6: 57915 | I6: 64044 | J6: 59116 | K6: 61223 | L6: 67912 | M6: 73259 | N6: 68779 | O6: 69819
B7: Borrowings -
B8: Long term Borrowings | C8: 76 | D8: 61 | E8: 27 | F8: 18 | G8: 12 | H8: 8 | I8: 6 | J8: 6 | K8: 5 | L8: 3 | M8: 2 | N8: 0 | O8: 0
B9: Short term Borrowings | C9: 150 | D9: 195 | E9: 44 | F9: 19 | G9: 17 | H9: 2 | I9: 1 | J9: 4 | K9: 1 | L9: 35 | M9: 10 | N9: 91 | O9: 157
B10: Lease Liabilities | C10: 0 | D10: 0 | E10: 0 | F10: 0 | G10: 0 | H10: 0 | I10: 268 | J10: 261 | K10: 244 | L10: 267 | M10: 292 | N10: 193 | O10: 206
B11: Other Borrowings | C11: 16 | D11: 13 | E11: 13 | F11: 8 | G11: 7 | H11: 3 | I11: 2 | J11: 0 | K11: 0 | L11: 0 | M11: 0 | N11: 0
B12: Other Liabilities -
B13: Non controlling int | C13: 203 | D13: 225 | E13: 261 | F13: 295 | G13: 334 | H13: 343 | I13: 377 | J13: 347 | K13: 366 | L13: 384 | M13: 383 | N13: 368 | O13: 523
B14: Trade Payables | C14: 2106 | D14: 2020 | E14: 2339 | F14: 2659 | G14: 3496 | H14: 3510 | I14: 3630 | J14: 4319 | K14: 4417 | L14: 4659 | M14: 4798 | N14: 4807 | O14: 5158
B15: Advance from Customers | C15: 0 | D15: 0 | E15: 805 | F15: 495 | G15: 461 | H15: 430 | I15: 703 | J15: 811 | K15: 1278 | L15: 1295 | M15: 886 | N15: 1264
B16: Other liability items | C16: 11060 | D16: 11702 | E16: 5483 | F16: 5991 | G16: 7404 | H16: 8301 | I16: 7050 | J16: 7666 | K16: 8429 | L16: 10032 | M16: 10877 | N16: 11249 | O16: 13687
B17: Total Liabilities | C17: 40848 | D17: 45952 | E17: 51651 | F17: 55898 | G17: 64241 | H17: 71739 | I17: 77311 | J17: 73761 | K17: 77196 | L17: 85831 | M17: 91754 | N17: 88003 | O17: 90803
B19: Fixed Assets - | C19: 12921 | D19: 15303 | E19: 15107 | F19: 15893 | G19: 16524 | H19: 19374 | I19: 21713 | J19: 23298 | K19: 24232 | L19: 25851 | M19: 27820 | N19: 21955 | O19: 22400
B20: Land | C20: 1564 | D20: 1717 | E20: 1615 | F20: 1673 | G20: 1685 | H20: 2021 | I20: 2797 | J20: 2889 | K20: 2829 | L20: 2830 | M20: 2865 | N20: 1588
B21: Building | C21: 4110 | D21: 4860 | E21: 4219 | F21: 4716 | G21: 5331 | H21: 6996 | I21: 8161 | J21: 8387 | K21: 9100 | L21: 9789 | M21: 10944 | N21: 7550
B22: Plant Machinery | C22: 12633 | D22: 14667 | E22: 9112 | F22: 10384 | G22: 11453 | H22: 13316 | I22: 14625 | J22: 15307 | K22: 16912 | L22: 18480 | M22: 20718 | N22: 19423
B23: Equipments | C23: 34 | D23: 46 | E23: 27 | F23: 32 | G23: 32 | H23: 34 | I23: 40 | J23: 41 | K23: 44 | L23: 44 | M23: 53 | N23: 63
B24: Furniture n fittings | C24: 729 | D24: 805 | E24: 413 | F24: 459 | G24: 497 | H24: 644 | I24: 810 | J24: 833 | K24: 907 | L24: 1000 | M24: 1068 | N24: 282
B25: Railway sidings | C25: 2 | D25: 2 | E25: 2 | F25: 2 | G25: 2 | H25: 2 | I25: 2 | J25: 2 | K25: 2 | L25: 2 | M25: 2 | N25: 2
B26: Vehicles | C26: 120 | D26: 128 | E26: 107 | F26: 128 | G26: 140 | H26: 161 | I26: 184 | J26: 180 | K26: 179 | L26: 189 | M26: 192 | N26: 141
B27: Intangible Assets | C27: 398 | D27: 678 | E27: 563 | F27: 563 | G27: 570 | H27: 684 | I27: 684 | J27: 2734 | K27: 2744 | L27: 3490 | M27: 3505 | N27: 3622 | O27: 4280
B28: Other fixed assets | C28: 411 | D28: 458 | E28: 117 | F28: 138 | G28: 212 | H28: 234 | I28: 663 | J28: 716 | K28: 719 | L28: 786 | M28: 841 | N28: 967
B29: Gross Block | C29: 20000 | D29: 23361 | E29: 16176 | F29: 18094 | G29: 19920 | H29: 24090 | I29: 27965 | J29: 31088 | K29: 33435 | L29: 36608 | M29: 40189 | N29: 33638
B30: Accumulated Depreciation | C30: 7073 | D30: 8057 | E30: 1069 | F30: 2201 | G30: 3396 | H30: 4716 | I30: 6252 | J30: 7790 | K30: 9204 | L30: 10757 | M30: 12368 | N30: 11683
B32: CWIP | C32: 3117 | D32: 2700 | E32: 2560 | F32: 3730 | G32: 5508 | H32: 4136 | I32: 3256 | J32: 4011 | K32: 3226 | L32: 3003 | M32: 2861 | N32: 1091 | O32: 1305
B33: Investments | C33: 7284 | D33: 6943 | E33: 11748 | F33: 17581 | G33: 22053 | H33: 25043 | I33: 28663 | J33: 24871 | K33: 24841 | L33: 29415 | M33: 31114 | N33: 34720 | O33: 32548
B35: Other Assets - | C35: 17526 | D35: 21006 | E35: 22237 | F35: 18694 | G35: 20156 | H35: 23185 | I35: 23678 | J35: 21580 | K35: 24898 | L35: 27561 | M35: 29959 | N35: 30237 | O35: 34550
B36: Inventories | C36: 8255 | D36: 8587 | E36: 9062 | F36: 8116 | G36: 7495 | H36: 7860 | I36: 8879 | J36: 10397 | K36: 10864 | L36: 11771 | M36: 14153 | N36: 15638 | O36: 18763
B37: Trade receivables | C37: 2439 | D37: 1982 | E37: 1917 | F37: 2474 | G37: 2682 | H37: 4035 | I37: 2562 | J37: 2502 | K37: 2462 | L37: 2956 | M37: 4026 | N37: 4720 | O37: 6503
B38: Cash Equivalents | C38: 3490 | D38: 7896 | E38: 6063 | F38: 2967 | G38: 2900 | H38: 4152 | I38: 7277 | J38: 4659 | K38: 4654 | L38: 4880 | M38: 7218 | N38: 4012 | O38: 4046
B39: Loans n Advances | C39: 107 | D39: 150 | E39: 14 | F39: 7 | G39: 74 | H39: 67 | I39: 6 | J39: 7 | K39: 11 | L39: 13 | M39: 31 | N39: 10 | O39: 564
B40: Other asset items | C40: 3234 | D40: 2391 | E40: 5180 | F40: 5129 | G40: 7004 | H40: 7071 | I40: 4952 | J40: 4015 | K40: 6906 | L40: 7941 | M40: 4531 | N40: 5858 | O40: 4673
B41: Total Assets | C41: 40848 | D41: 45952 | E41: 51651 | F41: 55898 | G41: 64241 | H41: 71739 | I41: 77311 | J41: 73761 | K41: 77196 | L41: 85831 | M41: 91754 | N41: 88003 | O41: 90803
B48: ar 2014 | C48: 42064 | D48: 42430 | E48: 42795 | F48: 43160 | G48: 43525 | H48: 43891 | I48: 44256 | J48: 44621 | K48: 44986 | L48: 45352 | M48: 45717
B49: Cash from Operating Activity - | C49: 7344 | D49: 9843 | E49: 9799 | F49: 10627 | G49: 13169 | H49: 12583 | I49: 14690 | J49: 12527 | K49: 15776 | L49: 18878 | M49: 17179 | N49: 17627
B50: Profit from operations | C50: 13172 | D50: 14261 | E50: 15154 | F50: 16075 | G50: 17433 | H50: 18862 | I50: 19416 | J50: 17326 | K50: 20857 | L50: 26052 | M50: 26635 | N50: 26719
B51: Receivables | C51: -1546 | D51: 558 | E51: -207 | F51: -870 | G51: -964 | H51: -755 | I51: 1411 | J51: -66 | K51: -732 | L51: -884 | M51: -934 | N51: -1023
B52: Inventory | C52: -755 | D52: -505 | E52: -693 | F52: 593 | G52: 602 | H52: -359 | I52: -508 | J52: -1460 | K52: -466 | L52: -1098 | M52: -2545 | N52: -2975
B53: Payables | C53: 456 | D53: -23 | E53: 622 | F53: 321 | G53: 2098 | H53: 639 | I53: -607 | J53: 1112 | K53: 1099 | L53: 1058 | M53: 141 | N53: 1256
B54: Working capital changes | C54: -1844 | D54: 31 | E54: -277 | F54: 44 | G54: 1736 | H54: -476 | I54: 296 | J54: -413 | K54: -100 | L54: -924 | M54: -3337 | N54: -2742
B55: Direct taxes | C55: -3984 | D55: -4449 | E55: -5078 | F55: -5492 | G55: -6000 | H55: -5803 | I55: -5023 | J55: -4387 | K55: -4982 | L55: -6250 | M55: -6120 | N55: -6350
B56: Cash from Investing Activity - | C56: -3254 | D56: -5275 | E56: -3921 | F56: -3251 | G56: -7114 | H56: -5546 | I56: -6174 | J56: 5740 | K56: -2238 | L56: -5732 | M56: 1563 | N56: -564
B57: Fixed assets purchased | C57: -2887 | D57: -3300 | E57: -2348 | F57: -3122 | G57: -2878 | H57: -3169 | I57: -2441 | J57: -1837 | K57: -2142 | L57: -2743 | M57: -3563 | N57: -2279
B58: Fixed assets sold | C58: 38 | D58: 9 | E58: 8 | F58: 50 | G58: 80 | H58: 28 | I58: 27 | J58: 3 | K58: 133 | L58: 49 | M58: 107 | N58: 175
B59: Investments purchased | C59: -94242 | D59: -98742 | E59: -154081 | F59: -85683 | G59: -98330 | H59: -94187 | I59: -79835 | J59: -57553 | K59: -69776 | L59: -80932 | M59: -75107 | N59: -66373
B60: Investments sold | C60: 93293 | D60: 99658 | E60: 150651 | F60: 81034 | G60: 95017 | H60: 92454 | I60: 75835 | J60: 62797 | K60: 70992 | L60: 77230 | M60: 77830 | N60: 67311
... B75: Net Cash Flow | C75: -32 | D75: -93 | E75: 266 | F75: 75 | G75: -166 | H75: 169 | I75: 334 | J75: -367 | K75: -43 | L75: 139 | M75: 191 | N75: 26

Sheet Reg. Beta
B3: Regression Beta for 2 years
C5: ITC | F5: Nifty | I5: Beta Drifting
B6: Date | C6: Price | D6: Change % | F6: Price | G6: Change %
B7: 44885 | C7: 319.96 | D7: -0.0022 | F7: 18512.75 | G7: 0.0112 | I7: Levered Beta : | J7: =J27 -> 0.51821111
B8: 44892 | C8: 316.99 | D8: -0.0093 | F8: 18696.1 | G8: 0.0099 | I8: Weightage : | J8: 0.75
B9: 44899 | C9: 320.99 | D9: 0.0126 | F9: 18496.6 | G9: -0.0107
B10: 44906 | C10: 315.07 | D10: -0.0185 | F10: 18269 | G10: -0.0123 | I10: Market Beta : | J10: 1
B11: 44913 | C11: 307.17 | D11: -0.0251 | F11: 17806.8 | G11: -0.0253 | I11: Weightage : | J11: 0.25
B12: 44920 | C12: 311.73 | D12: 0.0148 | F12: 18105.3 | G12: 0.0168
B13: 44927 | C13: 315.02 | D13: 0.0106 | F13: 17859.45 | G13: -0.0136 | I13: Adjusted Beta: | J13: =J7*J8+J10*J11 -> 0.63865833
B14: 44934 | C14: 309.1 | D14: -0.0188 | F14: 17956.6 | G14: 0.0054
B15: 44941 | C15: 314.6 | D15: 0.0178 | F15: 18027.65 | G15: 0.004
B16: 44948 | C16: 325.32 | D16: 0.0341 | F16: 17604.35 | G16: -0.0235
B17: 44955 | C17: 357.89 | D17: 0.1001 | F17: 17854.05 | G17: 0.0142
B18: 44962 | C18: 349.15 | D18: -0.0244 | F18: 17856.5 | G18: 0.0001
B19: 44969 | C19: 360.48 | D19: 0.0325 | F19: 17944.2 | G19: 0.0049
B20: 44976 | C20: 362.08 | D20: 0.0044 | F20: 17465.8 | G20: -0.0267
B21: 44983 | C21: 361.94 | D21: -0.0004 | F21: 17594.35 | G21: 0.0074
B22: 44990 | C22: 364.81 | D22: 0.0079 | F22: 17412.9 | G22: -0.0103
B23: 44997 | C23: 353.1 | D23: -0.0321 | F23: 17100.05 | G23: -0.018
B24: 45004 | C24: 356.06 | D24: 0.0084 | F24: 16945.05 | G24: -0.0091
B25: 45011 | C25: 360.58 | D25: 0.0127 | F25: 17359.75 | G25: 0.0245 | I25: Beta 1: | J25: =SLOPE(D7:D163,G7:G163) -> 0.51821111
B26: 45018 | C26: 364.19 | D26: 0.01 | F26: 17599.15 | G26: 0.0138
B27: 45025 | C27: 371.95 | D27: 0.0213 | F27: 17828 | G27: 0.013 | I27: Beta 2: | J27: =_xlfn.COVARIANCE.S(D7:D163,G7:G163)/VAR(G7:G163) -> 0.51821111
B28: 45032 | C28: 383.85 | D28: 0.032 | F28: 17624.05 | G28: -0.0114
B29: 45039 | C29: 400.11 | D29: 0.0424 | F29: 18065 | G29: 0.025 | I29: Beta 3: | J29: {=LINEST(D7:D163,G7:G163)} -> 0.51821111 | K29: 0.0004942779
B30: 45046 | C30: 403.12 | D30: 0.0075 | F30: 18069 | G30: 0.0002
B31: 45053 | C31: 395.32 | D31: -0.0194 | F31: 18314.8 | G31: 0.0136
B32: 45060 | C32: 394.75 | D32: -0.0014 | F32: 18203.4 | G32: -0.0061
B33: 45067 | C33: 417.08 | D33: 0.0566 | F33: 18499.35 | G33: 0.0163
B34: 45074 | C34: 419.46 | D34: 0.0057 | F34: 18534.1 | G34: 0.0019
B35: 45081 | C35: 414.78 | D35: -0.0112 | F35: 18563.4 | G35: 0.0016
B36: 45088 | C36: 428.64 | D36: 0.0334 | F36: 18826 | G36: 0.0141
B37: 45095 | C37: 420.74 | D37: -0.0184 | F37: 18665.5 | G37: -0.0085
B38: 45102 | C38: 427.22 | D38: 0.0154 | F38: 19189.05 | G38: 0.028
B39: 45109 | C39: 443.11 | D39: 0.0372 | F39: 19331.8 | G39: 0.0074
B40: 45116 | C40: 447.37 | D40: 0.0096 | F40: 19564.5 | G40: 0.012
B41: 45123 | C41: 463.97 | D41: 0.0371 | F41: 19745 | G41: 0.0092
... B163: 45977 | C163: 405.45 | D163: -0.0066 | F163: 26192.15 | G163: 0.0109

Sheet Intrinsic Growth
B3: Intrinsic Growth Rate
B6: Calculation of RIOC | C6: ='Data Sheet'!B16 -> 42460 | D6: ='Data Sheet'!C16 -> 42825 | E6: ='Data Sheet'!D16 -> 43190 | F6: ='Data Sheet'!E16 -> 43555 | G6: ='Data Sheet'!F16 -> 43921 | H6: ='Data Sheet'!G16 -> 44286 | I6: ='Data Sheet'!H16 -> 44651 | J6: ='Data Sheet'!I16 -> 45016 | ... L6: ='Data Sheet'!K16 -> 45747
B8: Current Assets
B9: ='Raw Data'!B36 -> Inventories | C9: ='Raw Data'!E36 -> 9062 | D9: ='Raw Data'!F36 -> 8116 | E9: ='Raw Data'!G36 -> 7495 | F9: ='Raw Data'!H36 -> 7860 | G9: ='Raw Data'!I36 -> 8879 | H9: ='Raw Data'!J36 -> 10397 | I9: ='Raw Data'!K36 -> 10864 | J9: ='Raw Data'!L36 -> 11771 | ... L9: ='Raw Data'!N36 -> 15638
B10: ='Raw Data'!B37 -> Trade receivables | C10: ='Raw Data'!E37 -> 1917 | D10: ='Raw Data'!F37 -> 2474 | E10: ='Raw Data'!G37 -> 2682 | F10: ='Raw Data'!H37 -> 4035 | G10: ='Raw Data'!I37 -> 2562 | H10: ='Raw Data'!J37 -> 2502 | I10: ='Raw Data'!K37 -> 2462 | J10: ='Raw Data'!L37 -> 2956 | ... L10: ='Raw Data'!N37 -> 4720
B11: ='Raw Data'!B39 -> Loans n Advances | C11: ='Raw Data'!E39 -> 14 | D11: ='Raw Data'!F39 -> 7 | E11: ='Raw Data'!G39 -> 74 | F11: ='Raw Data'!H39 -> 67 | G11: ='Raw Data'!I39 -> 6 | H11: ='Raw Data'!J39 -> 7 | I11: ='Raw Data'!K39 -> 11 | J11: ='Raw Data'!L39 -> 13 | ... L11: ='Raw Data'!N39 -> 10
B12: ='Raw Data'!B40 -> Other asset items | C12: ='Raw Data'!E40 -> 5180 | D12: ='Raw Data'!F40 -> 5129 | E12: ='Raw Data'!G40 -> 7004 | F12: ='Raw Data'!H40 -> 7071 | G12: ='Raw Data'!I40 -> 4952 | H12: ='Raw Data'!J40 -> 4015 | I12: ='Raw Data'!K40 -> 6906 | J12: ='Raw Data'!L40 -> 7941 | ... L12: ='Raw Data'!N40 -> 5858
B13: Total Non Current Asset | C13: =SUM(C9:C12) -> 16173 | D13: =SUM(D9:D12) -> 15726 | E13: =SUM(E9:E12) -> 17255 | F13: =SUM(F9:F12) -> 19033 | G13: =SUM(G9:G12) -> 16399 | H13: =SUM(H9:H12) -> 16921 | I13: =SUM(I9:I12) -> 20243 | J13: =SUM(J9:J12) -> 22681 | ... L13: =SUM(L9:L12) -> 26226
B15: Current Liabilities
B16: ='Raw Data'!B14 -> Trade Payables | C16: ='Raw Data'!E14 -> 2339 | D16: ='Raw Data'!F14 -> 2659 | E16: ='Raw Data'!G14 -> 3496 | F16: ='Raw Data'!H14 -> 3510 | G16: ='Raw Data'!I14 -> 3630 | H16: ='Raw Data'!J14 -> 4319 | I16: ='Raw Data'!K14 -> 4417 | J16: ='Raw Data'!L14 -> 4659 | ... L16: ='Raw Data'!N14 -> 4807
B17: ='Raw Data'!B15 -> Advance from Customers | C17: ='Raw Data'!E15 -> 805 | D17: ='Raw Data'!F15 -> 495 | E17: ='Raw Data'!G15 -> 461 | F17: ='Raw Data'!H15 -> 430 | G17: ='Raw Data'!I15 -> 703 | H17: ='Raw Data'!J15 -> 811 | I17: ='Raw Data'!K15 -> 1278 | J17: ='Raw Data'!L15 -> 1295 | ... L17: ='Raw Data'!N15 -> 1264
B18: ='Raw Data'!B16 -> Other liability items | C18: ='Raw Data'!E16 -> 5483 | D18: ='Raw Data'!F16 -> 5991 | E18: ='Raw Data'!G16 -> 7404 | F18: ='Raw Data'!H16 -> 8301 | G18: ='Raw Data'!I16 -> 7050 | H18: ='Raw Data'!J16 -> 7666 | I18: ='Raw Data'!K16 -> 8429 | J18: ='Raw Data'!L16 -> 10032 | ... L18: ='Raw Data'!N16 -> 11249
B19: Total Current Liabilities | C19: =SUM(C16:C18) -> 8627 | D19: =SUM(D16:D18) -> 9145 | E19: =SUM(E16:E18) -> 11361 | F19: =SUM(F16:F18) -> 12241 | G19: =SUM(G16:G18) -> 11383 | H19: =SUM(H16:H18) -> 12796 | I19: =SUM(I16:I18) -> 14124 | J19: =SUM(J16:J18) -> 15986 | ... L19: =SUM(L16:L18) -> 17320
B20: Total Working Capital | C20: =C13-C19 -> 7546 | D20: =D13-D19 -> 6581 | E20: =E13-E19 -> 5894 | F20: =F13-F19 -> 6792 | G20: =G13-G19 -> 5016 | H20: =H13-H19 -> 4125 | I20: =I13-I19 -> 6119 | J20: =J13-J19 -> 6695 | ... L20: =L13-L19 -> 8906
B24: Non Current Assets
B25: ='Raw Data'!B20 -> Land | C25: ='Raw Data'!E20 -> 1615 | D25: ='Raw Data'!F20 -> 1673 | E25: ='Raw Data'!G20 -> 1685 | F25: ='Raw Data'!H20 -> 2021 | G25: ='Raw Data'!I20 -> 2797 | H25: ='Raw Data'!J20 -> 2889 | I25: ='Raw Data'!K20 -> 2829 | J25: ='Raw Data'!L20 -> 2830 | ... L25: ='Raw Data'!N20 -> 1588
B26: ='Raw Data'!B21 -> Building | C26: ='Raw Data'!E21 -> 4219 | D26: ='Raw Data'!F21 -> 4716 | E26: ='Raw Data'!G21 -> 5331 | F26: ='Raw Data'!H21 -> 6996 | G26: ='Raw Data'!I21 -> 8161 | H26: ='Raw Data'!J21 -> 8387 | I26: ='Raw Data'!K21 -> 9100 | J26: ='Raw Data'!L21 -> 9789 | ... L26: ='Raw Data'!N21 -> 7550
B27: ='Raw Data'!B22 -> Plant Machinery | C27: ='Raw Data'!E22 -> 9112 | D27: ='Raw Data'!F22 -> 10384 | E27: ='Raw Data'!G22 -> 11453 | F27: ='Raw Data'!H22 -> 13316 | G27: ='Raw Data'!I22 -> 14625 | H27: ='Raw Data'!J22 -> 15307 | I27: ='Raw Data'!K22 -> 16912 | J27: ='Raw Data'!L22 -> 18480 | ... L27: ='Raw Data'!N22 -> 19423
B28: ='Raw Data'!B23 -> Equipments | C28: ='Raw Data'!E23 -> 27 | D28: ='Raw Data'!F23 -> 32 | E28: ='Raw Data'!G23 -> 32 | F28: ='Raw Data'!H23 -> 34 | G28: ='Raw Data'!I23 -> 40 | H28: ='Raw Data'!J23 -> 41 | I28: ='Raw Data'!K23 -> 44 | J28: ='Raw Data'!L23 -> 44 | ... L28: ='Raw Data'!N23 -> 63
B29: ='Raw Data'!B24 -> Furniture n fittings | C29: ='Raw Data'!E24 -> 413 | D29: ='Raw Data'!F24 -> 459 | E29: ='Raw Data'!G24 -> 497 | F29: ='Raw Data'!H24 -> 644 | G29: ='Raw Data'!I24 -> 810 | H29: ='Raw Data'!J24 -> 833 | I29: ='Raw Data'!K24 -> 907 | J29: ='Raw Data'!L24 -> 1000 | ... L29: ='Raw Data'!N24 -> 282
B30: ='Raw Data'!B25 -> Railway sidings | C30: ='Raw Data'!E25 -> 2 | D30: ='Raw Data'!F25 -> 2 | E30: ='Raw Data'!G25 -> 2 | F30: ='Raw Data'!H25 -> 2 | G30: ='Raw Data'!I25 -> 2 | H30: ='Raw Data'!J25 -> 2 | I30: ='Raw Data'!K25 -> 2 | J30: ='Raw Data'!L25 -> 2 | ... L30: ='Raw Data'!N25 -> 2
B31: ='Raw Data'!B26 -> Vehicles | C31: ='Raw Data'!E26 -> 107 | D31: ='Raw Data'!F26 -> 128 | E31: ='Raw Data'!G26 -> 140 | F31: ='Raw Data'!H26 -> 161 | G31: ='Raw Data'!I26 -> 184 | H31: ='Raw Data'!J26 -> 180 | I31: ='Raw Data'!K26 -> 179 | J31: ='Raw Data'!L26 -> 189 | ... L31: ='Raw Data'!N26 -> 141
B32: ='Raw Data'!B27 -> Intangible Assets | C32: ='Raw Data'!E27 -> 563 | D32: ='Raw Data'!F27 -> 563 | E32: ='Raw Data'!G27 -> 570 | F32: ='Raw Data'!H27 -> 684 | G32: ='Raw Data'!I27 -> 684 | H32: ='Raw Data'!J27 -> 2734 | I32: ='Raw Data'!K27 -> 2744 | J32: ='Raw Data'!L27 -> 3490 | ... L32: ='Raw Data'!N27 -> 3622
B33: ='Raw Data'!B28 -> Other fixed assets | C33: ='Raw Data'!E28 -> 117 | D33: ='Raw Data'!F28 -> 138 | E33: ='Raw Data'!G28 -> 212 | F33: ='Raw Data'!H28 -> 234 | G33: ='Raw Data'!I28 -> 663 | H33: ='Raw Data'!J28 -> 716 | I33: ='Raw Data'!K28 -> 719 | J33: ='Raw Data'!L28 -> 786 | ... L33: ='Raw Data'!N28 -> 967
B34: ='Raw Data'!B29 -> Gross Block | C34: =SUM(C25:C33) -> 16175 | D34: =SUM(D25:D33) -> 18095 | E34: =SUM(E25:E33) -> 19922 | F34: =SUM(F25:F33) -> 24092 | G34: =SUM(G25:G33) -> 27966 | H34: =SUM(H25:H33) -> 31089 | I34: =SUM(I25:I33) -> 33436 | J34: =SUM(J25:J33) -> 36610 | ... L34: =SUM(L25:L33) -> 33638
B35: ='Raw Data'!B30 -> Accumulated Depreciation | C35: ='Raw Data'!E30 -> 1069 | D35: ='Raw Data'!F30 -> 2201 | E35: ='Raw Data'!G30 -> 3396 | F35: ='Raw Data'!H30 -> 4716 | G35: ='Raw Data'!I30 -> 6252 | H35: ='Raw Data'!J30 -> 7790 | I35: ='Raw Data'!K30 -> 9204 | J35: ='Raw Data'!L30 -> 10757 | ... L35: ='Raw Data'!N30 -> 11683
B36: Total Non Current Assets | C36: =C34-C35 -> 15106 | D36: =D34-D35 -> 15894 | E36: =E34-E35 -> 16526 | F36: =F34-F35 -> 19376 | G36: =G34-G35 -> 21714 | H36: =H34-H35 -> 23299 | I36: =I34-I35 -> 24232 | J36: =J34-J35 -> 25853 | ... L36: =L34-L35 -> 21955
B40: Capital Invested | C40: =C36+C20 -> 22652 | D40: =D36+D20 -> 22475 | E40: =E36+E20 -> 22420 | F40: =F36+F20 -> 26168 | G40: =G36+G20 -> 26730 | H40: =H36+H20 -> 27424 | I40: =I36+I20 -> 30351 | J40: =J36+J20 -> 32548 | ... L40: =L36+L20 -> 30861
B41: EBIT | C41: ='Historical Financial Statemen'!C19-'Historical Financial Statemen'!C25 -> 11580.22 | D41: ='Historical Financial Statemen'!D19-'Historical Financial Statemen'!D25 -> 13743.23 | E41: ='Historical Financial Statemen'!E19-'Historical Financial Statemen'!E25 -> 15100.02 | F41: ='Historical Financial Statemen'!F19-'Historical Financial Statemen'!F25 -> 14653.96 | G41: ='Historical Financial Statemen'!G19-'Historical Financial Statemen'!G25 -> 13875.05 | H41: ='Historical Financial Statemen'!H19-'Historical Financial Statemen'!H25 -> 11551.7 | I41: ='Historical Financial Statemen'!I19-'Historical Financial Statemen'!I25 -> 15609.02 | J41: ='Historical Financial Statemen'!J19-'Historical Financial Statemen'!J25 -> 21080.43 | ... L41: ='Historical Financial Statemen'!L19-'Historical Financial Statemen'!L25 -> 4946.95
B45: ROIC | C45: =C41/C40 -> 0.51122285 | D45: =D41/D40 -> 0.61148966 | E45: =E41/E40 -> 0.67350669 | F45: =F41/F40 -> 0.55999541 | G45: =G41/G40 -> 0.51908156 | H45: =H41/H40 -> 0.42122593 | I45: =I41/I40 -> 0.51428355 | J45: =J41/J40 -> 0.64767205 | ... L45: =L41/L40 -> 0.16029779
B51: Calculation of Reinvestment Rate | C51: ='Data Sheet'!B16 -> 42460 | D51: ='Data Sheet'!C16 -> 42825 | E51: ='Data Sheet'!D16 -> 43190 | F51: ='Data Sheet'!E16 -> 43555 | G51: ='Data Sheet'!F16 -> 43921 | H51: ='Data Sheet'!G16 -> 44286 | I51: ='Data Sheet'!H16 -> 44651 | J51: ='Data Sheet'!I16 -> 45016 | ... L51: ='Data Sheet'!K16 -> 45747
B53: Net Capex | C53: =-('Raw Data'!D57+'Raw Data'!D58) -> 3291 | D53: =-('Raw Data'!E57+'Raw Data'!E58) -> 2340 | E53: =-('Raw Data'!F57+'Raw Data'!F58) -> 3072 | F53: =-('Raw Data'!G57+'Raw Data'!G58) -> 2798 | G53: =-('Raw Data'!H57+'Raw Data'!H58) -> 3141 | H53: =-('Raw Data'!I57+'Raw Data'!I58) -> 2414 | I53: =-('Raw Data'!J57+'Raw Data'!J58) -> 1834 | J53: =-('Raw Data'!K57+'Raw Data'!K58) -> 2009 | ... L53: =-('Raw Data'!M57+'Raw Data'!M58) -> 3456
B54: Change in working | D54: =D20-C20 -> -965 | E54: =E20-D20 -> -687 | F54: =F20-E20 -> 898 | G54: =G20-F20 -> -1776 | H54: =H20-G20 -> -891 | I54: =I20-H20 -> 1994 | J54: =J20-I20 -> 576 | K54: =K20-J20 -> -515 | L54: =L20-K20 -> 2726
B56: EBIT | C56: =C41 -> 11580.22 | D56: =D41 -> 13743.23 | E56: =E41 -> 15100.02 | F56: =F41 -> 14653.96 | G56: =G41 -> 13875.05 | H56: =H41 -> 11551.7 | I56: =I41 -> 15609.02 | J56: =J41 -> 21080.43 | ... L56: =L41 -> 4946.95
B57: Marginal Tax Rate | C57: 0.25 | D57: 0.25 | E57: 0.25 | F57: 0.25 | G57: 0.25 | H57: 0.25 | I57: 0.25 | J57: 0.25 | K57: 0.25 | L57: 0.25
B58: EBIT(1-T) | C58: =C56*(1-C57) -> 8685.165 | D58: =D56*(1-D57) -> 10307.422 | E58: =E56*(1-E57) -> 11325.015 | F58: =F56*(1-F57) -> 10990.47 | G58: =G56*(1-G57) -> 10406.287 | H58: =H56*(1-H57) -> 8663.775 | I58: =I56*(1-I57) -> 11706.765 | J58: =J56*(1-J57) -> 15810.322 | ... L58: =L56*(1-L57) -> 3710.2125
B60: Reinvestment | D60: =D53+D54 -> 1375 | E60: =E53+E54 -> 2385 | F60: =F53+F54 -> 3696 | G60: =G53+G54 -> 1365 | H60: =H53+H54 -> 1523 | I60: =I53+I54 -> 3828 | J60: =J53+J54 -> 2585 | K60: =K53+K54 -> 2179 | L60: =L53+L54 -> 6182
B61: Reinvestment Rate | D61: =D60/D58 -> 0.13339901 | E61: =E60/E58 -> 0.21059575 | F61: =F60/F58 -> 0.33629135 | G61: =G60/G58 -> 0.1311707 | H61: =H60/H58 -> 0.17578942 | I61: =I60/I58 -> 0.32699042 | J61: =J60/J58 -> 0.16350078 | K61: =K60/K58 -> 0.1482049 | L61: =L60/L58 -> 1.6662118
J63: 10 Years Average | L63: =AVERAGE(E61:M61) -> 0.39484439
J64: 10 Years Median | L64: =MEDIAN(E61:M61) -> 0.19319258
B71: Calculation of Growth Rate | C71: ='Data Sheet'!B16 -> 42460 | D71: ='Data Sheet'!C16 -> 42825 | E71: ='Data Sheet'!D16 -> 43190 | F71: ='Data Sheet'!E16 -> 43555 | G71: ='Data Sheet'!F16 -> 43921 | H71: ='Data Sheet'!G16 -> 44286 | I71: ='Data Sheet'!H16 -> 44651 | J71: ='Data Sheet'!I16 -> 45016 | ... L71: ='Data Sheet'!K16 -> 45747
B73: Reinvestment Rate | D73: =D61 -> 0.13339901 | E73: =E61 -> 0.21059575 | F73: =F61 -> 0.33629135 | G73: =G61 -> 0.1311707 | H73: =H61 -> 0.17578942 | I73: =I61 -> 0.32699042 | J73: =J61 -> 0.16350078 | K73: =K61 -> 0.1482049 | L73: =L61 -> 1.6662118
B74: ROIC | D74: =D45 -> 0.61148966 | E74: =E45 -> 0.67350669 | F74: =F45 -> 0.55999541 | G74: =G45 -> 0.51908156 | H74: =H45 -> 0.42122593 | I74: =I45 -> 0.51428355 | J74: =J45 -> 0.64767205 | K74: =K45 -> 0.57657324 | L74: =L45 -> 0.16029779
B76: Growth Rate | D76: =D74*D73 -> 0.081572117 | E76: =E74*E73 -> 0.14183764 | F76: =F74*F73 -> 0.18832161 | G76: =G74*G73 -> 0.06808829 | H76: =H74*H73 -> 0.074047063 | I76: =I74*I73 -> 0.16816579 | J76: =J74*J73 -> 0.10589488 | K76: =K74*K73 -> 0.08545098 | L76: =L74*L73 -> 0.26709007
J79: 10 Years Average | L79: =AVERAGE(D76:L76) -> 0.13116316
J80: 10 Years Median | L80: =MEDIAN(E76:M76) -> 0.12386626

Sheet Common Size Statement
B3: ="Common Size Income Statement - "&'Data Sheet'!B1 -> Common Size Income Statement - ITC LTD
B5: Particular | C5: ='Data Sheet'!B$16 -> 42460 | D5: ='Data Sheet'!C$16 -> 42825 | E5: ='Data Sheet'!D$16 -> 43190 | F5: ='Data Sheet'!E$16 -> 43555 | G5: ='Data Sheet'!F$16 -> 43921 | H5: ='Data Sheet'!G$16 -> 44286 | I5: ='Data Sheet'!H$16 -> 44651 | J5: ='Data Sheet'!I$16 -> 45016 | ... L5: ='Data Sheet'!K$16 -> 45747
B7: ='Data Sheet'!A17 -> Sales | C7: ='Data Sheet'!B17/'Data Sheet'!B$17 -> 1 | D7: ='Data Sheet'!C17/'Data Sheet'!C$17 -> 1 | E7: ='Data Sheet'!D17/'Data Sheet'!D$17 -> 1 | F7: ='Data Sheet'!E17/'Data Sheet'!E$17 -> 1 | G7: ='Data Sheet'!F17/'Data Sheet'!F$17 -> 1 | H7: ='Data Sheet'!G17/'Data Sheet'!G$17 -> 1 | I7: ='Data Sheet'!H17/'Data Sheet'!H$17 -> 1 | J7: ='Data Sheet'!I17/'Data Sheet'!I$17 -> 1 | ... L7: ='Data Sheet'!K17/'Data Sheet'!K$17 -> 1
B8: ='Data Sheet'!A18 -> Raw Material Cost | C8: ='Data Sheet'!B18/'Data Sheet'!B$17 -> 0.35119016 | D8: ='Data Sheet'!C18/'Data Sheet'!C$17 -> 0.36140887 | E8: ='Data Sheet'!D18/'Data Sheet'!D$17 -> 0.3412677 | F8: ='Data Sheet'!E18/'Data Sheet'!E$17 -> 0.36457743 | G8: ='Data Sheet'!F18/'Data Sheet'!F$17 -> 0.36544727 | H8: ='Data Sheet'!G18/'Data Sheet'!G$17 -> 0.42179833 | I8: ='Data Sheet'!H18/'Data Sheet'!H$17 -> 0.44638924 | J8: ='Data Sheet'!I18/'Data Sheet'!I$17 -> 0.41405473 | ... L8: ='Data Sheet'!K18/'Data Sheet'!K$17 -> 0.4341864
B9: ='Data Sheet'!A19 -> Change in Inventory | C9: ='Data Sheet'!B19/'Data Sheet'!B$17 -> 0.0049851883 | D9: ='Data Sheet'!C19/'Data Sheet'!C$17 -> -0.013855582 | E9: ='Data Sheet'!D19/'Data Sheet'!D$17 -> -0.023654432 | F9: ='Data Sheet'!E19/'Data Sheet'!E$17 -> 0.0042033878 | G9: ='Data Sheet'!F19/'Data Sheet'!F$17 -> 0.014236946 | H9: ='Data Sheet'!G19/'Data Sheet'!G$17 -> 0.013099947 | I9: ='Data Sheet'!H19/'Data Sheet'!H$17 -> 0.011311818 | J9: ='Data Sheet'!I19/'Data Sheet'!I$17 -> 0.0050563297 | ... L9: ='Data Sheet'!K19/'Data Sheet'!K$17 -> 0.0096338001
B10: ='Data Sheet'!A20 -> Power and Fuel | C10: ='Data Sheet'!B20/'Data Sheet'!B$17 -> 0.014591716 | D10: ='Data Sheet'!C20/'Data Sheet'!C$17 -> 0.013662913 | E10: ='Data Sheet'!D20/'Data Sheet'!D$17 -> 0.015040643 | F10: ='Data Sheet'!E20/'Data Sheet'!E$17 -> 0.01544759 | G10: ='Data Sheet'!F20/'Data Sheet'!F$17 -> 0.015810617 | H10: ='Data Sheet'!G20/'Data Sheet'!G$17 -> 0.014202116 | I10: ='Data Sheet'!H20/'Data Sheet'!H$17 -> 0.01467189 | J10: ='Data Sheet'!I20/'Data Sheet'!I$17 -> 0.017376718 | ... L10: ='Data Sheet'!K20/'Data Sheet'!K$17 -> 0.012948842
B11: ='Data Sheet'!A21 -> Other Mfr. Exp | C11: ='Data Sheet'!B21/'Data Sheet'!B$17 -> 0.040354816 | D11: ='Data Sheet'!C21/'Data Sheet'!C$17 -> 0.039373264 | E11: ='Data Sheet'!D21/'Data Sheet'!D$17 -> 0.039071609 | F11: ='Data Sheet'!E21/'Data Sheet'!E$17 -> 0.038705549 | G11: ='Data Sheet'!F21/'Data Sheet'!F$17 -> 0.038638973 | H11: ='Data Sheet'!G21/'Data Sheet'!G$17 -> 0.032222131 | I11: ='Data Sheet'!H21/'Data Sheet'!H$17 -> 0.031126792 | J11: ='Data Sheet'!I21/'Data Sheet'!I$17 -> 0.032823348 | ... L11: ='Data Sheet'!K21/'Data Sheet'!K$17 -> 0.031137228
B12: ='Data Sheet'!A22 -> Employee Cost | C12: ='Data Sheet'!B22/'Data Sheet'!B$17 -> 0.087797541 | D12: ='Data Sheet'!C22/'Data Sheet'!C$17 -> 0.084917788 | E12: ='Data Sheet'!D22/'Data Sheet'!D$17 -> 0.086559074 | F12: ='Data Sheet'!E22/'Data Sheet'!E$17 -> 0.086427727 | G12: ='Data Sheet'!F22/'Data Sheet'!F$17 -> 0.086980969 | H12: ='Data Sheet'!G22/'Data Sheet'!G$17 -> 0.090612283 | I12: ='Data Sheet'!H22/'Data Sheet'!H$17 -> 0.080642874 | J12: ='Data Sheet'!I22/'Data Sheet'!I$17 -> 0.080884073 | ... L12: ='Data Sheet'!K22/'Data Sheet'!K$17 -> 0.0819106
B13: ='Data Sheet'!A23 -> Selling and admin | C13: ='Data Sheet'!B23/'Data Sheet'!B$17 -> 0.10874079 | D13: ='Data Sheet'!C23/'Data Sheet'!C$17 -> 0.09773146 | E13: ='Data Sheet'!D23/'Data Sheet'!D$17 -> 0.091023394 | F13: ='Data Sheet'!E23/'Data Sheet'!E$17 -> 0.094051086 | G13: ='Data Sheet'!F23/'Data Sheet'!F$17 -> 0.090885585 | H13: ='Data Sheet'!G23/'Data Sheet'!G$17 -> 0.086012776 | I13: ='Data Sheet'!H23/'Data Sheet'!H$17 -> 0.080112406 | J13: ='Data Sheet'!I23/'Data Sheet'!I$17 -> 0.079020821 | ... L13: ='Data Sheet'!K23/'Data Sheet'!K$17 -> 0.076912282
B14: ='Data Sheet'!A24 -> Other Expenses | C14: ='Data Sheet'!B24/'Data Sheet'!B$17 -> 0.031534161 | D14: ='Data Sheet'!C24/'Data Sheet'!C$17 -> 0.027339154 | E14: ='Data Sheet'!D24/'Data Sheet'!D$17 -> 0.023153154 | F14: ='Data Sheet'!E24/'Data Sheet'!E$17 -> 0.021511358 | G14: ='Data Sheet'!F24/'Data Sheet'!F$17 -> 0.024806379 | H14: ='Data Sheet'!G24/'Data Sheet'!G$17 -> 0.021811726 | I14: ='Data Sheet'!H24/'Data Sheet'!H$17 -> 0.018302555 | J14: ='Data Sheet'!I24/'Data Sheet'!I$17 -> 0.018451465 | ... L14: ='Data Sheet'!K24/'Data Sheet'!K$17 -> 0.02949139
B15: ='Data Sheet'!A25 -> Other Income | C15: ='Data Sheet'!B25/'Data Sheet'!B$17 -> 0.037842065 | D15: ='Data Sheet'!C25/'Data Sheet'!C$17 -> 0.041120615 | E15: ='Data Sheet'!D25/'Data Sheet'!D$17 -> 0.051550395 | F15: ='Data Sheet'!E25/'Data Sheet'!E$17 -> 0.043038024 | G15: ='Data Sheet'!F25/'Data Sheet'!F$17 -> 0.04894579 | H15: ='Data Sheet'!G25/'Data Sheet'!G$17 -> 0.052315944 | I15: ='Data Sheet'!H25/'Data Sheet'!H$17 -> 0.031490386 | J15: ='Data Sheet'!I25/'Data Sheet'!I$17 -> 0.029577957 | ... L15: ='Data Sheet'!K25/'Data Sheet'!K$17 -> 0.23624656
B16: ='Data Sheet'!A26 -> Depreciation | C16: ='Data Sheet'!B26/'Data Sheet'!B$17 -> 0.027490234 | D16: ='Data Sheet'!C26/'Data Sheet'!C$17 -> 0.026954751 | E16: ='Data Sheet'!D26/'Data Sheet'!D$17 -> 0.028453629 | F16: ='Data Sheet'!E26/'Data Sheet'!E$17 -> 0.028891645 | G16: ='Data Sheet'!F26/'Data Sheet'!F$17 -> 0.033306066 | H16: ='Data Sheet'!G26/'Data Sheet'!G$17 -> 0.033407941 | I16: ='Data Sheet'!H26/'Data Sheet'!H$17 -> 0.028566628 | J16: ='Data Sheet'!I26/'Data Sheet'!I$17 -> 0.025508104 | ... L16: ='Data Sheet'!K26/'Data Sheet'!K$17 -> 0.021856705
B17: ='Data Sheet'!A27 -> Interest | C17: ='Data Sheet'!B27/'Data Sheet'!B$17 -> 0.001993514 | D17: ='Data Sheet'!C27/'Data Sheet'!C$17 -> 0.0011464286 | E17: ='Data Sheet'!D27/'Data Sheet'!D$17 -> 0.0026470151 | F17: ='Data Sheet'!E27/'Data Sheet'!E$17 -> 0.0014770505 | G17: ='Data Sheet'!F27/'Data Sheet'!F$17 -> 0.0016477787 | H17: ='Data Sheet'!G27/'Data Sheet'!G$17 -> 0.0011768778 | I17: ='Data Sheet'!H27/'Data Sheet'!H$17 -> 0.00098920694 | J17: ='Data Sheet'!I27/'Data Sheet'!I$17 -> 0.0010966027 | ... L17: ='Data Sheet'!K27/'Data Sheet'!K$17 -> 0.00059822095
B18: ='Data Sheet'!A28 -> Profit before tax | C18: ='Data Sheet'!B28/'Data Sheet'!B$17 -> 0.37913432 | D18: ='Data Sheet'!C28/'Data Sheet'!C$17 -> 0.3747304 | E18: ='Data Sheet'!D28/'Data Sheet'!D$17 -> 0.40067974 | F18: ='Data Sheet'!E28/'Data Sheet'!E$17 -> 0.39615197 | G18: ='Data Sheet'!F28/'Data Sheet'!F$17 -> 0.4056591 | H18: ='Data Sheet'!G28/'Data Sheet'!G$17 -> 0.36417171 | I18: ='Data Sheet'!H28/'Data Sheet'!H$17 -> 0.34200062 | J18: ='Data Sheet'!I28/'Data Sheet'!I$17 -> 0.36541842 | ... L18: ='Data Sheet'!K28/'Data Sheet'!K$17 -> 0.55683869
... B20: ='Data Sheet'!A30 -> Net profit | C20: ='Data Sheet'!B30/'Data Sheet'!B$17 -> 0.23842688 | D20: ='Data Sheet'!C30/'Data Sheet'!C$17 -> 0.24058961 | E20: ='Data Sheet'!D30/'Data Sheet'!D$17 -> 0.25941254 | F20: ='Data Sheet'!E30/'Data Sheet'!E$17 -> 0.2604973 | G20: ='Data Sheet'!F30/'Data Sheet'!F$17 -> 0.30991988 | H20: ='Data Sheet'!G30/'Data Sheet'!G$17 -> 0.26719187 | I20: ='Data Sheet'!H30/'Data Sheet'!H$17 -> 0.25134431 | J20: ='Data Sheet'!I30/'Data Sheet'!I$17 -> 0.27061368 | ... L20: ='Data Sheet'!K30/'Data Sheet'!K$17 -> 0.46129964
B21: EBITDA | C21: ='Data Sheet'!B33/'Data Sheet'!B$17 -> 0.40462721 | D21: ='Data Sheet'!C33/'Data Sheet'!C$17 -> 0.39844064 | E21: ='Data Sheet'!D33/'Data Sheet'!D$17 -> 0.42668291 | F21: ='Data Sheet'!E33/'Data Sheet'!E$17 -> 0.42148194 | G21: ='Data Sheet'!F33/'Data Sheet'!F$17 -> 0.43481089 | H21: ='Data Sheet'!G33/'Data Sheet'!G$17 -> 0.39425589 | I21: ='Data Sheet'!H33/'Data Sheet'!H$17 -> 0.36726142 | J21: ='Data Sheet'!I33/'Data Sheet'!I$17 -> 0.38800361 | ... L21: ='Data Sheet'!K33/'Data Sheet'!K$17 -> 0.57523312
B28: ="Common Size Balance Sheet - "&'Data Sheet'!B1 -> Common Size Balance Sheet - ITC LTD
B30: Particular | C30: ='Data Sheet'!B16 -> 42460 | D30: ='Data Sheet'!C16 -> 42825 | E30: ='Data Sheet'!D16 -> 43190 | F30: ='Data Sheet'!E16 -> 43555 | G30: ='Data Sheet'!F16 -> 43921 | H30: ='Data Sheet'!G16 -> 44286 | I30: ='Data Sheet'!H16 -> 44651 | J30: ='Data Sheet'!I16 -> 45016 | ... L30: ='Data Sheet'!K16 -> 45747
B32: Total Liabilities | C32: ='Data Sheet'!B61/'Data Sheet'!B$61 -> 1 | D32: ='Data Sheet'!C61/'Data Sheet'!C$61 -> 1 | E32: ='Data Sheet'!D61/'Data Sheet'!D$61 -> 1 | F32: ='Data Sheet'!E61/'Data Sheet'!E$61 -> 1 | G32: ='Data Sheet'!F61/'Data Sheet'!F$61 -> 1 | H32: ='Data Sheet'!G61/'Data Sheet'!G$61 -> 1 | I32: ='Data Sheet'!H61/'Data Sheet'!H$61 -> 1 | J32: ='Data Sheet'!I61/'Data Sheet'!I$61 -> 1 | ... L32: ='Data Sheet'!K61/'Data Sheet'!K$61 -> 1
B33: ='Data Sheet'!A57 -> Equity Share Capital | C33: ='Data Sheet'!B62/'Data Sheet'!B$61 -> 0.29247315 | D33: ='Data Sheet'!C62/'Data Sheet'!C$61 -> 0.2843284 | E33: ='Data Sheet'!D62/'Data Sheet'!D$61 -> 0.25721877 | F33: ='Data Sheet'!E62/'Data Sheet'!E$61 -> 0.27006481 | G33: ='Data Sheet'!F62/'Data Sheet'!F$61 -> 0.28085797 | H33: ='Data Sheet'!G62/'Data Sheet'!G$61 -> 0.31586551 | I33: ='Data Sheet'!H62/'Data Sheet'!H$61 -> 0.31389688 | J33: ='Data Sheet'!I62/'Data Sheet'!I$61 -> 0.30118817 | ... L33: ='Data Sheet'!K62/'Data Sheet'!K$61 -> 0.24947928
B34: ='Data Sheet'!A58 -> Reserves | C34: ='Data Sheet'!B63/'Data Sheet'!B$61 -> 0.049557669 | D34: ='Data Sheet'!C63/'Data Sheet'!C$61 -> 0.066726335 | E34: ='Data Sheet'!D63/'Data Sheet'!D$61 -> 0.085744934 | F34: ='Data Sheet'!E63/'Data Sheet'!E$61 -> 0.057659261 | G34: ='Data Sheet'!F63/'Data Sheet'!F$61 -> 0.042121697 | H34: ='Data Sheet'!G63/'Data Sheet'!G$61 -> 0.054382439 | I34: ='Data Sheet'!H63/'Data Sheet'!H$61 -> 0.04178376 | J34: ='Data Sheet'!I63/'Data Sheet'!I$61 -> 0.03499087 | ... L34: ='Data Sheet'!K63/'Data Sheet'!K$61 -> 0.012396324
B35: ='Data Sheet'!A59 -> Borrowings | C35: ='Data Sheet'!B64/'Data Sheet'!B$61 -> 0.22744018 | D35: ='Data Sheet'!C64/'Data Sheet'!C$61 -> 0.3145243 | E35: ='Data Sheet'!D64/'Data Sheet'!D$61 -> 0.3432839 | F35: ='Data Sheet'!E64/'Data Sheet'!E$61 -> 0.34909151 | G35: ='Data Sheet'!F64/'Data Sheet'!F$61 -> 0.37075504 | H35: ='Data Sheet'!G64/'Data Sheet'!G$61 -> 0.33718294 | I35: ='Data Sheet'!H64/'Data Sheet'!H$61 -> 0.32179133 | J35: ='Data Sheet'!I64/'Data Sheet'!I$61 -> 0.34270874 | ... L35: ='Data Sheet'!K64/'Data Sheet'!K$61 -> 0.3945313
B36: ='Data Sheet'!A60 -> Other Liabilities | C36: ='Data Sheet'!B65/'Data Sheet'!B$61 -> 0.430529 | D36: ='Data Sheet'!C65/'Data Sheet'!C$61 -> 0.33442096 | E36: ='Data Sheet'!D65/'Data Sheet'!D$61 -> 0.3137524 | F36: ='Data Sheet'!E65/'Data Sheet'!E$61 -> 0.32318442 | G36: ='Data Sheet'!F65/'Data Sheet'!F$61 -> 0.3062653 | H36: ='Data Sheet'!G65/'Data Sheet'!G$61 -> 0.29256911 | I36: ='Data Sheet'!H65/'Data Sheet'!H$61 -> 0.32252803 | J36: ='Data Sheet'!I65/'Data Sheet'!I$61 -> 0.32111222 | ... L36: ='Data Sheet'!K65/'Data Sheet'!K$61 -> 0.34359309
B38: Total Assets | C38: ='Data Sheet'!B66/'Data Sheet'!B$66 -> 1 | D38: ='Data Sheet'!C66/'Data Sheet'!C$66 -> 1 | E38: ='Data Sheet'!D66/'Data Sheet'!D$66 -> 1 | F38: ='Data Sheet'!E66/'Data Sheet'!E$66 -> 1 | G38: ='Data Sheet'!F66/'Data Sheet'!F$66 -> 1 | H38: ='Data Sheet'!G66/'Data Sheet'!G$66 -> 1 | I38: ='Data Sheet'!H66/'Data Sheet'!H$66 -> 1 | J38: ='Data Sheet'!I66/'Data Sheet'!I$66 -> 1 | ... L38: ='Data Sheet'!K66/'Data Sheet'!K$66 -> 1
B39: ='Data Sheet'!A62 -> Net Block | C39: ='Data Sheet'!B62/'Data Sheet'!B$66 -> 0.29247315 | D39: ='[1]Data Sheet'!C62/'[1]Data Sheet'!C$66 -> 0.2843284 | E39: ='[1]Data Sheet'!D62/'[1]Data Sheet'!D$66 -> 0.25721877 | F39: ='[1]Data Sheet'!E62/'[1]Data Sheet'!E$66 -> 0.27006481 | G39: ='[1]Data Sheet'!F62/'[1]Data Sheet'!F$66 -> 0.28085797 | H39: ='[1]Data Sheet'!G62/'[1]Data Sheet'!G$66 -> 0.31586551 | I39: ='[1]Data Sheet'!H62/'[1]Data Sheet'!H$66 -> 0.31389688 | J39: ='[1]Data Sheet'!I62/'[1]Data Sheet'!I$66 -> 0.30118817 | K39: ='[1]Data Sheet'!J62/'[1]Data Sheet'!J$66 -> 0.30320454 | L39: ='[1]Data Sheet'!K62/'[1]Data Sheet'!K$66 -> 0.24947928
B40: ='Data Sheet'!A63 -> Capital Work in Progress | C40: ='Data Sheet'!B63/'Data Sheet'!B$66 -> 0.049557669 | D40: ='[1]Data Sheet'!C63/'[1]Data Sheet'!C$66 -> 0.066726335 | E40: ='[1]Data Sheet'!D63/'[1]Data Sheet'!D$66 -> 0.085744934 | F40: ='[1]Data Sheet'!E63/'[1]Data Sheet'!E$66 -> 0.057659261 | G40: ='[1]Data Sheet'!F63/'[1]Data Sheet'!F$66 -> 0.042121697 | H40: ='[1]Data Sheet'!G63/'[1]Data Sheet'!G$66 -> 0.054382439 | I40: ='[1]Data Sheet'!H63/'[1]Data Sheet'!H$66 -> 0.04178376 | J40: ='[1]Data Sheet'!I63/'[1]Data Sheet'!I$66 -> 0.03499087 | K40: ='[1]Data Sheet'!J63/'[1]Data Sheet'!J$66 -> 0.031178814 | L40: ='[1]Data Sheet'!K63/'[1]Data Sheet'!K$66 -> 0.012396324
B41: ='Data Sheet'!A64 -> Investments | C41: ='Data Sheet'!B64/'Data Sheet'!B$66 -> 0.22744018 | D41: ='[1]Data Sheet'!C64/'[1]Data Sheet'!C$66 -> 0.3145243 | E41: ='[1]Data Sheet'!D64/'[1]Data Sheet'!D$66 -> 0.3432839 | F41: ='[1]Data Sheet'!E64/'[1]Data Sheet'!E$66 -> 0.34909151 | G41: ='[1]Data Sheet'!F64/'[1]Data Sheet'!F$66 -> 0.37075504 | H41: ='[1]Data Sheet'!G64/'[1]Data Sheet'!G$66 -> 0.33718294 | I41: ='[1]Data Sheet'!H64/'[1]Data Sheet'!H$66 -> 0.32179133 | J41: ='[1]Data Sheet'!I64/'[1]Data Sheet'!I$66 -> 0.34270874 | K41: ='[1]Data Sheet'!J64/'[1]Data Sheet'!J$66 -> 0.33910271 | L41: ='[1]Data Sheet'!K64/'[1]Data Sheet'!K$66 -> 0.3945313
B42: ='Data Sheet'!A65 -> Other Assets | C42: ='Data Sheet'!B74/'Data Sheet'!B$66 -> 0.10057474 | D42: ='[1]Data Sheet'!C74/'[1]Data Sheet'!C$66 -> 0.09187718 | E42: ='[1]Data Sheet'!D74/'[1]Data Sheet'!D$66 -> 0.11019074 | F42: ='[1]Data Sheet'!E74/'[1]Data Sheet'!E$66 -> 0.099500495 | G42: ='Data Sheet'!F74/'Data Sheet'!F$66 -> 0.064136617 | H42: ='[1]Data Sheet'!G74/'[1]Data Sheet'!G$66 -> 0.054530891 | I42: ='[1]Data Sheet'!H74/'[1]Data Sheet'!H$66 -> 0.089608376 | J42: ='[1]Data Sheet'!I74/'[1]Data Sheet'!I$66 -> 0.092668776 | K42: ='Data Sheet'!J74/'Data Sheet'!J$66 -> 0.049726132 | L42: ='[1]Data Sheet'!K74/'[1]Data Sheet'!K$66 -> 0.066674432
B43: ='Data Sheet'!A66 -> Total | C43: ='Data Sheet'!B67/'Data Sheet'!B$66 -> 0.03711772 | D43: ='Data Sheet'!C67/'Data Sheet'!C$66 -> 0.044264121 | E43: ='Data Sheet'!D67/'Data Sheet'!D$66 -> 0.041753631 | F43: ='Data Sheet'!E67/'Data Sheet'!E$66 -> 0.056249428 | G43: ='Data Sheet'!F67/'Data Sheet'!F$66 -> 0.033145196 | H43: ='Data Sheet'!G67/'Data Sheet'!G$66 -> 0.033916408 | I43: ='Data Sheet'!H67/'Data Sheet'!H$66 -> 0.031891541 | J43: ='Data Sheet'!I67/'Data Sheet'!I$66 -> 0.034441768 | ... L43: ='Data Sheet'!K67/'Data Sheet'!K$66 -> 0.053630968
B44: ='Data Sheet'!A67 -> Receivables | C44: ='Data Sheet'!B68/'Data Sheet'!B$66 -> 0.17544753 | D44: ='Data Sheet'!C68/'Data Sheet'!C$66 -> 0.14519399 | E44: ='Data Sheet'!D68/'Data Sheet'!D$66 -> 0.11667166 | F44: ='Data Sheet'!E68/'Data Sheet'!E$66 -> 0.10955764 | G44: ='Data Sheet'!F68/'Data Sheet'!F$66 -> 0.11485246 | H44: ='Data Sheet'!G68/'Data Sheet'!G$66 -> 0.14095788 | I44: ='Data Sheet'!H68/'Data Sheet'!H$66 -> 0.14073459 | J44: ='Data Sheet'!I68/'Data Sheet'!I$66 -> 0.13714352 | ... L44: ='Data Sheet'!K68/'Data Sheet'!K$66 -> 0.17769409
B45: ='Data Sheet'!A68 -> Inventory | C45: ='Data Sheet'!B69/'Data Sheet'!B$66 -> 0.11738902 | D45: ='Data Sheet'!C69/'Data Sheet'!C$66 -> 0.053085674 | E45: ='Data Sheet'!D69/'Data Sheet'!D$66 -> 0.045136368 | F45: ='Data Sheet'!E69/'Data Sheet'!E$66 -> 0.057876855 | G45: ='Data Sheet'!F69/'Data Sheet'!F$66 -> 0.094131023 | H45: ='Data Sheet'!G69/'Data Sheet'!G$66 -> 0.063163937 | I45: ='Data Sheet'!H69/'Data Sheet'!H$66 -> 0.060293523 | J45: ='Data Sheet'!I69/'Data Sheet'!I$66 -> 0.056858155 | ... L45: ='Data Sheet'!K69/'Data Sheet'!K$66 -> 0.045593601

Sheet Ind.details
B2: India - Sector Data
B3: Figures in $mn
B4: Industry Name | C4: Number of Firms | D4: Capital Expenditures | E4: Depreciation & Amort | F4: CapEx/Deprecn | G4: Acquisitions | H4: Net R&D | I4: Net Cap Ex/Sales | J4: Net Cap Ex/ EBIT (1-t) | K4: Sales/ Invested Capital | L4: Reinvestment Rate | M4: Expected EBIT Growth
B5: Advertising | C5: 13 | D5: $12.26 | E5: $6.17 | F5: 1.9856 | G5: $15.70 | H5: $1.95 | I5: 0.1151 | J5: 0.9287 | K5: 4.35 | L5: 0.2298
B6: Aerospace/Defense | C6: 13 | D6: $179.86 | E6: $230.04 | F6: 0.7818 | G6: $0.00 | H6: $130.91 | I6: 0.0113 | J6: 0.0859 | K6: 2.4 | L6: 0.4169 | M6: #REF!
B7: Air Transport | C7: 6 | D7: $522.14 | E7: $907.27 | F7: 0.5755 | G7: $0.00 | H7: $0.00 | I7: -0.0524 | J7: -30.164 | K7: 0.99 | L7: 1.0076 | M7: #REF!
B8: Apparel | C8: 323 | D8: $1,319.16 | E8: $1,037.40 | F8: 1.2716 | G8: $18.02 | H8: $19.95 | I8: 0.0045 | J8: 0.1325 | K8: 2.82 | L8: 0.354 | M8: #REF!
B9: Auto & Truck | C9: 12 | D9: $2,055.74 | E9: $4,078.64 | F9: 0.504 | G9: $103.40 | H9: $106.73 | I9: -0.0237 | J9: -0.4888 | K9: 1.17 | L9: 0.855 | M9: #REF!
B10: Auto Parts | C10: 107 | D10: $1,610.95 | E10: $1,354.44 | F10: 1.1894 | G10: $188.83 | H10: $14.64 | I10: 0.0126 | J10: 0.2541 | K10: 1.94 | L10: 0.5168 | M10: #REF!
B11: Bank (Money Center) | C11: 32 | D11: $2,515.32 | E11: $9.25 | F11: NA | G11: $283.76 | H11: $0.00 | I11: 0.0286 | J11: 95.3359 | K11: 0.44 | L11: 2.2859 | M11: #REF!
B12: Banks (Regional) | C12: 5 | D12: $90.31 | E12: $0.00 | F12: NA | G12: $0.00 | H12: $0.00 | I12: 0.0405 | J12: 14.6116 | K12: 0.53 | L12: 1.9044 | M12: #REF!
B13: Beverage (Alcoholic) | C13: 19 | D13: $132.86 | E13: $94.07 | F13: 1.4122 | G13: $31.03 | H13: $1.32 | I13: 0.0198 | J13: 0.2378 | K13: 1.88 | L13: 0.5327 | M13: #REF!
B14: Beverage (Soft) | C14: 5 | D14: $1.59 | E14: $70.09 | F14: 0.0227 | G14: $0.00 | H14: $0.00 | I14: -0.0435 | J14: -0.3401 | K14: 2 | L14: 0.4991 | M14: #REF!
B15: Broadcasting | C15: 17 | D15: $182.51 | E15: $165.61 | F15: 1.102 | G15: $4.95 | H15: $0.04 | I15: 0.0065 | J15: 0.0485 | K15: 1.09 | L15: 0.9192 | M15: #REF!
B16: Brokerage & Investment Banking | C16: 174 | D16: $98.35 | E16: $60.77 | F16: 1.6182 | G16: $1.61 | H16: $0.98 | I16: 0.0057 | J16: 2.6059 | K16: 0.8 | L16: 1.2567 | M16: #REF!
B17: Building Materials | C17: 48 | D17: $294.06 | E17: $132.09 | F17: 2.2262 | G17: -$0.03 | H17: $0.48 | I17: 0.0306 | J17: 0.5502 | K17: 2.01 | L17: 0.4974 | M17: #REF!
B18: Business & Consumer Services | C18: 58 | D18: $141.80 | E18: $125.52 | F18: 1.1296 | G18: -$26.31 | H18: $0.08 | I18: -0.0016 | J18: -0.0221 | K18: 4.08 | L18: 0.2453 | M18: #REF!
B19: Cable TV | C19: 8 | D19: $207.31 | E19: $272.43 | F19: 0.761 | G19: -$0.43 | H19: $0.00 | I19: -0.0503 | J19: -0.9137 | K19: 0.98 | L19: 1.0202 | M19: #REF!
B20: Chemical (Basic) | C20: 128 | D20: $1,638.43 | E20: $741.09 | F20: 2.2109 | G20: $29.03 | H20: $4.49 | I20: 0.0365 | J20: 0.3616 | K20: 1.48 | L20: 0.6743 | M20: #REF!
B21: Chemical (Diversified) | C21: 10 | D21: $678.43 | E21: $188.10 | F21: 3.6068 | G21: $33.42 | H21: $1.67 | I21: 0.0688 | J21: 0.698 | K21: 1.94 | L21: 0.5156 | M21: #REF!
B22: Chemical (Specialty) | C22: 167 | D22: $2,136.23 | E22: $1,159.72 | F22: 1.842 | G22: $149.75 | H22: -$8.03 | I22: 0.0225 | J22: 0.2345 | K22: 2.03 | L22: 0.4914 | M22: #REF!
B23: Coal & Related Energy | C23: 2 | D23: $1,808.80 | E23: $550.30 | F23: 3.2869 | G23: $0.00 | H23: $0.79 | I23: 0.0829 | J23: 0.433 | K23: 4.04 | L23: 0.2476 | M23: #REF!
B24: Computer Services | C24: 132 | D24: $1,553.52 | E24: $2,311.91 | F24: 0.672 | G24: $1,856.96 | H24: -$15.58 | I24: 0.0118 | J24: 0.0898 | K24: 2.36 | L24: 0.4231 | M24: #REF!
... B29: Drugs (Pharmaceutical) | C29: 156 | D29: $2,186.78 | E29: $1,565.34 | F29: 1.397 | G29: $407.01 | H29: $93.17 | I29: 0.0318 | J29: 0.292 | K29: 0.93 | L29: 1.0765 | M29: #REF!
B30: Education | C30: 26 | D30: $9.19 | E30: $17.79 | F30: 0.5166 | G30: $4.21 | H30: $0.30 | I30: -0.0257 | J30: NA | K30: 0.47 | L30: 2.1481 | M30: #REF!
B31: Electrical Equipment | C31: 102 | D31: $563.66 | E31: $356.55 | F31: 1.5809 | G31: $1.61 | H31: $32.25 | I31: 0.0132 | J31: 0.2899 | K31: 1.53 | L31: 0.6528 | M31: #REF!
B32: Electronics (Consumer & Office) | C32: 8 | D32: $57.40 | E32: $14.18 | F32: 4.0468 | G32: $0.00 | H32: $0.42 | I32: 0.0249 | J32: 1.2335 | K32: 8.03 | L32: 0.1246 | M32: #REF!
B33: Electronics (General) | C33: 27 | D33: $56.80 | E33: $29.40 | F33: 1.9322 | G33: $38.20 | H33: $1.46 | I33: 0.0488 | J33: 0.761 | K33: 2.43 | L33: 0.4121 | M33: #REF!
B34: Engineering/Construction | C34: 144 | D34: $1,658.84 | E34: $1,125.75 | F34: 1.4735 | G34: $31.05 | H34: $41.38 | I34: 0.0122 | J34: 0.19 | K34: 0.98 | L34: 1.021 | M34: #REF!
B35: Entertainment | C35: 60 | D35: $108.20 | E35: $238.99 | F35: 0.4527 | G35: $14.46 | H35: $0.23 | I35: -0.0633 | J35: -0.9014 | K35: 0.68 | L35: 1.4707 | M35: #REF!
B36: Environmental & Waste Services | C36: 10 | D36: $37.59 | E36: $8.30 | F36: 4.5279 | G36: $0.00 | H36: $0.12 | I36: 0.0472 | J36: 0.3187 | K36: 5.27 | L36: 0.1897 | M36: #REF!
B37: Farming/Agriculture | C37: 57 | D37: $161.96 | E37: $119.34 | F37: 1.3572 | G37: -$3.79 | H37: $2.44 | I37: 0.0077 | J37: 0.1395 | K37: 1.5 | L37: 0.667 | M37: #REF!
B38: Financial Svcs. (Non-bank & Insurance) | C38: 254 | D38: $906.48 | E38: $620.98 | F38: 1.4598 | G38: $287.92 | H38: $0.36 | I38: 0.0114 | J38: 0.1943 | K38: 0.1 | L38: 9.6511 | M38: #REF!
B39: Food Processing | C39: 185 | D39: $1,139.24 | E39: $609.47 | F39: 1.8692 | G39: $99.59 | H39: $3.10 | I39: 0.0165 | J39: 0.3467 | K39: 2.4 | L39: 0.4169 | M39: #REF!
B40: Food Wholesalers | C40: 32 | D40: $6.99 | E40: $5.03 | F40: 1.3893 | G40: $0.00 | H40: $0.01 | I40: 0.0019 | J40: 0.2785 | K40: 6.25 | L40: 0.1599 | M40: #REF!
B41: Furn/Home Furnishings | C41: 38 | D41: $205.16 | E41: $125.41 | F41: 1.636 | G41: $258.56 | H41: $0.72 | I41: 0.0568 | J41: 1.2294 | K41: 2.84 | L41: 0.3517 | M41: #REF!
B42: Green & Renewable Energy | C42: 18 | D42: $2,209.95 | E42: $407.42 | F42: 5.4243 | G42: $155.48 | H42: $0.02 | I42: 0.6222 | J42: 1.7376 | K42: 0.18 | L42: 5.6206 | M42: #REF!
... B45: Heathcare Information and Technology | C45: 14 | D45: $245.56 | E45: $130.38 | F45: 1.8834 | G45: $0.00 | H45: -$5.96 | I45: 0.0528 | J45: 0.2745 | K45: 0.84 | L45: 1.1878 | M45: #REF!
B46: Homebuilding | C46: 1 | D46: $0.00 | E46: $0.00 | F46: NA | G46: $0.00 | H46: $0.00 | I46: 0 | J46: 0 | K46: 0.39 | L46: 2.5519 | M46: #REF!
B47: Hospitals/Healthcare Facilities | C47: 24 | D47: $359.26 | E47: $253.77 | F47: 1.4157 | G47: $37.39 | H47: -$0.23 | I47: 0.029 | J47: 0.276 | K47: 1.56 | L47: 0.6395 | M47: #REF!
B48: Hotel/Gaming | C48: 57 | D48: $148.64 | E48: $218.18 | F48: 0.6813 | G48: $2.83 | H48: -$0.29 | I48: -0.0242 | J48: -0.2882 | K48: 0.55 | L48: 1.8318 | M48: #REF!
B49: Household Products | C49: 36 | D49: $349.27 | E49: $289.44 | F49: 1.2067 | G49: $7.23 | H49: $0.23 | I49: 0.0053 | J49: 0.0346 | K49: 1.85 | L49: 0.5415 | M49: #REF!
B50: Information Services | C50: 24 | D50: $242.61 | E50: $190.99 | F50: 1.2703 | G50: $152.81 | H50: $0.80 | I50: 0.0544 | J50: NA | K50: 2.02 | L50: 0.496 | M50: #REF!
B51: Insurance (General) | C51: 2 | D51: $22.01 | E51: $20.84 | F51: 1.0561 | G51: $0.00 | H51: $0.00 | I51: 0.0006 | J51: NA | K51: 2.02 | L51: 0.4944 | M51: #REF!
B52: Insurance (Life) | C52: 7 | D52: $159.36 | E52: -$1,789.21 | F52: NA | G52: $0.00 | H52: $0.00 | I52: 0.0159 | J52: 1.083 | K52: 27.66 | L52: 0.0362 | M52: #REF!
B53: Insurance (Prop/Cas.) | C53: 2 | D53: $20.02 | E53: $7.80 | F53: 2.5667 | G53: $0.00 | H53: $0.00 | I53: 0.0018 | J53: 0.0237 | K53: 1.2 | L53: 0.8353 | M53: #REF!
B54: Investments & Asset Management | C54: 96 | D54: $123.97 | E54: $152.52 | F54: 0.8128 | G54: $0.01 | H54: $0.80 | I54: -0.0062 | J54: -0.0323 | K54: 0.24 | L54: 4.1669 | M54: #REF!
B55: Machinery | C55: 149 | D55: $364.85 | E55: $282.71 | F55: 1.2905 | G55: $47.93 | H55: -$203.97 | I55: -0.0065 | J55: -0.0811 | K55: 1.75 | L55: 0.5717 | M55: #REF!
B56: Metals & Mining | C56: 39 | D56: $3,290.71 | E56: $2,544.55 | F56: 1.2932 | G56: $50.60 | H56: $2.43 | I56: 0.015 | J56: 0.1219 | K56: 1.51 | L56: 0.6627 | M56: #REF!
B57: Office Equipment & Services | C57: 13 | D57: $11.14 | E57: $8.62 | F57: 1.2927 | G57: $0.00 | H57: $0.04 | I57: 0.0104 | J57: 0.1632 | K57: 1.98 | L57: 0.5041 | M57: #REF!
B58: Oil/Gas (Integrated) | C58: 1 | D58: $5,441.30 | E58: $3,108.80 | F58: 1.7503 | G58: $0.00 | H58: $6.76 | I58: 0.0311 | J58: 0.4489 | K58: 1.59 | L58: 0.6307 | M58: #REF!
B59: Oil/Gas (Production and Exploration) | C59: 6 | D59: $984.04 | E59: $356.79 | F59: 2.758 | G59: $0.00 | H59: $3.40 | I59: 0.1298 | J59: 0.5551 | K59: 0.77 | L59: 1.3054 | M59: #REF!
B60: Oil/Gas Distribution | C60: 11 | D60: $175.25 | E60: $308.00 | F60: 0.569 | G60: $24.60 | H60: $0.00 | I60: -0.0127 | J60: -0.1373 | K60: 2.47 | L60: 0.4047 | M60: #REF!
B61: Oilfield Svcs/Equip. | C61: 22 | D61: $20,972.77 | E61: $7,314.32 | F61: 2.8674 | G61: $303.30 | H61: $20.55 | I61: 0.0431 | J61: 1.2697 | K61: 1.72 | L61: 0.5824 | M61: #REF!
B62: Packaging & Container | C62: 79 | D62: $496.73 | E62: $241.20 | F62: 2.0595 | G62: -$0.02 | H62: $0.71 | I62: 0.0395 | J62: 0.6905 | K62: 1.48 | L62: 0.6763 | M62: #REF!
B63: Paper/Forest Products | C63: 50 | D63: $383.41 | E63: $200.15 | F63: 1.9156 | G63: $6.63 | H63: $0.81 | I63: 0.0351 | J63: 0.3674 | K63: 1.21 | L63: 0.8244 | M63: #REF!
B64: Power | C64: 30 | D64: $9,577.58 | E64: $6,046.04 | F64: 1.5841 | G64: $136.30 | H64: $11.25 | I64: 0.0496 | J64: 0.3352 | K64: 0.54 | L64: 1.8438 | M64: #REF!
B65: Precious Metals | C65: 1 | D65: $0.04 | E65: $0.00 | F65: 12.6667 | G65: $0.00 | H65: $0.00 | I65: 8.75 | J65: NA | K65: 0 | L65: 1457.25 | M65: #REF!
B66: Publishing & Newspapers | C66: 25 | D66: $22.61 | E66: $66.91 | F66: 0.3379 | G66: $5.00 | H66: $0.10 | I66: -0.0315 | J66: -0.4728 | K66: 0.8 | L66: 1.2572 | M66: #REF!
B67: R.E.I.T. | C67: 4 | D67: $0.48 | E67: $221.10 | F67: 0.0022 | G67: $167.40 | H67: $0.00 | I67: -0.0555 | J67: -0.1196 | K67: 0.1 | L67: 9.6138 | M67: #REF!
B68: Real Estate (Development) | C68: 137 | D68: $458.40 | E68: $132.47 | F68: 3.4603 | G68: -$1.07 | H68: $0.22 | I68: 0.0657 | J68: 0.4604 | K68: 0.36 | L68: 2.8133 | M68: #REF!
B69: Real Estate (General/Diversified) | C69: 15 | D69: $43.76 | E69: $91.66 | F69: 0.4774 | G69: $114.00 | H69: $0.07 | I69: 0.0372 | J69: 0.191 | K69: 0.18 | L69: 5.4532 | M69: #REF!
B70: Real Estate (Operations & Services) | C70: 30 | D70: $2.45 | E70: $24.22 | F70: 0.1011 | G70: $0.00 | H70: $0.02 | I70: -0.1214 | J70: -0.3509 | K70: 0.22 | L70: 4.4969 | M70: #REF!
B71: Recreation | C71: 11 | D71: $3.55 | E71: $18.69 | F71: 0.19 | G71: $0.00 | H71: $0.00 | I71: -0.139 | J71: -0.8794 | K71: 0.4 | L71: 2.5287 | M71: #REF!
B72: Reinsurance | C72: 1 | D72: $2.48 | E72: $0.80 | F72: 3.1 | G72: $0.00 | H72: $0.00 | I72: 0.0003 | J72: 0.0034 | K72: 1.08 | L72: 0.922 | M72: #REF!
B73: Restaurant/Dining | C73: 13 | D73: $238.22 | E73: $197.71 | F73: 1.2049 | G73: $96.36 | H73: $0.00 | I73: 0.0698 | J73: 0.8838 | K73: 1.12 | L73: 0.8959 | M73: #REF!
B74: Retail (Automotive) | C74: 4 | D74: $2.09 | E74: $2.96 | F74: 0.7058 | G74: $0.00 | H74: $0.00 | I74: -0.0041 | J74: -0.2976 | K74: 3.91 | L74: 0.2555 | M74: #REF!
B75: Retail (Building Supply) | C75: 2 | D75: $5.16 | E75: $6.35 | F75: 0.8126 | G75: $0.00 | H75: $0.00 | I75: -0.0027 | J75: -0.4739 | K75: 3.93 | L75: 0.2543 | M75: #REF!
B76: Retail (Distributors) | C76: 239 | D76: $1,877.35 | E76: $270.20 | F76: 6.9481 | G76: $66.36 | H76: $0.03 | I76: 0.0864 | J76: 3.0138 | K76: 1.85 | L76: 0.5407 | M76: #REF!
B77: Retail (General) | C77: 5 | D77: $37.17 | E77: $304.18 | F77: 0.1222 | G77: $0.00 | H77: $0.00 | I77: -0.1182 | J77: NA | K77: 0.78 | L77: 1.2789 | M77: #REF!
B78: Retail (Grocery and Food) | C78: 5 | D78: $290.52 | E78: $72.55 | F78: 4.0046 | G78: $0.00 | H78: $0.00 | I78: 0.0449 | J78: 0.7738 | K78: 2.83 | L78: 0.3533 | M78: #REF!
B79: Retail (Online) | C79: 13 | D79: $35.31 | E79: $47.83 | F79: 0.7382 | G79: $26.27 | H79: $0.43 | I79: 0.0083 | J79: NA | K79: 0.9 | L79: 1.1076 | M79: #REF!
B80: Retail (Special Lines) | C80: 28 | D80: $130.68 | E80: $208.64 | F80: 0.6263 | G80: -$0.12 | H80: $0.14 | I80: -0.0167 | J80: -0.7383 | K80: 1.57 | L80: 0.6377 | M80: #REF!
B81: Rubber& Tires | C81: 16 | D81: $867.08 | E81: $510.81 | F81: 1.6975 | G81: $0.00 | H81: $2.46 | I81: 0.0342 | J81: 0.8589 | K81: 1.32 | L81: 0.7573 | M81: #REF!
B82: Semiconductor | C82: 8 | D82: $11.17 | E82: $3.60 | F82: 3.1017 | G82: $0.00 | H82: $0.05 | I82: 0.0989 | J82: 6.4894 | K82: 0.91 | L82: 1.102 | M82: #REF!
B83: Semiconductor Equip | C83: 1 | D83: $59.90 | E83: $5.22 | F83: 11.4751 | G83: $0.00 | H83: $0.00 | I83: 0.6448 | J83: 3.1908 | K83: 0.84 | L83: 1.1841 | M83: #REF!
B84: Shipbuilding & Marine | C84: 20 | D84: $931.37 | E84: $501.20 | F84: 1.8583 | G84: $186.80 | H84: $0.00 | I84: 0.1669 | J84: 0.538 | K84: 0.34 | L84: 2.9672 | M84: #REF!
B85: Shoe | C85: 12 | D85: $59.26 | E85: $69.01 | F85: 0.8588 | G85: $0.00 | H85: $0.39 | I85: -0.0072 | J85: -0.0855 | K85: 1.61 | L85: 0.6217 | M85: #REF!
B86: Software (Entertainment) | C86: 7 | D86: $10.95 | E86: $48.87 | F86: 0.224 | G86: $12.31 | H86: $1.24 | I86: -0.0197 | J86: -0.1266 | K86: 0.35 | L86: 2.8903 | M86: #REF!
B87: Software (Internet) | C87: 7 | D87: $2.84 | E87: $2.61 | F87: 1.0873 | G87: $0.00 | H87: $0.00 | I87: 0.0071 | J87: 0.0444 | K87: 2.85 | L87: 0.3506 | M87: #REF!
B88: Software (System & Application) | C88: 74 | D88: $144.43 | E88: $159.71 | F88: 0.9043 | G88: $196.19 | H88: $32.92 | I88: 0.0444 | J88: 0.3578 | K88: 1.72 | L88: 0.5806 | M88: #REF!
B89: Steel | C89: 157 | D89: $6,002.26 | E89: $3,615.02 | F89: 1.6604 | G89: $1,294.38 | H89: $53.60 | I89: 0.0359 | J89: 0.3882 | K89: 1.42 | L89: 0.703 | M89: #REF!
B90: Telecom (Wireless) | C90: 3 | D90: $3,793.33 | E90: $7,141.80 | F90: 0.5311 | G90: $0.00 | H90: $0.00 | I90: -0.1595 | J90: -1.84 | K90: 0.41 | L90: 2.4484 | M90: #REF!
B91: Telecom. Equipment | C91: 20 | D91: $99.48 | E91: $74.33 | F91: 1.3384 | G91: $29.49 | H91: $12.54 | I91: 0.0428 | J91: 8.5531 | K91: 0.72 | L91: 1.3867 | M91: #REF!
... B96: Trucking | C96: 12 | D96: $39.14 | E96: $24.74 | F96: 1.5823 | G96: $0.00 | H96: $0.00 | I96: 0.0239 | J96: 0.3903 | K96: 2.44 | L96: 0.4096 | M96: #REF!
B97: Utility (General) | C97: 0 | D97: $0.00 | E97: $0.00 | F97: NA | G97: $0.00 | H97: $0.00 | I97: NA | J97: NA | K97: NA | L97: #VALUE! | M97: #REF!
B98: Utility (Water) | C98: 1 | D98: $0.33 | E98: $1.15 | F98: 0.2878 | G98: $0.00 | H98: $1.26 | I98: 0.0012 | J98: 0.0212 | K98: 1.52 | L98: 0.66 | M98: #REF!
B99: Total Market | C99: 4149 | D99: $91,128.20 | E99: $56,787.85 | F99: 1.6047 | G99: $7,200.64 | H99: $290.69 | I99: 0.024 | J99: 0.3592 | K99: 0.93 | L99: 1.0754 | M99: #REF!
B100: Total Market (without financials) | C100: 3577 | D100: $87,192.38 | E100: $57,704.90 | F100: 1.511 | G100: $6,627.34 | H100: $288.55 | I100: 0.0252 | J100: 0.3279 | K100: 1.29 | L100: 0.7725 | M100: #REF!
M101: #REF!

Sheet Equity Value
B3: Equity Value
B6: Calculation Of PV of FCFF | E6: ='Data Sheet'!B16 -> 42460 | F6: ='Data Sheet'!C16 -> 42825 | G6: ='Data Sheet'!D16 -> 43190 | H6: ='Data Sheet'!E16 -> 43555 | I6: ='Data Sheet'!F16 -> 43921 | J6: ='Data Sheet'!G16 -> 44286 | K6: ='Data Sheet'!H16 -> 44651 | L6: ='Data Sheet'!I16 -> 45016 | ... N6: ='Data Sheet'!K16 -> 45747
B8: EBIT | E8: ='Intrinsic Growth'!C41 -> 11580.22 | F8: ='Intrinsic Growth'!D41 -> 13743.23 | G8: ='Intrinsic Growth'!E41 -> 15100.02 | H8: ='Intrinsic Growth'!F41 -> 14653.96 | I8: ='Intrinsic Growth'!G41 -> 13875.05 | J8: ='Intrinsic Growth'!H41 -> 11551.7 | K8: ='Intrinsic Growth'!I41 -> 15609.02 | L8: ='Intrinsic Growth'!J41 -> 21080.43 | ... N8: ='Intrinsic Growth'!L41 -> 4946.95
B9: Tax Rate | E9: 0.25 | F9: 0.25 | G9: 0.25 | H9: 0.25 | I9: 0.25 | J9: 0.25 | K9: 0.25 | L9: 0.25 | M9: 0.25 | N9: 0.25
B10: EBIT(1-T) | E10: =E8*(1-E9) -> 8685.165 | F10: =F8*(1-F9) -> 10307.422 | G10: =G8*(1-G9) -> 11325.015 | H10: =H8*(1-H9) -> 10990.47 | I10: =I8*(1-I9) -> 10406.287 | J10: =J8*(1-J9) -> 8663.775 | K10: =K8*(1-K9) -> 11706.765 | L10: =L8*(1-L9) -> 15810.322 | ... N10: =N8*(1-N9) -> 3710.2125
B11: Reinvestment Rate | E11: 0.2395 | F11: 0.2395 | G11: 0.2395 | H11: 0.2395 | I11: 0.2395 | J11: 0.2395 | K11: 0.2395 | L11: 0.2395 | M11: 0.2395 | N11: 0.2395
B12: Free Cash Flow to Firm | E12: =E10*(1-E11) -> 6605.068 | F12: =F10*(1-F11) -> 7838.7948 | G12: =G10*(1-G11) -> 8612.6739 | H12: =H10*(1-H11) -> 8358.2524 | I12: =I10*(1-I11) -> 7913.9816 | J12: =J10*(1-J11) -> 6588.8009 | K12: =K10*(1-K11) -> 8902.9948 | L12: =L10*(1-L11) -> 12023.75 | ... N12: =N10*(1-N11) -> 2821.6166
B14: Mid Year Convention | F14: 0.5 | G14: =F14+1 -> 1.5 | H14: =G14+1 -> 2.5 | I14: =H14+1 -> 3.5 | J14: =I14+1 -> 4.5 | K14: =J14+1 -> 5.5 | L14: =K14+1 -> 6.5 | M14: =L14+1 -> 7.5 | N14: =M14+1 -> 8.5
B15: Discouning Factor | F15: =1/(1+WACC!$J$42)^'Equity Value'!F14 -> 0.93494029 | G15: =1/(1+WACC!$J$42)^'Equity Value'!G14 -> 0.81724379 | H15: =1/(1+WACC!$J$42)^'Equity Value'!H14 -> 0.7143637 | I15: =1/(1+WACC!$J$42)^'Equity Value'!I14 -> 0.62443485 | J15: =1/(1+WACC!$J$42)^'Equity Value'!J14 -> 0.54582684 | K15: =1/(1+WACC!$J$42)^'Equity Value'!K14 -> 0.47711452 | L15: =1/(1+WACC!$J$42)^'Equity Value'!L14 -> 0.41705217 | M15: =1/(1+WACC!$J$42)^'Equity Value'!M14 -> 0.36455087 | N15: =1/(1+WACC!$J$42)^'Equity Value'!N14 -> 0.31865878
B17: PV of FCFF | F17: =F15*F12 -> 7328.8051 | G17: =G15*G12 -> 7038.6542 | H17: =H15*H12 -> 5970.8322 | I17: =I15*I12 -> 4941.7659 | J17: =J15*J12 -> 3596.3443 | K17: =K15*K12 -> 4247.7481 | L17: =L15*L12 -> 5014.5312 | M17: =M15*M12 -> 4076.1674 | N17: =N15*N12 -> 899.13291
B21: Expected Growth Rate | E21: 0.131
B22: Terminal Growth Rate | E22: 0.0456
B23: WACC | E23: =WACC!J42 -> 0.14401639
B28: Calculation of Terminal Value | I28: Sensitivity Analysis for Enterprise Value
B29: FCFF(n + 1) | E29: =F12 -> 7838.7948 | I29: =E40 -> 68494.923 | J29: 0.12 | K29: 0.13 | L29: =E30 -> 0.14401639 | M29: 0.15 | N29: 0.16
B30: WACC | E30: =E23 -> 0.14401639 | I30: 0.02 | J30: 68092.989 | K30: 65822.17 | L30: 65822.17 | M30: 62328.603 | N30: 60956.13
B31: Terminal Growth Rate | E31: =E22 -> 0.0456 | I31: 0.03 | J31: 70868.435 | K31: 68092.989 | L31: 68092.989 | M31: 63929.821 | N31: 62328.603
B32: Terminal Value | E32: =E29/(E30-E31) -> 79649.279 | I32: =E31 -> 0.0456 | J32: 70868.435 | K32: 68092.989 | L32: 68092.989 | M32: 63929.821 | N32: 62328.603
I33: 0.05 | J33: 78798.279 | K33: 74337.741 | L33: 74337.741 | M33: 68092.989 | N33: 65822.17
I34: 0.06 | J34: 84745.661 | K34: 78798.279 | L34: 78798.279 | M34: 70868.435 | N34: 68092.989
B37: Calculation of Equity Value per Share
B38: PV of FCFF | E38: =SUM(F17:N17) -> 43113.981
B39: PV of Terminal Value | E39: =E32*N15 -> 25380.942
B40: Value of Operating Assets | E40: =E38+E39 -> 68494.923 | I40: Sensitivity Analysis for Equity Value
I41: =E48 -> 57.750072 | J41: 0.12 | K41: 0.13 | L41: =E30 -> 0.14401639 | M41: 0.15 | N41: 0.16
B42: Cash | E42: ='Data Sheet'!K69 -> 4012.36 | I42: 0.02 | J42: 57.429247 | K42: 55.616677 | L42: 55.616677 | M42: 52.828108 | N42: 51.732599
B43: Debt | E43: ='Raw Data'!O8+'Raw Data'!O9 -> 157 | I43: 0.03 | J43: 59.644611 | K43: 57.429247 | L43: 57.429247 | M43: 54.106202 | N43: 52.828108
I44: =E31 -> 0.0456 | J44: 59.644611 | K44: 57.429247 | L44: 57.429247 | M44: 54.106202 | N44: 52.828108
B45: Value of Equity | E45: =E40+E42-E43 -> 72350.283 | I45: 0.05 | J45: 65.97422 | K45: 62.413815 | L45: 62.413815 | M45: 57.429247 | N45: 55.616677
B46: No. of Shares | E46: ='Data Sheet'!B6 -> 1252.8172 | I46: 0.06 | J46: 70.721428 | K46: 65.97422 | L46: 65.97422 | M46: 59.644611 | N46: 57.429247
B48: Equity Value | E48: =E45/E46 -> 57.750072

Sheet Sheet2
B2: S.No. | C2: Name | D2: CMP Rs. | E2: No. Eq. Shares Cr. | F2: Debt Rs.Cr. | G2: Cash End Rs.Cr. | H2: EV Rs.Cr. | I2: Sales Rs.Cr. | J2: EV / EBITDA | K2: Mar Cap Rs.Cr. | L2: NP 12M Rs.Cr. | M2: Net Debt
B3: 1 | C3: Hind. Unilever | D3: 2451.7 | E3: 234.96 | F3: 1775 | G3: 7554 | H3: 573299.16 | I3: 64243 | J3: 36.64 | K3: 575966.16 | L3: 10926 | M3: =F3-G3 -> -5779
B4: 2 | C4: ITC | D4: 404.3 | E4: 1252.88 | F4: 362.97 | G4: 4012.36 | H4: 502917.53 | I4: 78551.59 | J4: 17.26 | K4: 506600.92 | L4: 35351.02 | M4: =F4-G4 -> -3649.39
B5: 3 | C5: Hindustan Foods | D5: 538.25 | E5: 11.95 | F5: 900.81 | G5: 83.62 | H5: 7262.89 | I5: 3846.38 | J5: 21.83 | K5: 6439.44 | L5: 126.41 | M5: =F5-G5 -> 817.19
B6: 4 | C6: Godavari Bioref. | D6: 243.8 | E6: 5.12 | F6: 492.54 | G6: 31.38 | H6: 1704.16 | I6: 1990.76 | J6: 10.43 | K6: 1249.64 | L6: 20.08 | M6: =F6-G6 -> 461.16
B7: 5 | C7: Davangere Sugar | D7: 3.99 | E7: 143 | F7: 199.76 | G7: 3.38 | H7: 758.36 | I7: 202.35 | J7: 13.38 | K7: 570.57 | L7: 12.64 | M7: =F7-G7 -> 196.38
C8: Median: 5 Co. | D8: 404.3 | E8: 143 | F8: 492.54 | G8: 83.62 | H8: 7262.89 | I8: 3846.38 | J8: 17.26 | K8: 6439.44 | L8: 126.41 | M8: =F8-G8 -> 408.92

Sheet Comps_Val
B3: Comparable Company Valuation
C6: Market Data | J6: Financials | N6: Valuation
B7: Company | C7: Ticker | D7: Share Price | E7: Share Outstanding | F7: Equity Value | G7: Net Debt | H7: Enterprise Value | J7: Revenue | K7: EBITDA | L7: Net Income | N7: EV/Revenue | O7: EV/EBITDA | P7: P/E
B9: =Sheet2!C3 -> Hind. Unilever | D9: =Sheet2!D3 -> 2451.7 | E9: =Sheet2!E3 -> 234.96 | F9: =Comps_Val!D9*Comps_Val!E9 -> 576051.43 | G9: =Sheet2!M3 -> -5779 | H9: =F9+G9 -> 570272.43 | J9: =Sheet2!I3 -> 64243 | K9: =1/Sheet2!J3*Sheet2!H3 -> 15646.811 | L9: =Sheet2!L3 -> 10926 | N9: =H9/J9 -> 8.8768026 | O9: =H9/K9 -> 36.446559 | P9: =F9/L9 -> 52.722994
B10: =Sheet2!C4 -> ITC | D10: =Sheet2!D4 -> 404.3 | E10: =Sheet2!E4 -> 1252.88 | F10: =Comps_Val!D10*Comps_Val!E10 -> 506539.38 | G10: =Sheet2!M4 -> -3649.39 | H10: =F10+G10 -> 502889.99 | J10: =Sheet2!I4 -> 78551.59 | K10: =1/Sheet2!J4*Sheet2!H4 -> 29137.748 | L10: =Sheet2!L4 -> 35351.02 | N10: =H10/J10 -> 6.4020346 | O10: =H10/K10 -> 17.259055 | P10: =F10/L10 -> 14.328848
B11: =Sheet2!C5 -> Hindustan Foods | D11: =Sheet2!D5 -> 538.25 | E11: =Sheet2!E5 -> 11.95 | F11: =Comps_Val!D11*Comps_Val!E11 -> 6432.0875 | G11: =Sheet2!M5 -> 817.19 | H11: =F11+G11 -> 7249.2775 | J11: =Sheet2!I5 -> 3846.38 | K11: =1/Sheet2!J5*Sheet2!H5 -> 332.70224 | L11: =Sheet2!L5 -> 126.41 | N11: =H11/J11 -> 1.8847013 | O11: =H11/K11 -> 21.789085 | P11: =F11/L11 -> 50.882743
B12: =Sheet2!C6 -> Godavari Bioref. | D12: =Sheet2!D6 -> 243.8 | E12: =Sheet2!E6 -> 5.12 | F12: =Comps_Val!D12*Comps_Val!E12 -> 1248.256 | G12: =Sheet2!M6 -> 461.16 | H12: =F12+G12 -> 1709.416 | J12: =Sheet2!I6 -> 1990.76 | K12: =1/Sheet2!J6*Sheet2!H6 -> 163.39022 | L12: =Sheet2!L6 -> 20.08 | N12: =H12/J12 -> 0.85867508 | O12: =H12/K12 -> 10.462168 | P12: =F12/L12 -> 62.164143
B13: =Sheet2!C7 -> Davangere Sugar | D13: =Sheet2!D7 -> 3.99 | E13: =Sheet2!E7 -> 143 | F13: =Comps_Val!D13*Comps_Val!E13 -> 570.57 | G13: =Sheet2!M7 -> 196.38 | H13: =F13+G13 -> 766.95 | J13: =Sheet2!I7 -> 202.35 | K13: =1/Sheet2!J7*Sheet2!H7 -> 56.678625 | L13: =Sheet2!L7 -> 12.64 | N13: =H13/J13 -> 3.790215 | O13: =H13/K13 -> 13.531556 | P13: =F13/L13 -> 45.140032
B15: High | N15: =MAX(N9:N13) -> 8.8768026 | O15: =MAX(O9:O13) -> 36.446559 | P15: =MAX(P9:P13) -> 62.164143
B16: 75th Percentile | N16: =QUARTILE(N9:N13,3) -> 6.4020346 | O16: =QUARTILE(O9:O13,3) -> 21.789085 | P16: =QUARTILE(P9:P13,3) -> 52.722994
B17: Average | N17: =AVERAGE(N9:N13) -> 4.3624857 | O17: =AVERAGE(O9:O13) -> 19.897685 | P17: =AVERAGE(P9:P13) -> 45.047752
B18: Median | N18: =MEDIAN(N9:N13) -> 3.790215 | O18: =MEDIAN(O9:O13) -> 17.259055 | P18: =MEDIAN(P9:P13) -> 50.882743
B19: 25th Percentile | N19: =QUARTILE(N9:N13,1) -> 1.8847013 | O19: =QUARTILE(O9:O13,1) -> 13.531556 | P19: =QUARTILE(P9:P13,1) -> 45.140032
B20: Low | N20: =MIN(N9:N13) -> 0.85867508 | O20: =MIN(O9:O13) -> 10.462168 | P20: =MIN(P9:P13) -> 14.328848
B22: ITC Comparable Valuation | N22: EV/Revenue | O22: EV/EBITDA | P22: P/E
B23: Implied Enterprise Value | N23: =N18*J10 -> 297727.41 | O23: =O18*K10 -> 502889.99 | P23: =P25+P24 -> 1795107.5
B24: Net Debt | N24: =G10 -> -3649.39 | O24: =N24 -> -3649.39 | P24: =O24 -> -3649.39
B25: Implied Market Value | N25: =N24+N23 -> 294078.02 | O25: =O24+O23 -> 499240.6 | P25: =P18*L10 -> 1798756.9
B26: Shares Outstanding | N26: =$E$10 -> 1252.88 | O26: =$E$10 -> 1252.88 | P26: =$E$10 -> 1252.88
B27: Implied Value Per Share | N27: =N25/N26 -> 234.72162 | O27: =O25/O26 -> 398.4744 | P27: =P25/P26 -> 1435.6976

Sheet FTF_Analysis
B3: Football Field Analysis
C6: OpenLow | D6: Low | E6: OpenHigh | F6: High
B7: Comps | C7: =D7 -> 234.72162 | D7: =Comps_Val!N27 -> 234.72162 | E7: =F7 -> 1435.6976 | F7: =Comps_Val!P27 -> 1435.6976
B8: DCF Bear | C8: =D8 -> 57.429247 | D8: ='Equity Value'!J42 -> 57.429247 | E8: =F8 -> 70.721428 | F8: ='Equity Value'!J46 -> 70.721428
B9: DCF Base | C9: =D9 -> 55.616677 | D9: ='Equity Value'!L42 -> 55.616677 | E9: =F9 -> 65.97422 | F9: ='Equity Value'!L46 -> 65.97422
B10: DCF Bull | C10: =D10 -> 51.732599 | D10: ='Equity Value'!N42 -> 51.732599 | E10: =F10 -> 57.429247 | F10: ='Equity Value'!N46 -> 57.429247
B11: 52W H/L | C11: =D11 -> 390.15 | D11: 390.15 | E11: =F11 -> 491 | F11: 491

Sheet VAR_MCS
B3: VAR
B6: Date | C6: Price | D6: Returns | E6: Sorted Return | F6: Replication | G6: Simulated Returns | I6: Calculation of Value At Risk - ITC
B7: 45989 | C7: 404.25 | F7: 1 | G7: =_xlfn.NORM.INV(RAND(),$L$8,$L$9) -> -0.0066607716
B8: 45988 | C8: 404.3 | D8: =(C8-C7)/C7 -> 0.00012368584 | E8: 0.14268143 | F8: 2 | G8: =_xlfn.NORM.INV(RAND(),$L$8,$L$9) -> 0.012548739 | I8: Mean | L8: =AVERAGE(D8:D4966) -> -0.00029269988
B9: 45987 | C9: 402.3 | D9: =(C9-C8)/C8 -> -0.0049468217 | E9: 0.13739469 | F9: 3 | G9: =_xlfn.NORM.INV(RAND(),$L$8,$L$9) -> 0.0092267335 | I9: Std. Dev. | L9: =_xlfn.STDEV.S(D8:D4966) -> 0.017240358
B10: 45986 | C10: 400.8 | D10: =(C10-C9)/C9 -> -0.0037285608 | E10: 0.12740693 | F10: 4 | G10: =_xlfn.NORM.INV(RAND(),$L$8,$L$9) -> -0.026640746 | I10: Min | L10: =MIN(D8:D4966) -> -0.10010215
B11: 45985 | C11: 403.55 | D11: =(C11-C10)/C10 -> 0.0068612774 | E11: 0.10357909 | F11: 5 | G11: =_xlfn.NORM.INV(RAND(),$L$8,$L$9) -> 0.013994801 | I11: Max | L11: =MAX(D8:D4966) -> 0.14268143
B12: 45982 | C12: 407.85 | D12: =(C12-C11)/C11 -> 0.010655433 | E12: 0.10186757 | F12: 6 | G12: =_xlfn.NORM.INV(RAND(),$L$8,$L$9) -> -0.015415731 | I12: CMP | L12: 404.25
B13: 45981 | C13: 405.45 | D13: =(C13-C12)/C12 -> -0.0058845164 | E13: 0.089539155 | F13: 7 | G13: =_xlfn.NORM.INV(RAND(),$L$8,$L$9) -> 0.0041248885
B14: 45980 | C14: 403.55 | D14: =(C14-C13)/C13 -> -0.0046861512 | E14: 0.085537779 | F14: 8 | G14: =_xlfn.NORM.INV(RAND(),$L$8,$L$9) -> 0.012506868
B15: 45979 | C15: 405.85 | D15: =(C15-C14)/C14 -> 0.0056994177 | E15: 0.078020713 | F15: 9 | G15: =_xlfn.NORM.INV(RAND(),$L$8,$L$9) -> 0.013514592 | I15: Percentile | J15: Confidence | K15: VAR% | L15: Stock Price | M15: VAR(INR)
B16: 45978 | C16: 407.1 | D16: =(C16-C15)/C15 -> 0.0030799556 | E16: 0.073744292 | F16: 10 | G16: =_xlfn.NORM.INV(RAND(),$L$8,$L$9) -> 0.017401755 | I16: 0.05 | J16: =100%-I16 -> 0.95 | K16: =_xlfn.PERCENTILE.INC(G8:G4966,I16) -> -0.028685536 | L16: =$L$12*(100%-K16) -> 415.84613 | M16: =$L$12-L16 -> -11.596128
B17: 45975 | C17: 408.15 | D17: =(C17-C16)/C16 -> 0.0025792189 | E17: 0.07143888 | F17: 11 | G17: =_xlfn.NORM.INV(RAND(),$L$8,$L$9) -> 0.009149706 | I17: 0.01 | J17: =100%-I17 -> 0.99 | K17: =_xlfn.PERCENTILE.INC(G9:G4967,I17) -> -0.039790572 | L17: =$L$12*(100%-K17) -> 420.33534 | M17: =$L$12-L17 -> -16.085339
B18: 45974 | C18: 405.7 | D18: =(C18-C17)/C17 -> -0.0060026951 | E18: 0.068813131 | F18: 12 | G18: =_xlfn.NORM.INV(RAND(),$L$8,$L$9) -> -0.0092220918 | I18: 0.005 | J18: =100%-I18 -> 0.995 | K18: =_xlfn.PERCENTILE.INC(G10:G4968,I18) -> -0.043640913 | L18: =$L$12*(100%-K18) -> 421.89184 | M18: =$L$12-L18 -> -17.641839
B19: 45973 | C19: 407 | D19: =(C19-C18)/C18 -> 0.0032043382 | E19: 0.067849007 | F19: 13 | G19: =_xlfn.NORM.INV(RAND(),$L$8,$L$9) -> -0.0026279722 | I19: 0.1 | J19: =100%-I19 -> 0.9 | K19: =_xlfn.PERCENTILE.INC(G11:G4969,I19) -> -0.022138356 | L19: =$L$12*(100%-K19) -> 413.19943 | M19: =$L$12-L19 -> -8.9494306
B20: 45972 | C20: 406.85 | D20: =(C20-C19)/C19 -> -0.00036855037 | E20: 0.067493393 | F20: 14 | G20: =_xlfn.NORM.INV(RAND(),$L$8,$L$9) -> 0.05230614
B21: 45971 | C21: 405.55 | D21: =(C21-C20)/C20 -> -0.0031952808 | E21: 0.067116542 | F21: 15 | G21: =_xlfn.NORM.INV(RAND(),$L$8,$L$9) -> -0.033311473
B22: 45968 | C22: 404.05 | D22: =(C22-C21)/C21 -> -0.0036986808 | E22: 0.066410204 | F22: 16 | G22: =_xlfn.NORM.INV(RAND(),$L$8,$L$9) -> 0.0053700187
B23: 45967 | C23: 407.5 | D23: =(C23-C22)/C22 -> 0.0085385472 | E23: 0.065982595 | F23: 17 | G23: =_xlfn.NORM.INV(RAND(),$L$8,$L$9) -> 0.0066104814
B24: 45965 | C24: 408.9 | D24: =(C24-C23)/C23 -> 0.0034355828 | E24: 0.06585249 | F24: 18 | G24: =_xlfn.NORM.INV(RAND(),$L$8,$L$9) -> -0.010732545
B25: 45964 | C25: 413.95 | D25: =(C25-C24)/C24 -> 0.012350208 | E25: 0.065512917 | F25: 19 | G25: =_xlfn.NORM.INV(RAND(),$L$8,$L$9) -> -0.020884033
B26: 45961 | C26: 420.35 | D26: =(C26-C25)/C25 -> 0.015460804 | E26: 0.064701171 | F26: 20 | G26: =_xlfn.NORM.INV(RAND(),$L$8,$L$9) -> 0.018195826
B27: 45960 | C27: 418.75 | D27: =(C27-C26)/C26 -> -0.0038063518 | E27: 0.063012171 | F27: 21 | G27: =_xlfn.NORM.INV(RAND(),$L$8,$L$9) -> -0.012809693
B28: 45959 | C28: 421.6 | D28: =(C28-C27)/C27 -> 0.0068059701 | E28: 0.062552407 | F28: 22 | G28: =_xlfn.NORM.INV(RAND(),$L$8,$L$9) -> -0.0013747319
B29: 45958 | C29: 417.9 | D29: =(C29-C28)/C28 -> -0.0087760911 | E29: 0.062544547 | F29: 23 | G29: =_xlfn.NORM.INV(RAND(),$L$8,$L$9) -> 0.018326051
B30: 45957 | C30: 420.65 | D30: =(C30-C29)/C29 -> 0.0065805217 | E30: 0.061556415 | F30: 24 | G30: =_xlfn.NORM.INV(RAND(),$L$8,$L$9) -> -0.035901489
B31: 45954 | C31: 416.8 | D31: =(C31-C30)/C30 -> -0.0091525021 | E31: 0.061325233 | F31: 25 | G31: =_xlfn.NORM.INV(RAND(),$L$8,$L$9) -> 0.0070073312
... B4966: 38685 | C4966: 45.38 | D4966: =(C4966-C4965)/C4965 -> 0.017945267 | E4966: -0.10010215 | F4966: 4960 | G4966: =_xlfn.NORM.INV(RAND(),$L$8,$L$9) -> -0.017140218

Sheet S_VAR
B3: SVAR
B6: Date | C6: Price | D6: Returns | E6: Sorted Return | G6: Calculation of Value At Risk - ITC
B7: 45989 | C7: 404.25
B8: 45988 | C8: 404.3 | D8: =(C8-C7)/C7 -> 0.00012368584 | E8: 0.14268143 | G8: Mean | H8: =AVERAGE(D8:D4966) -> -0.00029269988
B9: 45987 | C9: 402.3 | D9: =(C9-C8)/C8 -> -0.0049468217 | E9: 0.13739469 | G9: Std. Dev. | H9: =_xlfn.STDEV.S(D8:D4966) -> 0.017240358
B10: 45986 | C10: 400.8 | D10: =(C10-C9)/C9 -> -0.0037285608 | E10: 0.12740693 | G10: Min | H10: =MIN(D8:D4966) -> -0.10010215
B11: 45985 | C11: 403.55 | D11: =(C11-C10)/C10 -> 0.0068612774 | E11: 0.10357909 | G11: Max | H11: =MAX(D8:D4966) -> 0.14268143
B12: 45982 | C12: 407.85 | D12: =(C12-C11)/C11 -> 0.010655433 | E12: 0.10186757 | G12: CMP | H12: 404.25
B13: 45981 | C13: 405.45 | D13: =(C13-C12)/C12 -> -0.0058845164 | E13: 0.089539155
B14: 45980 | C14: 403.55 | D14: =(C14-C13)/C13 -> -0.0046861512 | E14: 0.085537779
B15: 45979 | C15: 405.85 | D15: =(C15-C14)/C14 -> 0.0056994177 | E15: 0.078020713 | G15: Percentile | H15: Confidence | I15: VAR% | J15: Stock Price | K15: VAR(INR)
B16: 45978 | C16: 407.1 | D16: =(C16-C15)/C15 -> 0.0030799556 | E16: 0.073744292 | G16: 0.05 | H16: =100%-G16 -> 0.95 | I16: =_xlfn.PERCENTILE.INC(D8:D4966,G16) -> -0.02656591 | J16: =$H$12*(100%-I16) -> 414.98927 | K16: =$H$12-J16 -> -10.739269
B17: 45975 | C17: 408.15 | D17: =(C17-C16)/C16 -> 0.0025792189 | E17: 0.07143888 | G17: 0.01 | H17: =100%-G17 -> 0.99 | I17: =_xlfn.PERCENTILE.INC(D9:D4966,G17) -> -0.047160428 | J17: =$H$12*(100%-I17) -> 423.3146 | K17: =$H$12-J17 -> -19.064603
B18: 45974 | C18: 405.7 | D18: =(C18-C17)/C17 -> -0.0060026951 | E18: 0.068813131 | G18: 0.005 | H18: =100%-G18 -> 0.995 | I18: =_xlfn.PERCENTILE.INC(D10:D4966,G18) -> -0.05733239 | J18: =$H$12*(100%-I18) -> 427.42662 | K18: =$H$12-J18 -> -23.176619
B19: 45973 | C19: 407 | D19: =(C19-C18)/C18 -> 0.0032043382 | E19: 0.067849007 | G19: 0.1 | H19: =100%-G19 -> 0.9 | I19: =_xlfn.PERCENTILE.INC(C9:C4967,G19) -> 60.651 | J19: =$H$12*(100%-I19) -> -24113.917 | K19: =$H$12-J19 -> 24518.167
B20: 45972 | C20: 406.85 | D20: =(C20-C19)/C19 -> -0.00036855037 | E20: 0.067493393
B21: 45971 | C21: 405.55 | D21: =(C21-C20)/C20 -> -0.0031952808 | E21: 0.067116542
B22: 45968 | C22: 404.05 | D22: =(C22-C21)/C21 -> -0.0036986808 | E22: 0.066410204
B23: 45967 | C23: 407.5 | D23: =(C23-C22)/C22 -> 0.0085385472 | E23: 0.065982595
B24: 45965 | C24: 408.9 | D24: =(C24-C23)/C23 -> 0.0034355828 | E24: 0.06585249
B25: 45964 | C25: 413.95 | D25: =(C25-C24)/C24 -> 0.012350208 | E25: 0.065512917
B26: 45961 | C26: 420.35 | D26: =(C26-C25)/C25 -> 0.015460804 | E26: 0.064701171
B27: 45960 | C27: 418.75 | D27: =(C27-C26)/C26 -> -0.0038063518 | E27: 0.063012171
B28: 45959 | C28: 421.6 | D28: =(C28-C27)/C27 -> 0.0068059701 | E28: 0.062552407
B29: 45958 | C29: 417.9 | D29: =(C29-C28)/C28 -> -0.0087760911 | E29: 0.062544547
B30: 45957 | C30: 420.65 | D30: =(C30-C29)/C29 -> 0.0065805217 | E30: 0.061556415
B31: 45954 | C31: 416.8 | D31: =(C31-C30)/C30 -> -0.0091525021 | E31: 0.061325233
... B4966: 38685 | C4966: 45.38 | D4966: =(C4966-C4965)/C4965 -> 0.017945267 | E4966: -0.10010215
